Workbook

Sheet DATOS
B1: LOSAS NERVADAS CASA ROCHA — DATOS DE ENTRADA
B2: Casa habitación de dos niveles · muros de block de 15 cm confinados con castillos K-15x15 y dalas D-15x20 · losa reticular LR-25 en entrepiso (N+3.00) y azotea (N+6.00). Se diseñan las nervaduras secundarias de cada tablero y las nervaduras principales (dalas que quedan sin muro abajo y trabajan como trabe).
B4: CÓMO SE USA: sólo se tocan las celdas AMARILLAS con número AZUL. Todo lo demás está calculado y se rompe si lo escribes encima. La columna «CÓMO SE CALCULA» dice de dónde sale el número y la columna «REFERENCIA» dice qué documento, norma o archivo lo respalda.
B5: ALCANCE: (1) nervaduras secundarias de 32 tableros con el método de coeficientes de la NTC-Concreto para losas apoyadas en su perímetro; (2) dos tableros en volado (F80012 y F80019); (3) 34 nervaduras principales sin muro abajo diseñadas como trabe, incluida la revisión de muros sobre vigas de la NTC-Mampostería; (4) carga de la losa sobre los muros. NO incluye la escalera, el pergolado de vigas VP-15x40, la revisión de los muros por sismo ni la cimentación.
B6: NORMAS: NTC-Concreto 2023, NTC-Criterios y Acciones 2023 y NTC-Mampostería 2023 (CDMX). Cada fórmula se cotejó contra el texto oficial del compendio NTC 2023 y se cita con su numeral y la página impresa de cada norma (p. ej. «6.7.8.1.4, p. 187»). Los criterios que la norma deja al calculista se marcan como «criterio de esta hoja». ACI 318-19 ya no se usa para nada que la NTC 2023 resuelva.
B8: 1. GEOMETRÍA DE LA LOSA NERVADA LR-25 Y RECUBRIMIENTOS
B9: Casetón de poliestireno 60×60×20, nervadura de 10 cm y capa de 5 cm, como dice la nota 2 del plano de cortes. El E2K lo confirma: sus modificadores de la losa LR-25 salen exactos con esta geometría (ver sección 4).
B10: Concepto | C10: Valor | D10: Unidad | E10: Cómo se calcula / de dónde sale | F10: Referencia
B11: a_c — lado del casetón (separación libre entre nervaduras) | C11: 60 | D11: cm | E11: CAPTURA. Debe ser ≤ 80 cm y ≤ claro/6 para que la losa cuente como encasetonada (se revisa en TABLEROS). | F11: 001_PLANO_CROCHA_R3.0.dxf · NOTAS DE CORTES, nota 2 · NTC-Concreto 2023 (CDMX) 6.7.8.1.4, p. 187
B12: h_c — altura del casetón | C12: 20 | D12: cm | E12: CAPTURA. | F12: 001_PLANO_CROCHA_R3.0.dxf · NOTAS DE CORTES, nota 2
B13: b_w — ancho de la nervadura secundaria | C13: 10 | D13: cm | E13: CAPTURA. Mínimo 10 cm en cualquier punto del peralte. | F13: 001_PLANO_CROCHA_R3.0.dxf · nota 2 · NTC-Concreto 2023 (CDMX) 6.7.8.1.2, p. 187
B14: t — espesor de la capa de compresión | C14: 5 | D14: cm | E14: CAPTURA. Mínimo el mayor de a_c/13 y 5 cm; 6 cm si algún tablero tiene claro ≥ 6 m (diafragma). | F14: 001_PLANO_CROCHA_R3.0.dxf · nota 2 · NTC-Concreto 2023 (CDMX) 6.7.8.3.1, p. 188 y 6.8.3.1.2, p. 189
B15: h — peralte total de la losa | C15: =(DATOS!$C$12+DATOS!$C$14) -> 25 | D15: cm | E15: CALCULADA = h_c + t. Debe dar 25: es la LR-25 del modelo. Máximo 3.5·b_w. | F15: 001_EST_CROCHA_R3.2.e2k · SHELLPROP "LR-25" SLABTHICKNESS 0.25 · NTC-Concreto 2023 (CDMX) 6.7.8.1.3, p. 187
B16: s — separación entre ejes de nervaduras | C16: =(DATOS!$C$11+DATOS!$C$13) -> 70 | D16: cm | E16: CALCULADA = a_c + b_w. Es el ancho tributario de cada nervadura. | F16: Geometría
B17: b_p — ancho de la nervadura principal / dala | C17: 15 | D17: cm | E17: CAPTURA. Es el ancho de las dalas D-15x20 del modelo. En PRINCIPALES cada tramo lleva su propia sección propuesta. | F17: 001_EST_CROCHA_R3.2.e2k · FRAMESECTION "002_D-15x20" B 0.15
B18: ¿Se anotan en planos las precauciones de 3.9.2? (casetón de medida fija que garantiza b_w y silletas que fijan el peralte del lecho superior) | C18: SÍ | D18: — | E18: SELECTOR. b_w = 10 cm < 200 mm y, donde el lecho superior queda con d ≤ 200 mm, la norma pide calcular con 20 mm menos, salvo que se tomen precauciones que garanticen la dimensión y se anoten en planos. Si dices NO, la hoja usa b_w − 2 cm en cortante y en flexión negativa, y d − 2 cm en el lecho superior de cada tablero cuyo d sea ≤ 20 cm. | F18: NTC-Concreto 2023 (CDMX) 3.9.1 d) y e) y 3.9.2, p. 74 · 6.3.1.2 b), p. 117 (las nervaduras son vigas)
B19: b_w de cálculo | C19: =IF(DATOS!$C$18="SÍ",DATOS!$C$13,DATOS!$C$13-2) -> 10 | D19: cm | E19: CALCULADA. | F19: NTC-Concreto 2023 (CDMX) 3.9.1 e), p. 74
B20: r — recubrimiento libre en losa y nervaduras secundarias (interior, A1) | C20: 2 | D20: cm | E20: CAPTURA. El mayor de: 15 mm (colocación en losas), 0.75 × 25 mm = 19 mm (corrosión A1 con f'c = 250) y 20 mm (losas y viguetas no expuestas). Manda 20 mm. | F20: NTC-Concreto 2023 (CDMX) 4.13.1.1 y 4.13.2.2 b), p. 83 · Tabla 4.13.3.1 y 4.13.3.2, p. 84 · Tabla 4.14.16.a, p. 85 · Naim — CASA HABITACIÓN, MEMORIA DE CÁLCULO (sep-2024) pág. 13
B21: r_ext — recubrimiento de caras expuestas a la intemperie (barras ≤ No. 5) | C21: 4 | D21: cm | E21: CAPTURA. Se usa en el lecho inferior de los volados (cara exterior), en su lecho superior si queda a la intemperie (selector de abajo) y en el lecho superior de azotea si la pones como expuesta. Con No. 6 o mayor son 5 cm. | F21: NTC-Concreto 2023 (CDMX) Tabla 4.14.16.a, p. 85 · Tabla 4.3.1, p. 76
B22: r_np — recubrimiento libre de las nervaduras principales que trabajan como trabe | C22: 4 | D22: cm | E22: CAPTURA. Para «vigas» no expuestas la tabla pide 40 mm al estribo (las nervaduras ordinarias son «viguetas» y llevan 20 mm). También lo llevan las nervaduras secundarias de los tableros que no cumplen 6.7.8.1.4: esa losa se diseña como losa apoyada en vigas (6.7.8.1.9) y sus nervaduras ya no son «viguetas». | F22: NTC-Concreto 2023 (CDMX) Tabla 4.14.16.a, p. 85 (vigas: refuerzo principal y estribos, 40 mm) · 6.7.8.1.9 y comentario de 6.7.8, p. 188
B23: ¿La cara superior de la azotea queda expuesta directo a la intemperie? | C23: NO | D23: — | E23: SELECTOR. Con relleno, entortado e impermeabilizante encima la hoja la toma como protegida (criterio del Responsable: la norma no lo dice expresamente). Si dices SÍ, el lecho superior de azotea usa r_ext. | F23: NTC-Concreto 2023 (CDMX) 4.3.2 y Tabla 4.3.1, p. 76 · Tabla 4.14.16.a, p. 85
B24: ¿La cara superior de los volados F80012 y F80019 queda expuesta a la intemperie? | C24: SÍ | D24: — | E24: SELECTOR. Los dos volados del N+3.00 quedan fuera de la azotea (sin techo encima): su cara superior recibe la lluvia directa (exposición A2) y su lecho superior lleva r_ext, igual que la malla. Si dices NO, escribe en planos el criterio de protección del Responsable (piso o impermeabilizante que cubra la losa), como en azotea. | F24: NTC-Concreto 2023 (CDMX) Tabla 4.3.1 c), p. 76 · 4.3.2, p. 76 · Tabla 4.14.16.a, p. 85
B25: No. de estribo en la nervadura secundaria (0 = sin estribo) | C25: 0 | D25: — | E25: CAPTURA. Las nervaduras de 10 cm no llevan estribo: la fuerza cortante la toma el concreto con la ec. 5.5.3.2.1 y donde no alcanza se maciza junto al apoyo. Si algún día se ponen, deben ser de varilla o alambre CORRUGADO (no alambrón liso). | F25: NTC-Concreto 2023 (CDMX) 5.5.3.8.1, p. 97 · Tabla 6.3.5.4.1 c), p. 123 · 2.4.2.1.1, p. 43 y Tabla 2.4.2.2.4.a, p. 46
B26: No. de varilla preferida — lecho INFERIOR de nervaduras secundarias | C26: 4 | D26: — | E26: CAPTURA. Mínimo No. 4: toda nervadura lleva al menos 1 No. 4 abajo y 1 No. 4 arriba, corridas. Si con el máximo de varillas no alcanza, la hoja sube sola al siguiente número. | F26: NTC-Concreto 2023 (CDMX) 6.7.6.1.3, p. 175
B27: No. de varilla preferida — lecho SUPERIOR de nervaduras secundarias | C27: 4 | D27: — | E27: CAPTURA. Misma regla: una varilla del lecho superior es corrida y las demás son bastones. | F27: NTC-Concreto 2023 (CDMX) 6.7.6.1.3, p. 175
B28: Máximo de varillas por lecho en una nervadura de 10 cm | C28: 2 | D28: pzas | E28: CAPTURA. La hoja revisa además que quepan con la separación libre mínima. | F28: Geometría · NTC-Concreto 2023 (CDMX) 14.2.1, p. 347
B29: Mínimo de varillas por lecho y por nervadura | C29: 1 | D29: pzas | E29: CAPTURA. 1 No. 4 corrida. Si As colocada < 4/3 de la requerida, la hoja pide 2 varillas y As mín de viga. | F29: NTC-Concreto 2023 (CDMX) 6.7.6.1.3, p. 175 · 6.3.5.1.1 y 6.3.5.1.3, p. 122
B30: Tamaño máximo del agregado grueso | C30: 1.27 | D30: cm | E30: CAPTURA. 1/2". No más de 2/3 del recubrimiento ni de la separación libre entre barras: con r = 2 cm el máximo es 1.33 cm, así que el de 3/4" NO sirve en esta losa. | F30: NTC-Concreto 2023 (CDMX) 2.2.5.2.1, p. 32
B31: ¿El agregado cabe? (≤ 2/3 de r y de la separación libre) | C31: =IF(DATOS!$C$30<=2/3*MIN(DATOS!$C$20,MAX(2.5,1.5*DATOS!$C$30)),"CUMPLE","NO CUMPLE — usa agregado más chico") -> CUMPLE | D31: — | E31: CALCULADA. | F31: NTC-Concreto 2023 (CDMX) 2.2.5.2.1, p. 32
B32: Separación libre mínima entre varillas | C32: =MAX(2.5,1.5*DATOS!$C$30) -> 2.5 | D32: cm | E32: CALCULADA = el mayor de 25 mm, d_b y 1.5·TMA (d_b se revisa barra por barra). | F32: NTC-Concreto 2023 (CDMX) 14.2.1, p. 347
B33: Ancho libre para varillas dentro de la nervadura secundaria | C33: =DATOS!$C$13-2*DATOS!$C$20-2*IF(DATOS!$C$25=0,0,INDEX(TABLAS!$C$52:$C$58,MATCH(DATOS!$C$25,TABLAS!$B$52:$B$58,0))) -> 6 | D33: cm | E33: CALCULADA = b_w − 2r − 2·estribo con r = 2 cm (tableros que cumplen 6.7.8.1.4). Informativa: TABLEROS revisa renglón por renglón con su r; con r = 4 cm (tableros que no cumplen 6.7.8.1.4 y volados) quedan 2 cm y cabe una sola varilla de d_b ≤ 2 cm. | F33: Geometría
B34: Malla electrosoldada en la capa de compresión | C34: 6x6-6/6 | D34: — | E34: SELECTOR. La lista está en TABLAS. Debe cubrir: contracción y temperatura (0.0018·t), cortante de diafragma (0.0025·t), flexión de la capa con 1 000 kg entre nervaduras, acero mínimo alrededor de la carga concentrada (6.7.6.1.2) y caber con 2 cm de recubrimiento por cara (r_ext = 4 cm donde la cara superior queda expuesta: azotea o volados según los selectores de arriba) (NERVADURA sección 11). Con capa de 5 cm ninguna malla cumple a la vez diafragma, punzonamiento y acero mínimo junto a la carga (RESUMEN, decisión 3). Con capa de 5 cm la 6x6-6/6 es la que mejor cumple; la 6x6-4/4 ya no cabe con su recubrimiento. | F34: NTC-Concreto 2023 (CDMX) 13.8.2.1.1, p. 345 · 6.7.8.1.8, p. 188 · 6.8.6.4, p. 196 · 6.7.6.1.2, p. 175 · Tabla 6.7.4.2.2.3, p. 171 · Tabla 4.14.16.a, p. 85 · Naim — CASA HABITACIÓN, PLANOS EST-01 a EST-06 · EST-03 (dice 6x6-10/10)
B35: Ø del alambre de la malla | C35: =INDEX(TABLAS!$C$63:$C$66,MATCH(DATOS!$C$34,TABLAS!$B$63:$B$66,0))/10 -> 0.488 | D35: cm | E35: CALCULADA. La malla va con r = 2 cm a la cara superior y las varillas superiores de las nervaduras pasan DEBAJO de ella: su d pierde 2·Ø. | F35: TABLAS sección C
B37: 2. MATERIALES
B38: Concepto | C38: Valor | D38: Unidad | E38: Cómo se calcula / de dónde sale | F38: Referencia
B39: f'c — resistencia del concreto | C39: 250 | D39: kg/cm² | E39: CAPTURA. Concreto Clase 1A (250 ≤ f'c < 400). Es también el mínimo para estructuras de ductilidad baja y para exposición A1, A2 y B1. | F39: 001_EST_CROCHA_R3.2.e2k · MATERIAL "Concreto f'c=250kg/cm2. Clase 1A" · NTC-Concreto 2023 (CDMX) 2.2.2 a), p. 30 · Tabla 2.2.6.3, p. 33 · 4.4.1.1 y 4.5.2 a), p. 78
B40: fy — fluencia de la varilla corrugada | C40: 4200 | D40: kg/cm² | E40: CAPTURA. Grado 42, NMX-B-506. Es también el máximo para estribos. | F40: 001_EST_CROCHA_R3.2.e2k · MATERIAL "Fy=4200" · NTC-Concreto 2023 (CDMX) Tabla 2.4.2.1.2.a, p. 43 y Tabla 2.4.2.2.4.a, p. 46
B41: fy de la malla electrosoldada | C41: 5000 | D41: kg/cm² | E41: CAPTURA. Alambre de malla NMX-B-290; en contracción, temperatura y flexión de losas se permite hasta 7 000. En 2023 la cuantía de temperatura ya no depende de fy. | F41: NTC-Concreto 2023 (CDMX) 2.4.2.1.6 y 2.4.2.1.7, p. 44 · Tabla 2.4.2.2.4.a renglón «Otras», p. 46 · plano EST Casa Yépez (Naim), nota 1.2
B42: fy de los estribos de nervaduras principales | C42: 4200 | D42: kg/cm² | E42: CAPTURA. Varilla corrugada; para cortante el máximo es 4 200. | F42: NTC-Concreto 2023 (CDMX) 5.5.2.4.3, p. 94 · Tabla 2.4.2.2.4.a, p. 46
B43: γc — peso volumétrico del concreto reforzado | C43: 2.44 | D43: t/m³ | E43: CAPTURA. El mismo del modelo (valor máximo probable). | F43: 001_EST_CROCHA_R3.2.e2k · WEIGHTPERVOLUME 2440 · NTC-Criterios y Acciones 2023 (CDMX) 5.1.1.2, p. 9
B44: γ del casetón de poliestireno | C44: 0.015 | D44: t/m³ | E44: CAPTURA. Poliestireno expandido. El modelo no lo cuenta; aquí sí. | F44: 001_PLANO_CROCHA_R3.0.dxf · simbología del corte «CASETÓN DE POLIESTIRENO»
B45: Ec — módulo de elasticidad | C45: =14000*SQRT(DATOS!$C$39) -> 221359.44 | D45: kg/cm² | E45: CALCULADA = 14 000·√f'c: Clase 1A con agregado grueso CALIZO (con basalto sería 11 000·√f'c). Especificarlo así en planos. | F45: 001_EST_CROCHA_R3.2.e2k · E 2.2135944E+09 kgf/m² · NTC-Concreto 2023 (CDMX) Tabla 2.2.1, p. 31 y 2.2.8.4, p. 34
B46: Es — módulo de elasticidad del acero | C46: 2000000 | D46: kg/cm² | E46: CAPTURA. | F46: NTC-Concreto 2023 (CDMX) 2.4.2.2.2, p. 45
B47: f̄f — módulo de rotura medio (para el momento de agrietamiento) | C47: =2*SQRT(DATOS!$C$39) -> 31.622777 | D47: kg/cm² | E47: CALCULADA = 2·√f'c (Clase 1A). Se usa sólo en las flechas. | F47: NTC-Concreto 2023 (CDMX) Tabla 2.2.1, p. 31 · 13.4.3.3, p. 338
B48: f''c — esfuerzo del bloque equivalente | C48: =0.85*DATOS!$C$39 -> 212.5 | D48: kg/cm² | E48: CALCULADA = 0.85·f'c (sin límite de f'c en 2023). | F48: NTC-Concreto 2023 (CDMX) 3.6.1 e), p. 68 · Naim — CASA HABITACIÓN, MEMORIA DE CÁLCULO (sep-2024) (su MR sale con 0.85 f'c)
B49: β1 — profundidad del bloque | C49: =IF(DATOS!$C$39<=300,0.85,MAX(0.65,1.05-DATOS!$C$39/1400)) -> 0.85 | D49: — | E49: CALCULADA. 0.85 hasta f'c = 300 kg/cm². | F49: NTC-Concreto 2023 (CDMX) ec. 3.6.1, p. 68
B50: f'm — resistencia de diseño a compresión del block | C50: 50 | D50: kg/cm² | E50: CAPTURA. Block de concreto f'p = 100 kg/cm² con mortero tipo I. La casa es estructura Tipo I (tiene muros desplantados sobre vigas): no se pueden usar los valores por omisión del Cap. 12. | F50: 001_EST_CROCHA_R3.2.e2k · MATERIAL "f'm=50kg/cm2 (Mortero Tipo I, f'p=100kg/cm2)" · NTC-Mampostería 2023 (CDMX) Tabla 2.8.1.4.1, p. 24 · 1.6.1 c), p. 15 · 1.6.2, p. 16
B51: Em — módulo de elasticidad de la mampostería | C51: =800*DATOS!$C$50 -> 40000 | D51: kg/cm² | E51: CALCULADA = 800·f'm (block de concreto, cargas de corta duración). El E2K trae 40 000. | F51: NTC-Mampostería 2023 (CDMX) ec. 2.8.5.4.a, p. 27 · 001_EST_CROCHA_R3.2.e2k E 4.0E+08 kgf/m²
B53: 3. FACTORES DE CARGA Y DE RESISTENCIA
B54: Concepto | C54: Valor | D54: Unidad | E54: Cómo se calcula / de dónde sale | F54: Referencia
B55: FC_CM — factor de carga muerta | C55: 1.3 | D55: — | E55: CAPTURA. Grupo B, cargas permanentes + variables (Grupo A sería 1.5). | F55: NTC-Criterios y Acciones 2023 (CDMX) 3.4.1 a), p. 7 (combinación 2.3.1 a), p. 5) · Naim — CASA HABITACIÓN, MEMORIA DE CÁLCULO (sep-2024) pág. 8 · 001_EST_CROCHA_R3.2.e2k COMBO "Comb2.2"
B56: FC_CV — factor de carga viva | C56: 1.5 | D56: — | E56: CAPTURA. Grupo B (Grupo A sería 1.7). | F56: NTC-Criterios y Acciones 2023 (CDMX) 3.4.1 a), p. 7
B57: FC_acc — factor de carga en combinaciones con acciones accidentales | C57: 1.1 | D57: — | E57: CAPTURA. Se usa en la combinación de granizo en azotea: 1.1·(CM + W_g), sin carga viva. | F57: NTC-Criterios y Acciones 2023 (CDMX) 3.4.1 b), p. 7 · 7.3.1.3, p. 17
B58: F_R — flexión | C58: 0.9 | D58: — | E58: CAPTURA. Sólo vale si la sección es controlada por tensión (ε_t ≥ 0.005). Losas y vigas sin presfuerzo tienen que serlo, así que la hoja limita el acero para garantizarlo (p_max, sección 4). | F58: NTC-Concreto 2023 (CDMX) Tabla 3.8.2.1 a) y Tabla 3.8.2.2, p. 70 · 3.8.2.4, p. 71 · 6.3.3.3.1, p. 121 · 6.7.3.3.1, p. 169
B59: F_R — cortante | C59: 0.75 | D59: — | E59: CAPTURA. | F59: NTC-Concreto 2023 (CDMX) Tabla 3.8.2.1 b), p. 70
B60: F_R — mampostería en compresión | C60: 0.6 | D60: — | E60: CAPTURA. Para muros sobre vigas (esfuerzo en los extremos del muro). | F60: NTC-Mampostería 2023 (CDMX) 4.1.6.2, p. 39 · 4.1.18.2.2, p. 44
B61: Fracción de la cuantía balanceada que se permite | C61: 0.9 | D61: — | E61: CAPTURA. Tope de vigas de ductilidad baja; en la práctica manda antes ε_t ≥ 0.005. | F61: NTC-Concreto 2023 (CDMX) 6.3.5.2.1, p. 122
B62: Incremento de V_cR en losas encasetonadas | C62: 1.1 | D62: — | E62: CAPTURA. Sólo se aplica en los tableros que cumplen las limitaciones geométricas de losa encasetonada (claro ≥ 6·a_c en las dos direcciones); en los demás vale 1.0. | F62: NTC-Concreto 2023 (CDMX) 6.7.8.1.5, p. 187 · 6.7.8.1.9, p. 188
B63: Incremento de cortante con bordes continuos y discontinuos | C63: 1.15 | D63: — | E63: CAPTURA. Parte de la fórmula de cortante de losas perimetralmente apoyadas de la NTC 2017, que la 2023 ya no trae; se conserva como «método reconocido». | F63: NTC-Concreto 2023 (CDMX) 3.4.1.1, p. 64 (métodos reconocidos) · NTC-Concreto 2017
B64: Relación M⁻/M⁺ para nervaduras principales apoyadas | C64: 0.667 | D64: — | E64: CAPTURA. Equivale a wL²/12 contra wL²/8: arriba se arma para empotramiento, abajo para apoyo simple (envolvente conservadora). | F64: Criterio de esta hoja — no viene de norma
B66: 4. PROPIEDADES DE LA SECCIÓN NERVADA — Y COMPROBACIÓN CONTRA EL MODELO
B67: Si estos dos cocientes coinciden con los del E2K, la hoja y el modelo están hablando de la misma losa.
B68: Concepto | C68: Valor | D68: Unidad | E68: Cómo se calcula / de dónde sale | F68: Referencia
B69: Volumen de concreto por m² de losa | C69: =(DATOS!$C$15/100-(DATOS!$C$11/100)^2*(DATOS!$C$12/100)/(DATOS!$C$16/100)^2) -> 0.10306122 | D69: m³/m² | E69: CALCULADA = h − a_c²·h_c / s² (lo macizo menos los huecos de casetón). | F69: Geometría
B70: Peso propio geométrico de la losa nervada | C70: =(DATOS!$C$69*DATOS!$C$43+(DATOS!$C$11/100)^2*(DATOS!$C$12/100)/(DATOS!$C$16/100)^2*DATOS!$C$44)*1000 -> 253.67347 | D70: kg/m² | E70: CALCULADA = V·γc + casetón·γ_pol. A esto se le suma el incremento de la sección 5. | F70: Geometría
B71: Peso propio que trae el modelo | C71: =1503.75*0.25*0.6688 -> 251.427 | D71: kg/m² | E71: CALCULADA = 1503.75 kg/m³ × 0.25 m × WMOD 0.6688. Sin casetón: por eso sale 2 kg/m² abajo. | F71: 001_EST_CROCHA_R3.2.e2k · MATERIAL "LR-25 equiv" 1503.75 kg/m³ y SHELLPROP "LR-25" WMOD 0.6688
B72: A_T — área de la sección T de una nervadura | C72: =DATOS!$C$16*DATOS!$C$14+DATOS!$C$13*DATOS!$C$12 -> 550 | D72: cm² | E72: CALCULADA = s·t + b_w·h_c. | F72: Geometría
B73: ȳ — centroide medido desde arriba | C73: =(DATOS!$C$16*DATOS!$C$14*DATOS!$C$14/2+DATOS!$C$13*DATOS!$C$12*(DATOS!$C$14+DATOS!$C$12/2))/DATOS!$C$72 -> 7.0454545 | D73: cm | E73: CALCULADA. | F73: Geometría
B74: I_T — inercia bruta de una nervadura con su patín | C74: =DATOS!$C$16*DATOS!$C$14^3/12+DATOS!$C$16*DATOS!$C$14*(DATOS!$C$73-DATOS!$C$14/2)^2+DATOS!$C$13*DATOS!$C$12^3/12+DATOS!$C$13*DATOS!$C$12*(DATOS!$C$14+DATOS!$C$12/2-DATOS!$C$73)^2 -> 27282.197 | D74: cm⁴ | E74: CALCULADA (Steiner). | F74: Geometría
B75: I_T / I de losa maciza del mismo peralte | C75: =DATOS!$C$74/(DATOS!$C$16*DATOS!$C$15^3/12) -> 0.29932468 | D75: — | E75: CALCULADA. Debe coincidir con el modificador de inercia del modelo. | F75: Geometría
B76: Modificador de inercia en el modelo | C76: 0.29914984 | D76: — | E76: DATO del modelo. Si difiere de la fila de arriba, la losa del modelo no es la misma. | F76: 001_EST_CROCHA_R3.2.e2k · SHELLPROP "LR-25" M11MOD 0.29914984
B77: h_eq — espesor de losa maciza con la misma inercia | C77: =(12*DATOS!$C$74/DATOS!$C$16)^(1/3) -> 16.723256 | D77: cm | E77: CALCULADA = ∛(12·I_T / s). La norma no da espesor mínimo especial para encasetonadas: la hoja compara h_eq (no los 25 cm) contra el espesor mínimo, del lado seguro. | F77: Criterio de esta hoja · NTC-Concreto 2023 (CDMX) 6.7.3.1, p. 167–168
B78: d inferior típico (varilla preferida) | C78: =DATOS!$C$15-DATOS!$C$20-IF(DATOS!$C$25=0,0,INDEX(TABLAS!$C$52:$C$58,MATCH(DATOS!$C$25,TABLAS!$B$52:$B$58,0)))-INDEX(TABLAS!$C$52:$C$58,MATCH(DATOS!$C$26,TABLAS!$B$52:$B$58,0))/2 -> 22.365 | D78: cm | E78: CALCULADA = h − r − estribo − d_b/2. En TABLEROS se recalcula con la varilla real, la dirección (la del claro largo va encima de la del corto) y el recubrimiento de cada tablero. | F78: Geometría
B79: d superior típico (varilla preferida) | C79: =DATOS!$C$15-DATOS!$C$20-2*DATOS!$C$35-IF(DATOS!$C$25=0,0,INDEX(TABLAS!$C$52:$C$58,MATCH(DATOS!$C$25,TABLAS!$B$52:$B$58,0)))-INDEX(TABLAS!$C$52:$C$58,MATCH(DATOS!$C$27,TABLAS!$B$52:$B$58,0))/2 -> 21.389 | D79: cm | E79: CALCULADA = h − r − 2·Ø malla − estribo − d_b/2 (la varilla va bajo la malla). La reducción de 20 mm de 3.9.1 d) (d ≤ 200 mm sin la precaución anotada) se revisa renglón por renglón en TABLEROS: con r = 4 cm o con barras más gruesas d baja de 20 cm. | F79: Geometría · NTC-Concreto 2023 (CDMX) 3.9.1 d) y 3.9.2, p. 74
B80: p_b — cuantía balanceada | C80: =DATOS!$C$48/DATOS!$C$40*6000*DATOS!$C$49/(DATOS!$C$40+6000) -> 0.025297619 | D80: — | E80: CALCULADA = (f''c/fy)·6000β1/(fy + 6000). | F80: NTC-Concreto 2023 (CDMX) ec. 5.2.1.3.1, p. 88
B81: p para ε_t = 0.005 (sección controlada por tensión) | C81: =0.375*DATOS!$C$49*DATOS!$C$48/DATOS!$C$40 -> 0.016127232 | D81: — | E81: CALCULADA: c ≤ 0.375·d ⇒ a ≤ 0.375·β1·d ⇒ p ≤ 0.375·β1·f''c/fy, sobre el ancho que trabaja a compresión. | F81: NTC-Concreto 2023 (CDMX) Tabla 3.8.2.2, p. 70 · 3.8.2.4, p. 71 (ε_ty = 0.002) · 6.3.3.3.1, p. 121
B82: p_max — cuantía máxima | C82: =MIN(DATOS!$C$61*DATOS!$C$80,DATOS!$C$81) -> 0.016127232 | D82: — | E82: CALCULADA = el menor de 0.90·p_b y el de ε_t = 0.005 (manda el segundo). | F82: NTC-Concreto 2023 (CDMX) 6.3.5.2.1, p. 122 · 6.3.3.3.1, p. 121 · 6.7.3.3.1, p. 169
B83: p_min — cuantía mínima por flexión (vigas y nervaduras) | C83: =MAX(0.8*SQRT(DATOS!$C$39),14)/DATOS!$C$40 -> 0.0033333333 | D83: — | E83: CALCULADA = el mayor de 0.80·√f'c/fy y 14/fy, sobre b_w·d. Con f'c = 250 manda 14/fy = 0.00333. Se dispensa si la As colocada es ≥ 4/3 de la requerida. | F83: NTC-Concreto 2023 (CDMX) 6.3.5.1.2 y 6.3.5.1.3, p. 122
B84: As mín de losa por nervadura = 0.0018·A_g | C84: =0.0018*(DATOS!$C$16*DATOS!$C$14+DATOS!$C$13*DATOS!$C$12) -> 0.99 | D84: cm² | E84: CALCULADA. La cubre de sobra la No. 4 corrida (1.27 cm²). | F84: NTC-Concreto 2023 (CDMX) 6.7.6.1.1, p. 175
B86: 5. CARGAS VIVAS UNITARIAS E INCREMENTOS DE CARGA MUERTA
B87: Valores de la tabla de cargas vivas de la NTC. Son los mismos que trae el modelo en cada tablero y los que usa Naim. En TABLEROS cada tablero dice si es HABITACIÓN o AZOTEA y de ahí toma W_m (diseño) y W (flechas diferidas).
B88: Concepto | C88: Valor | D88: Unidad | E88: Cómo se calcula / de dónde sale | F88: Referencia
B89: Habitación — W_m (máxima, para diseño por gravedad) | C89: 190 | D89: kg/m² | E89: CAPTURA. | F89: NTC-Criterios y Acciones 2023 (CDMX) Tabla 6.1.2.2 inciso a), p. 11 · 6.1.2.1 a), p. 10 · Naim — CASA HABITACIÓN, MEMORIA DE CÁLCULO (sep-2024) pág. 5 · 001_EST_CROCHA_R3.2.e2k AREALOAD "Carga Viva Máxima" 190
B90: Habitación — W_a (instantánea) | C90: 100 | D90: kg/m² | E90: CAPTURA. Informativa: no entra en el diseño por gravedad. | F90: NTC-Criterios y Acciones 2023 (CDMX) Tabla 6.1.2.2 a), p. 11 · 6.1.2.1 b), p. 10
B91: Habitación — W (media, para flechas diferidas) | C91: 80 | D91: kg/m² | E91: CAPTURA. | F91: NTC-Criterios y Acciones 2023 (CDMX) Tabla 6.1.2.2 a), p. 11 · 6.1.2.1 c), p. 10
B92: Azotea con pendiente ≤ 5% — W_m | C92: 100 | D92: kg/m² | E92: CAPTURA. | F92: NTC-Criterios y Acciones 2023 (CDMX) Tabla 6.1.2.2 inciso h), p. 11 · Naim — CASA HABITACIÓN, MEMORIA DE CÁLCULO (sep-2024) pág. 6 · 001_EST_CROCHA_R3.2.e2k AREALOAD 100
B93: Azotea con pendiente ≤ 5% — W_a | C93: 70 | D93: kg/m² | E93: CAPTURA. Informativa. | F93: NTC-Criterios y Acciones 2023 (CDMX) Tabla 6.1.2.2 h), p. 11
B94: Azotea con pendiente ≤ 5% — W (media) | C94: 15 | D94: kg/m² | E94: CAPTURA. | F94: NTC-Criterios y Acciones 2023 (CDMX) Tabla 6.1.2.2 h), p. 11
B95: Incremento del peso propio por losa colada en el lugar | C95: 20 | D95: kg/m² | E95: CAPTURA. Se suma al peso propio geométrico en todos los tableros. | F95: NTC-Criterios y Acciones 2023 (CDMX) 5.1.2.1, p. 9
B96: Incremento por capa de mortero sobre la losa (pegapiso, firme o entortado) | C96: 20 | D96: kg/m² | E96: CAPTURA. Si la sobrecarga del modelo ya trae la «carga adicional 0.04 t/m²» de Naim, pon aquí 0 y en la fila de arriba 0 para no contarla dos veces. No se aplica donde la carga muerta es favorable. | F96: NTC-Criterios y Acciones 2023 (CDMX) 5.1.2.1 y 5.1.2.2, p. 9 · Naim — CASA HABITACIÓN, MEMORIA DE CÁLCULO (sep-2024) pág. 5 (carga adicional 0.04 t/m²)
B97: W_g — granizo en azotea (Grupo B, pendiente < 5°) | C97: =900*0.125*1 -> 112.5 | D97: kg/m² | E97: CALCULADA = 900·H_s·C_s con H_s = 0.125 m y C_s = 1.0. Va con FC = 1.1 y sin carga viva. | F97: NTC-Criterios y Acciones 2023 (CDMX) ec. 7.3.2.1, p. 17 · Tablas 7.3.2.2 y 7.3.2.3, p. 18
B99: 6. MUROS DE PLANTA ALTA QUE QUEDAN SOBRE LA LOSA
B100: Los muros del primer nivel que no tienen muro abajo descargan en las nervaduras principales, con su propio peso y con la azotea que cargan. Su peso por metro sale de aquí.
B101: Concepto | C101: Valor | D101: Unidad | E101: Cómo se calcula / de dónde sale | F101: Referencia
B102: γm — peso volumétrico del block | C102: 1.9 | D102: t/m³ | E102: CAPTURA. El mismo del modelo. | F102: 001_EST_CROCHA_R3.2.e2k · MATERIAL "f'm=50kg/cm2..." WEIGHTPERVOLUME 1900
B103: t_m — espesor del muro | C103: 0.15 | D103: m | E103: CAPTURA. Mínimo 120 mm en estructuras Tipo I. | F103: 001_EST_CROCHA_R3.2.e2k · SHELLPROP "Muro 15 cm" · NTC-Mampostería 2023 (CDMX) 6.1.3, p. 60
B104: Altura de entrepiso | C104: 3 | D104: m | E104: CAPTURA. | F104: 001_EST_CROCHA_R3.2.e2k · STORY "N+6.00" HEIGHT 3
B105: Altura del muro sobre la losa | C105: =DATOS!$C$104-DATOS!$C$15/100 -> 2.75 | D105: m | E105: CALCULADA = entrepiso − h. H/t = 18 ≤ 25. | F105: Geometría · NTC-Mampostería 2023 (CDMX) 6.1.3, p. 60
B106: Aplanados (las dos caras) | C106: 0.06 | D106: t/m² | E106: CAPTURA. 2 cm por cara con mortero de 1.5 t/m³. | F106: Práctica de ingeniería
B107: w_muro — peso del muro por metro lineal (servicio) | C107: =(DATOS!$C$102*DATOS!$C$103+DATOS!$C$106)*DATOS!$C$105 -> 0.94875 | D107: t/m | E107: CALCULADA = (γm·t + aplanados)·altura. Los muros divisorios se cuantifican aparte de la carga viva. | F107: Geometría · NTC-Criterios y Acciones 2023 (CDMX) 6.1.1.2 y 6.1.1.3, p. 10
...

Sheet APOYOS
B1: APOYOS — DÓNDE SE APOYA CADA TABLERO, CUÁLES SON LAS NERVADURAS PRINCIPALES Y DÓNDE HAY VACÍOS
B2: Se cruzó el modelo (muros, castillos y dalas por nivel) con el plano arquitectónico (capa 004_Vacios y escalera) y con el DXF de áreas tributarias. Los muros que cargan la losa N+3.00 son los de planta baja; los que cargan la azotea N+6.00 son los del primer nivel.
B4: A. LO QUE SE ENCONTRÓ
B5: 1) AZOTEA (N+6.00): casi todos los bordes caen sobre muros del primer nivel. Sólo 4 tramos cortos quedan sin muro (bordes de los tragaluces, la ventana del área de tendido y el borde del vacío de la escalera) y todos llegan a muros en sus dos extremos.
B6: 2) ENTREPISO (N+3.00): en planta baja sólo hay muros en los ejes A y J y en dos núcleos (baño junto a la cochera y servicios atrás). La cochera mide 8.70 m libres y la sala tiene el vacío de doble altura: muchas dalas del modelo quedan sin muro abajo y en realidad son NERVADURAS PRINCIPALES que trabajan como trabe.
B7: 3) En el modelo tal cual, varias de esas principales rematan en nudos que no tienen nada abajo: las esquinas de la cochera (x = 4.327 y = 1.919; x = 5.923 y = 2.921), las esquinas del vacío (x = 4.327 con y = 7.871 y 14.021), la esquina de la escalera (F-8) y la esquina C-10. Así quedan en volado de 4 a 8 m: con 25 cm de peralte NO funcionan.
B8: 4) En esos mismos nudos el primer nivel SÍ tiene castillo, pero no baja a planta baja (31 castillos sin continuidad, lista F). La propuesta de esta hoja es bajar 7 de ellos a cimentación y agregar uno nuevo en la llegada de la escalera (lista B). Con eso todas las principales quedan apoyadas en sus dos extremos.
B9: 5) F80012 (área de tendido, fuera del eje A) y F80019 (terraza entre los ejes 14 y 15) son VOLADOS de 2.00 m. Sus orillas libres llevan nervadura de borde, no trabe. La de F80019 recibe el barandal de 333.7 kg/m que trae el modelo.
B10: 6) VACÍOS: doble altura de la sala (4.17 × 6.00 m), cubo de la escalera curva, vacío sobre la escalera en azotea y tres tragaluces de 0.30 m en azotea. F80028 y F80029 son prácticamente hueco (quedan 0.60 y 0.53 m² de losa): se tratan como marco de hueco, no como tablero.
B11: 7) En azotea, F80032 y F80010 están en el modelo como «Slab1» (maciza de 20 cm, concreto 4000 psi), no como LR-25. El plano dice losa reticular: aquí se diseñan como LR-25 y conviene corregirlos en ETABS.
B12: 8) F2 (azotea, sobre la terraza del frente) no tiene cargas en el modelo. Aquí se le pone la misma sobrecarga que al tablero vecino F80023 (270 kg/m²): REVISAR.
B14: B. CASTILLOS QUE SE PROPONE BAJAR A CIMENTACIÓN — TÚ DECIDES
B15: Si pones NO, los tramos que dependen de ese castillo pasan a volado en PRINCIPALES y la hoja te dice si así aguantan. OJO: si rechazas un castillo que parte un tramo en dos (C2, C4), junta a mano los dos renglones de PRINCIPALES en uno solo con el claro completo.
B16: Castillo | C16: ¿Se acepta? | D16: x (m) | E16: y (m) | F16: Ejes | G16: Tramos que dependen | H16: Por qué
B17: C1 — PROPUESTO | C17: SÍ | D17: 4.327 | E17: 1.919 | F17: x=4.327-2 | G17: NP-01, NP-20 | H17: Esquina libre al frente de la cochera: ahí rematan las nervaduras de y = 1.919 y de x = 4.327. Ya hay castillo en el primer nivel.
B18: C2 — PROPUESTO | C18: SÍ | D18: 4.327 | E18: 2.921 | F18: x=4.327-3 | G18: NP-02, NP-03, NP-20, NP-21 | H18: Cochera: cruce de x = 4.327 con y = 2.921, bajo esquina de muro del primer nivel. Ya hay castillo en el primer nivel.
B19: C3 — PROPUESTO | C19: SÍ | D19: 5.923 | E19: 2.921 | F19: G-3 | G19: NP-03, NP-29 | H19: Esquina libre de la cochera (lado pickup): ahí rematan y = 2.921 y el eje G. Ya hay castillo en el primer nivel.
B20: C4 — PROPUESTO | C20: SÍ | D20: 4.327 | E20: 7.871 | F20: x=4.327-7 | G20: NP-06, NP-22, NP-23 | H20: Esquina sur del vacío de doble altura: recibe la nervadura del eje 7. Ya hay castillo en el primer nivel.
B21: C5 — PROPUESTO | C21: SÍ | D21: 4.327 | E21: 14.021 | F21: x=4.327-y=14.021 | G21: NP-10, NP-23 | H21: Esquina norte del vacío de doble altura: sin él x = 4.327 queda en volado de 8 m. Ya hay castillo en el primer nivel.
B22: C6 — PROPUESTO | C22: SÍ | D22: 5.422 | E22: 9.95 | F22: F-8 | G22: NP-08, NP-26 | H22: Esquina escalera/cocina (F-8): recibe la nervadura del eje F que carga muro de planta alta. Ya hay castillo en el primer nivel.
B23: C7 — PROPUESTO | C23: SÍ | D23: 5.441 | E23: 8.91 | F23: F-y=8.910 | G23: NP-07, NP-25 | H23: Llegada de la escalera: amarra el anillo x = 5.44 / y = 8.91. NO hay castillo arriba: es propuesta nueva, revisar con arquitectura.
B24: C8 — PROPUESTO | C24: SÍ | D24: 3.427 | E24: 15.846 | F24: C-y=15.846 | G24: NP-12, NP-19 | H24: Esquina C-10 (arq.): ahí remata y = 15.846 que carga muro de planta alta. Ya hay castillo en el primer nivel.
B26: C. BORDES DE CADA TABLERO — APOYO Y CONTINUIDAD
B27: «Apoyo» dice qué hay bajo el borde: MURO, una NERVADURA PRINCIPAL (ver PRINCIPALES) o nada (LIBRE). «Continuidad» dice si del otro lado sigue losa: con eso TABLEROS escoge el caso de la tabla de coeficientes. La continuidad es AMARILLA: la puedes cambiar si el criterio automático no te convence.
B28: Tablero | C28: Lado | D28: Largo (m) | E28: % sobre muro | F28: Apoyo | G28: Continuidad | H28: Del otro lado | I28: Vacío o hueco junto
B29: F80001 N+3.00 | C29: inferior | D29: 4.327 | E29: 0.005 | F29: NERV. PRINCIPAL NP-01 | G29: DISCONTINUO
B30: F80001 N+3.00 | C30: superior | D30: 4.327 | E30: 0.005 | F30: NERV. PRINCIPAL NP-02 | G30: CONTINUO | H30: F80003
B31: F80001 N+3.00 | C31: izquierdo | D31: 1.002 | E31: 1 | F31: MURO | G31: DISCONTINUO
B32: F80001 N+3.00 | C32: derecho | D32: 1.002 | E32: 0 | F32: NERV. PRINCIPAL NP-20 | G32: DISCONTINUO
B33: F80003 N+3.00 | C33: inferior | D33: 4.327 | E33: 0.005 | F33: NERV. PRINCIPAL NP-02 | G33: CONTINUO | H33: F80001
B34: F80003 N+3.00 | C34: superior | D34: 4.327 | E34: 0.333 | F34: MURO | G34: CONTINUO | H34: F80005, F80006
B35: F80003 N+3.00 | C35: izquierdo | D35: 3.025 | E35: 1 | F35: MURO | G35: DISCONTINUO | H35: F80005
B36: F80003 N+3.00 | C36: derecho | D36: 3.025 | E36: 0.007 | F36: NERV. PRINCIPAL NP-21 | G36: CONTINUO | H36: F80004
B37: F80004 N+3.00 | C37: inferior | D37: 1.596 | E37: 0 | F37: NERV. PRINCIPAL NP-03 | G37: DISCONTINUO
B38: F80004 N+3.00 | C38: superior | D38: 1.596 | E38: 1 | F38: MURO | G38: CONTINUO | H38: F80008
B39: F80004 N+3.00 | C39: izquierdo | D39: 3.025 | E39: 0.007 | F39: NERV. PRINCIPAL NP-21 | G39: CONTINUO | H39: F80003
B40: F80004 N+3.00 | C40: derecho | D40: 3.025 | E40: 0.007 | F40: NERV. PRINCIPAL NP-29 | G40: DISCONTINUO
B41: F80005 N+3.00 | C41: inferior | D41: 2.925 | E41: 1 | F41: MURO | G41: CONTINUO | H41: F80003
B42: F80005 N+3.00 | C42: superior | D42: 2.925 | E42: 1 | F42: MURO | G42: CONTINUO | H42: F80007
B43: F80005 N+3.00 | C43: izquierdo | D43: 1.602 | E43: 1 | F43: MURO | G43: DISCONTINUO
B44: F80005 N+3.00 | C44: derecho | D44: 1.602 | E44: 1 | F44: MURO | G44: CONTINUO | H44: F80003, F80006
B45: F80006 N+3.00 | C45: inferior | D45: 1.402 | E45: 1 | F45: MURO | G45: CONTINUO | H45: F80003
B46: F80006 N+3.00 | C46: superior | D46: 1.402 | E46: 0.014 | F46: NERV. PRINCIPAL NP-04 | G46: CONTINUO | H46: F80007
B47: F80006 N+3.00 | C47: izquierdo | D47: 1.002 | E47: 1 | F47: MURO | G47: CONTINUO | H47: F80005
B48: F80006 N+3.00 | C48: derecho | D48: 1.002 | E48: 0.02 | F48: NERV. PRINCIPAL NP-22 | G48: CONTINUO | H48: F80008
B49: F80007 N+3.00 | C49: inferior | D49: 4.327 | E49: 0.681 | F49: NERV. PRINCIPAL NP-04 | G49: CONTINUO | H49: F80005, F80006
B50: F80007 N+3.00 | C50: superior | D50: 4.327 | E50: 0.005 | F50: NERV. PRINCIPAL NP-06 | G50: DISCONTINUO | I50: Vacío doble altura (sala)
B51: F80007 N+3.00 | C51: izquierdo | D51: 0.923 | E51: 1 | F51: MURO | G51: DISCONTINUO
B52: F80007 N+3.00 | C52: derecho | D52: 0.923 | E52: 0 | F52: NERV. PRINCIPAL NP-22 | G52: CONTINUO | H52: F80008
B53: F80008 N+3.00 | C53: inferior | D53: 4.321 | E53: 0.674 | F53: NERV. PRINCIPAL NP-10 / sigue el pasillo | G53: DISCONTINUO | H53: F80003, F80004, F80006
B54: F80008 N+3.00 | C54: superior | D54: 4.321 | E54: 0.566 | F54: NERV. PRINCIPAL NP-15 | G54: CONTINUO | H54: F80013, F80015, F80016, F80017, F80018
B55: F80008 N+3.00 | C55: izquierdo | D55: 11.5 | E55: 0.002 | F55: NERV. PRINCIPAL NP-18, NP-19 | G55: CONTINUO | H55: F80006, F80007, F80010, F80014 | I55: Vacío doble altura (sala)
B56: F80008 N+3.00 | C56: derecho | D56: 11.5 | E56: 0.009 | F56: MURO / NERV. PRINCIPAL NP-26 | G56: CONTINUO | H56: F80009, F80011, F80015 | I56: Escalera curva (cubo)
B57: F80009 N+3.00 | C57: inferior | D57: 3.428 | E57: 0.211 | F57: NERV. PRINCIPAL NP-08 | G57: CONTINUO | H57: F80008 | I57: Escalera curva (cubo)
B58: F80009 N+3.00 | C58: superior | D58: 3.428 | E58: 1 | F58: MURO | G58: CONTINUO | H58: F80011
B59: F80009 N+3.00 | C59: izquierdo | D59: 5.497 | E59: 0.004 | F59: NERV. PRINCIPAL NP-26 | G59: CONTINUO | H59: F80008 | I59: Escalera curva (cubo)
B60: F80009 N+3.00 | C60: derecho | D60: 5.497 | E60: 1 | F60: MURO | G60: DISCONTINUO | I60: Escalera curva (cubo)
B61: F80010 N+3.00 | C61: inferior | D61: 3.427 | E61: 0.006 | F61: NERV. PRINCIPAL NP-10 | G61: DISCONTINUO | I61: Vacío doble altura (sala)
B62: F80010 N+3.00 | C62: superior | D62: 3.427 | E62: 0.006 | F62: NERV. PRINCIPAL NP-12 | G62: CONTINUO | H62: F80008, F80014
B63: F80010 N+3.00 | C63: izquierdo | D63: 1.825 | E63: 1 | F63: MURO | G63: CONTINUO | H63: F80012
B64: F80010 N+3.00 | C64: derecho | D64: 1.825 | E64: 0 | F64: NERV. PRINCIPAL NP-19 | G64: CONTINUO | H64: F80008
B65: F80011 N+3.00 | C65: inferior | D65: 3.428 | E65: 1 | F65: MURO | G65: CONTINUO | H65: F80009
B66: F80011 N+3.00 | C66: superior | D66: 3.428 | E66: 0.006 | F66: NERV. PRINCIPAL NP-13 | G66: CONTINUO | H66: F80013, F80015
B67: F80011 N+3.00 | C67: izquierdo | D67: 0.399 | E67: 0.05 | F67: NERV. PRINCIPAL NP-27 | G67: CONTINUO | H67: F80013
B68: F80011 N+3.00 | C68: derecho | D68: 0.399 | E68: 1 | F68: MURO | G68: DISCONTINUO
B69: F80012 N+3.00 | C69: inferior | D69: 2 | E69: 0.01 | F69: NERV. PRINCIPAL NP-09 | G69: DISCONTINUO
B70: F80012 N+3.00 | C70: superior | D70: 2 | E70: 0.01 | F70: NERV. PRINCIPAL NP-14 | G70: DISCONTINUO
B71: F80012 N+3.00 | C71: izquierdo | D71: 3.425 | E71: 0 | F71: NERV. PRINCIPAL NP-17 | G71: DISCONTINUO
B72: F80012 N+3.00 | C72: derecho | D72: 3.425 | E72: 1 | F72: MURO | G72: CONTINUO | H72: F80010, F80014
B73: F80013 N+3.00 | C73: inferior | D73: 0.897 | E73: 1 | F73: MURO | G73: CONTINUO | H73: F80008, F80009, F80011
B74: F80013 N+3.00 | C74: superior | D74: 0.897 | E74: 1 | F74: MURO | G74: CONTINUO | H74: F80018
B75: F80013 N+3.00 | C75: izquierdo | D75: 1.999 | E75: 1 | F75: MURO | G75: CONTINUO | H75: F80008
B76: F80013 N+3.00 | C76: derecho | D76: 1.999 | E76: 0.02 | F76: NERV. PRINCIPAL NP-28 | G76: CONTINUO | H76: F80011, F80015
B77: F80014 N+3.00 | C77: inferior | D77: 3.029 | E77: 0.007 | F77: NERV. PRINCIPAL NP-12 | G77: CONTINUO | H77: F80010
B78: F80014 N+3.00 | C78: superior | D78: 3.029 | E78: 0.007 | F78: NERV. PRINCIPAL NP-15 | G78: CONTINUO | H78: F80016
B79: F80014 N+3.00 | C79: izquierdo | D79: 1.6 | E79: 1 | F79: MURO | G79: CONTINUO | H79: F80012
B80: F80014 N+3.00 | C80: derecho | D80: 1.6 | E80: 0 | F80: NERV. PRINCIPAL NP-18 | G80: CONTINUO | H80: F80008
B81: F80015 N+3.00 | C81: inferior | D81: 3.028 | E81: 0.007 | F81: NERV. PRINCIPAL NP-13 | G81: CONTINUO | H81: F80011
B82: F80015 N+3.00 | C82: superior | D82: 3.028 | E82: 1 | F82: MURO | G82: CONTINUO | H82: F80018
B83: F80015 N+3.00 | C83: izquierdo | D83: 1.6 | E83: 0.012 | F83: NERV. PRINCIPAL NP-28 | G83: CONTINUO | H83: F80013
B84: F80015 N+3.00 | C84: derecho | D84: 1.6 | E84: 1 | F84: MURO | G84: DISCONTINUO
B85: F80016 N+3.00 | C85: inferior | D85: 4.426 | E85: 0.005 | F85: NERV. PRINCIPAL NP-15 | G85: CONTINUO | H85: F80008, F80014
B86: F80016 N+3.00 | C86: superior | D86: 4.426 | E86: 1 | F86: MURO | G86: CONTINUO | H86: F80019
B87: F80016 N+3.00 | C87: izquierdo | D87: 4 | E87: 1 | F87: MURO | G87: DISCONTINUO
B88: F80016 N+3.00 | C88: derecho | D88: 4 | E88: 0.005 | F88: NERV. PRINCIPAL NP-24 | G88: CONTINUO | H88: F80017
B89: F80017 N+3.00 | C89: inferior | D89: 0.499 | E89: 0.04 | F89: NERV. PRINCIPAL NP-15 | G89: CONTINUO | H89: F80008
B90: F80017 N+3.00 | C90: superior | D90: 0.499 | E90: 1 | F90: MURO | G90: CONTINUO | H90: F80019
B91: F80017 N+3.00 | C91: izquierdo | D91: 4 | E91: 0.005 | F91: NERV. PRINCIPAL NP-24 | G91: CONTINUO | H91: F80016
B92: F80017 N+3.00 | C92: derecho | D92: 4 | E92: 1 | F92: MURO | G92: CONTINUO | H92: F80018
B93: F80018 N+3.00 | C93: inferior | D93: 3.925 | E93: 1 | F93: MURO | G93: CONTINUO | H93: F80013, F80015
B94: F80018 N+3.00 | C94: superior | D94: 3.925 | E94: 1 | F94: MURO | G94: CONTINUO | H94: F80019, F80020
B95: F80018 N+3.00 | C95: izquierdo | D95: 4 | E95: 1 | F95: MURO | G95: CONTINUO | H95: F80017
B96: F80018 N+3.00 | C96: derecho | D96: 4 | E96: 1 | F96: MURO | G96: DISCONTINUO
B97: F80019 N+3.00 | C97: inferior | D97: 7.25 | E97: 1 | F97: MURO | G97: CONTINUO | H97: F80016, F80017, F80018
B98: F80019 N+3.00 | C98: superior | D98: 7.25 | E98: 0.006 | F98: NERV. PRINCIPAL NP-16 | G98: DISCONTINUO
B99: F80019 N+3.00 | C99: izquierdo | D99: 2 | E99: 1 | F99: MURO | G99: CONTINUO | H99: F80021
B100: F80019 N+3.00 | C100: derecho | D100: 2 | E100: 1 | F100: MURO | G100: CONTINUO | H100: F80020
B101: F80020 N+3.00 | C101: inferior | D101: 1.6 | E101: 1 | F101: MURO | G101: CONTINUO | H101: F80018
B102: F80020 N+3.00 | C102: superior | D102: 1.6 | E102: 1 | F102: MURO | G102: DISCONTINUO
B103: F80020 N+3.00 | C103: izquierdo | D103: 2.925 | E103: 1 | F103: MURO | G103: CONTINUO | H103: F80019
...

Sheet CARGAS
B1: CARGAS — PESO PROPIO, SOBRECARGA, CARGA VIVA Y CARGAS LINEALES
B2: La sobrecarga de cada tablero se toma del modelo (varía de 160 a 315 kg/m²) y vive en TABLEROS. Aquí está el desglose de referencia de Naim, los incrementos de la NTC y las cargas lineales del modelo.
B4: 1. PESO PROPIO DE LA LOSA NERVADA
B5: Concepto | C5: Valor | D5: Unidad | E5: Cómo se calcula / de dónde sale | F5: Referencia
B6: Peso propio geométrico LR-25 (con casetón) | C6: =DATOS!$C$70 -> 253.67347 | D6: kg/m² | E6: Enlazado a DATOS sección 4. | F6: DATOS
B7: Incremento por losa colada en el lugar | C7: =DATOS!$C$95 -> 20 | D7: kg/m² | E7: DATOS sección 5. | F7: NTC-Criterios y Acciones 2023 (CDMX) 5.1.2.1, p. 9
B8: Incremento por capa de mortero | C8: =DATOS!$C$96 -> 20 | D8: kg/m² | E8: DATOS sección 5. No se aplica donde la carga muerta es favorable (p. ej. el claro que equilibra un volado). | F8: NTC-Criterios y Acciones 2023 (CDMX) 5.1.2.1 y 5.1.2.2, p. 9
B9: Peso propio de diseño | C9: =DATOS!$C$70+DATOS!$C$95+DATOS!$C$96 -> 293.67347 | D9: kg/m² | E9: Suma de los tres renglones. Es el que usa TABLEROS. | F9: NTC-Criterios y Acciones 2023 (CDMX) 5.1.2.1, p. 9
B10: Peso propio que trae el modelo | C10: =DATOS!$C$71 -> 251.427 | D10: kg/m² | E10: Enlazado a DATOS sección 4. | F10: 001_EST_CROCHA_R3.2.e2k
B12: 2. SOBRECARGA MUERTA — DESGLOSE DE REFERENCIA (NAIM)
B13: Sólo de referencia: no entra en ningún cálculo. Sirve para juzgar si las sobrecargas del modelo (columna SCM de TABLEROS) son razonables. Ojo: la «carga adicional 0.04 t/m²» de Naim es el mismo incremento de 40 kg/m² de 5.1.2.1.
B14: Concepto | C14: Carga | D14: Unidad | E14: Cómo se obtiene | F14: Referencia
B15: Entrepiso — relleno 8 cm | C15: 0.13 | D15: t/m² | E15: 1.60 t/m³ × 0.08 m | F15: Naim — CASA HABITACIÓN, MEMORIA DE CÁLCULO (sep-2024) · pág. 5, CARGAS DE ENTREPISO
B16: Entrepiso — piso 3 cm | C16: 0.06 | D16: t/m² | E16: 2.00 t/m³ × 0.03 m | F16: Naim — CASA HABITACIÓN, MEMORIA DE CÁLCULO (sep-2024) · pág. 5, CARGAS DE ENTREPISO
B17: Entrepiso — pegapiso 3 cm | C17: 0.05 | D17: t/m² | E17: 1.50 t/m³ × 0.03 m | F17: Naim — CASA HABITACIÓN, MEMORIA DE CÁLCULO (sep-2024) · pág. 5, CARGAS DE ENTREPISO
B18: Entrepiso — yeso 3 cm | C18: 0.05 | D18: t/m² | E18: 1.50 t/m³ × 0.03 m | F18: Naim — CASA HABITACIÓN, MEMORIA DE CÁLCULO (sep-2024) · pág. 5, CARGAS DE ENTREPISO
B19: Entrepiso — instalaciones | C19: 0.02 | D19: t/m² | E19: — | F19: Naim — CASA HABITACIÓN, MEMORIA DE CÁLCULO (sep-2024) · pág. 5, CARGAS DE ENTREPISO
B20: Entrepiso — carga adicional | C20: 0.04 | D20: t/m² | E20: — | F20: Naim — CASA HABITACIÓN, MEMORIA DE CÁLCULO (sep-2024) · pág. 5, CARGAS DE ENTREPISO
B21: Entrepiso — TOTAL según Naim | C21: 0.33 | D21: t/m² | E21: Naim reporta 0.33 (subtotal 0.29 + carga adicional 0.04); la suma de los renglones de arriba da 0.35 (0.338 sin redondear). | F21: Naim — CASA HABITACIÓN, MEMORIA DE CÁLCULO (sep-2024) · pág. 5
B22: Azotea — relleno 10 cm | C22: 0.16 | D22: t/m² | E22: 1.60 t/m³ × 0.10 m | F22: Naim — CASA HABITACIÓN, MEMORIA DE CÁLCULO (sep-2024) · pág. 5, CARGAS DE AZOTEA
B23: Azotea — yeso 3 cm | C23: 0.05 | D23: t/m² | E23: 1.50 t/m³ × 0.03 m | F23: Naim — CASA HABITACIÓN, MEMORIA DE CÁLCULO (sep-2024) · pág. 5, CARGAS DE AZOTEA
B24: Azotea — impermeabilizante | C24: 0.03 | D24: t/m² | E24: 1.40 t/m³ × 0.02 m | F24: Naim — CASA HABITACIÓN, MEMORIA DE CÁLCULO (sep-2024) · pág. 5, CARGAS DE AZOTEA
B25: Azotea — instalaciones | C25: 0.02 | D25: t/m² | E25: — | F25: Naim — CASA HABITACIÓN, MEMORIA DE CÁLCULO (sep-2024) · pág. 5, CARGAS DE AZOTEA
B26: Azotea — carga adicional | C26: 0.04 | D26: t/m² | E26: — | F26: Naim — CASA HABITACIÓN, MEMORIA DE CÁLCULO (sep-2024) · pág. 5, CARGAS DE AZOTEA
B27: Azotea — TOTAL según Naim | C27: 0.29 | D27: t/m² | E27: Naim reporta 0.29 (la suma de renglones da 0.30). | F27: Naim — CASA HABITACIÓN, MEMORIA DE CÁLCULO (sep-2024) · pág. 5
B28: Sobrecarga del modelo — mínima y máxima en entrepiso | C28: =TEXT(MIN(TABLEROS!$T$9:$T$28),"0")&" a "&TEXT(MAX(TABLEROS!$T$9:$T$28),"0") -> 160 a 270 | D28: kg/m² | E28: Rango de la columna SCM de TABLEROS para N+3.00. | F28: 001_EST_CROCHA_R3.2.e2k · AREALOAD "Sobrecarga"
B29: Sobrecarga del modelo — mínima y máxima en azotea | C29: =TEXT(MIN(TABLEROS!$T$29:$T$40),"0")&" a "&TEXT(MAX(TABLEROS!$T$29:$T$40),"0") -> 270 a 315 | D29: kg/m² | E29: Rango de la columna SCM de TABLEROS para N+6.00. | F29: 001_EST_CROCHA_R3.2.e2k · AREALOAD "Sobrecarga"
B31: 3. COMBINACIONES DE DISEÑO
B32: Concepto | C32: Valor | D32: Unidad | E32: Cómo se calcula / de dónde sale | F32: Referencia
B33: Carga muerta CM = PP de diseño + SCM | C33: por tablero | D33: — | E33: TABLEROS, columna CM. | F33: NTC-Criterios y Acciones 2023 (CDMX) 5.1.2.1, p. 9
B34: w_u gravitacional = 1.3·CM + 1.5·W_m | C34: por tablero | D34: — | E34: TABLEROS, columna w_u. Grupo B. W_m uniforme en todos los tableros a la vez: se permite porque W_m ≤ 0.75·CM. | F34: NTC-Criterios y Acciones 2023 (CDMX) 2.3.1 a), p. 5 y 3.4.1 a), p. 7 · NTC-Concreto 2023 (CDMX) 3.3.2.2.3, p. 50
B35: w_u con granizo (sólo azotea) = 1.1·(CM + W_g) | C35: =DATOS!$C$57*(CARGAS!$C$9+270+DATOS!$C$97) -> 743.79082 | D35: kg/m² | E35: Ejemplo con SCM = 270 kg/m². En TABLEROS se toma el mayor de las dos combinaciones; en azotea manda la gravitacional. | F35: NTC-Criterios y Acciones 2023 (CDMX) 3.4.1 b), p. 7 · 7.3.1.1 y 7.3.1.3, p. 17
B36: w de servicio = CM + W_m | C36: por tablero | D36: — | E36: TABLEROS, columna w serv. Factor de carga 1.0. | F36: NTC-Criterios y Acciones 2023 (CDMX) 3.3.2, p. 6 y 3.4.1 d), p. 7
B37: Carga sostenida para flechas diferidas = CM + W | C37: por tramo | D37: — | E37: PRINCIPALES, revisión de flechas. | F37: NTC-Criterios y Acciones 2023 (CDMX) 6.1.2.1 c), p. 10
B39: 4. CARGAS CONCENTRADAS QUE PIDE LA NORMA
B40: Concepto | C40: Valor | D40: Unidad | E40: Cómo se calcula / de dónde sale | F40: Referencia
B41: Capa entre nervaduras: carga concentrada mínima | C41: 1000 | D41: kg | E41: En un área de 10 × 10 cm en la posición más desfavorable. Se revisa en NERVADURA sección 11 (flexión, punzonamiento y acero mínimo de la capa). | F41: NTC-Concreto 2023 (CDMX) 6.7.8.1.6, p. 187 · 6.7.8.1.8, p. 188
B42: Habitación: carga en lugar de W_m cuando sea más desfavorable | C42: 500 | D42: kg | E42: En 50 × 50 cm. La cubre la revisión de 1 000 kg en 10 × 10 cm. | F42: NTC-Criterios y Acciones 2023 (CDMX) Tabla 6.1.2.2 nota [1], p. 11
B43: Azotea: carga concentrada en la posición más crítica | C43: 100 | D43: kg | E43: La cubre la revisión de 1 000 kg. Tinacos y equipos van aparte y deben indicarse en planos. | F43: NTC-Criterios y Acciones 2023 (CDMX) Tabla 6.1.2.2 notas [7] y [8], p. 12
B44: Carga transitoria al colar la azotea sobre el entrepiso | C44: 150 | D44: kg/m² | E44: Más el peso del colado y la cimbra, y 150 kg concentrados. Indicar en planos el apuntalamiento a planta baja mientras se cuela N+6.00. | F44: NTC-Criterios y Acciones 2023 (CDMX) 6.1.3.1, p. 10
B45: Temperatura en la estructura | C45: se omite | D45: — | E45: Dimensiones < 30 m, miembros de ejes rectos y azotea protegida (relleno + impermeabilizante; la norma pide «al menos un enladrillado»: confirmarlo). | F45: NTC-Criterios y Acciones 2023 (CDMX) 6.2.3.1, p. 13
B47: 5. CARGAS LINEALES QUE TRAE EL MODELO (BARANDALES, MUROS BAJOS, PRETILES Y ESCALERA)
B48: Se suman a la nervadura principal sobre la que caen (PRINCIPALES, columnas SCM y CV lineal). Las de 333.7 kg/m en las orillas de F80012 y F80019 entran como carga en la orilla del volado.
B49: Viga · nivel · caso | C49: w | D49: Unidad | E49: Dónde (de – a) y largo cargado | F49: Fuente
B50: B50063 · N+3.00 · Sobrecarga | C50: 206 | D50: kg/m | E50: de (4.327, 5.946) a (5.298, 5.946) · 0.97 m | F50: 001_EST_CROCHA_R3.2.e2k · FRAME OBJECT LOADS
B51: B50066 · N+3.00 · Sobrecarga | C51: 50 | D51: kg/m | E51: de (5.460, 6.948) a (5.923, 6.948) · 0.46 m | F51: 001_EST_CROCHA_R3.2.e2k · FRAME OBJECT LOADS
B52: B50069 · N+3.00 · Sobrecarga | C52: 50 | D52: kg/m | E52: de (5.460, 8.910) a (7.350, 8.910) · 1.89 m | F52: 001_EST_CROCHA_R3.2.e2k · FRAME OBJECT LOADS
B53: B50069 · N+3.00 · Sobrecarga | C53: 144 | D53: kg/m | E53: de (5.495, 8.910) a (7.350, 8.910) · 1.85 m | F53: 001_EST_CROCHA_R3.2.e2k · FRAME OBJECT LOADS
B54: B50069 · N+3.00 · Carga Viva Máxima | C54: 35.1 | D54: kg/m | E54: de (5.495, 8.910) a (7.350, 8.910) · 1.85 m | F54: 001_EST_CROCHA_R3.2.e2k · FRAME OBJECT LOADS
B55: B50069 · N+3.00 · Carga Viva Instantanea | C55: 18.5 | D55: kg/m | E55: de (5.495, 8.910) a (7.350, 8.910) · 1.85 m | F55: 001_EST_CROCHA_R3.2.e2k · FRAME OBJECT LOADS
B56: B50069 · N+3.00 · Carga Viva Media | C56: 14.8 | D56: kg/m | E56: de (5.495, 8.910) a (7.350, 8.910) · 1.85 m | F56: 001_EST_CROCHA_R3.2.e2k · FRAME OBJECT LOADS
B57: B50071 · N+3.00 · Sobrecarga | C57: 333.7 | D57: kg/m | E57: de (-2.000, 14.021) a (0.000, 14.021) · 2.00 m | F57: 001_EST_CROCHA_R3.2.e2k · FRAME OBJECT LOADS
B58: B50079 · N+3.00 · Sobrecarga | C58: 294 | D58: kg/m | E58: de (-0.000, 21.446) a (5.275, 21.446) · 5.28 m | F58: 001_EST_CROCHA_R3.2.e2k · FRAME OBJECT LOADS
B59: B50079 · N+3.00 · Sobrecarga | C59: 500 | D59: kg/m | E59: de (5.275, 21.446) a (7.250, 21.446) · 1.98 m | F59: 001_EST_CROCHA_R3.2.e2k · FRAME OBJECT LOADS
B60: B50079 · N+3.00 · Sobrecarga | C60: 206 | D60: kg/m | E60: de (7.250, 21.446) a (8.146, 21.446) · 0.90 m | F60: 001_EST_CROCHA_R3.2.e2k · FRAME OBJECT LOADS
B61: B50084 · N+3.00 · Sobrecarga | C61: 333.7 | D61: kg/m | E61: de (7.250, 24.371) a (7.479, 24.371) · 0.23 m | F61: 001_EST_CROCHA_R3.2.e2k · FRAME OBJECT LOADS
... B99: B29 · N+6.00 · Sobrecarga | C99: 101 | D99: kg/m | E99: de (4.327, 2.921) a (5.923, 2.921) · 1.60 m | F99: 001_EST_CROCHA_R3.2.e2k · FRAME OBJECT LOADS

Sheet TABLEROS
B1: TABLEROS — NERVADURAS SECUNDARIAS DE CADA TABLERO (MÉTODO DE COEFICIENTES, NTC-CONCRETO 2023 TABLA 3.4.2.1)
B2: Un renglón por tablero. Momentos = coeficiente × 10⁻⁴ × w_u × a1² por metro; por nervadura × s. Abajo trabaja la sección T con el patín efectivo de la Tabla 5.2.1.4.2; arriba sólo la nervadura (b_w de cálculo). Toda nervadura lleva al menos 1 No. 4 corrida abajo y 1 No. 4 corrida arriba (6.7.6.1.3); arriba, las demás varillas son bastones. Lo AMARILLO se puede cambiar. El detalle paso a paso está en NERVADURA.
B3: ESTADO: «CUMPLE» = flexión, ε_t ≥ 0.005, cortante, peralte, capa y apoyos bien. «VER PRINCIPALES» = el tablero pasa pero alguna nervadura principal que lo recibe no. «MACIZAR n hilera(s)» = quitar casetones junto al apoyo por cortante. «6.7.8: NO» = la separación libre a_c pasa de 1/6 del claro corto (6.7.8.1.4): la losa se diseña como losa apoyada en vigas (6.7.8.1.9): nervaduras con recubrimiento de viga (r_np) y sin el ×1.1 de V_cR. «3.4.2.1 c)» = los M⁻ del borde común con un vecino difieren más de 50 % del menor: los coeficientes quedan fuera de su campo y conviene confirmar con el modelo; aun así se distribuye 2/3 del desequilibrio (3.4.3.1).
B6: TABLERO | F6: GEOMETRÍA | T6: CARGAS (kg/m²) | Z6: CASO DE LA TABLA | AF6: COEFICIENTES ×10⁻⁴ (Tabla 3.4.2.1, interpolados en m) | AN6: DISTRIBUCIÓN CON LOS VECINOS (3.4.3.1) Y 3.4.2.1 c) | BA6: MOMENTOS POR NERVADURA (t·m) | BF6: INFERIOR — CLARO CORTO | BN6: SUPERIOR — CLARO CORTO | BV6: INFERIOR — CLARO LARGO | CD6: SUPERIOR — CLARO LARGO | CL6: CORTANTE | CP6: PERALTE Y CAPA | CU6: DETALLE Y RESUMEN
B7: Tablero | C7: Nivel | D7: Modo | E7: Destino | F7: Lx | G7: Ly | H7: a_x usado | I7: a_y usado | J7: a1 corto | K7: a2 largo | L7: m = a1/a2 | M7: Corto ‖ | N7: Claro libre corto | O7: Claro libre largo | P7: Patín b_f corto | Q7: Patín b_f largo | R7: r inferior | S7: r superior | T7: SCM | U7: CV W_m | V7: PP diseño | W7: CM | X7: w serv. | Y7: w_u | Z7: Bordes discont. | AA7: … cortos | AB7: … largos | AC7: Caso automático | AD7: Forzar caso | AE7: Caso usado | AF7: col. m | AG7: interp. | AH7: M⁻ cont. corto | AI7: M⁻ cont. largo | AJ7: M⁻ disc. corto | AK7: M⁻ disc. largo | AL7: M⁺ corto | AM7: M⁺ largo | AN7: M⁻ borde inferior por nerv. | AO7: M⁻ borde superior por nerv. | AP7: M⁻ borde izquierdo por nerv. | AQ7: M⁻ borde derecho por nerv. | AR7: Rigidez d³/a1 ‖X | AS7: Rigidez d³/a1 ‖Y | AT7: M⁻ corto que deja el vecino | AU7: M⁻ largo que deja el vecino | AV7: ΔM⁺ corto por distribución | AW7: ΔM⁺ largo por distribución | AX7: ΔV por volado vecino | AY7: Vecinos con M⁻ > 50 % distinto | AZ7: 3.4.2.1 c) | BA7: Carga en orilla de volado | BB7: M⁺ corto | BC7: M⁻ corto | BD7: M⁺ largo | BE7: M⁻ largo | BF7: d para As (var. preferida) | BG7: As req. | BH7: Var. No. | BI7: Pzas | BJ7: d | BK7: M_R | BL7: Mu/M_R | BM7: ε_t | BN7: d para As (var. preferida) | BO7: As req. | BP7: Var. No. | BQ7: Pzas | BR7: d | BS7: M_R | BT7: Mu/M_R | BU7: ε_t | BV7: d para As (var. preferida) | BW7: As req. | BX7: Var. No. | BY7: Pzas | BZ7: d | CA7: M_R | CB7: Mu/M_R | CC7: ε_t | CD7: d para As (var. preferida) | CE7: As req. | CF7: Var. No. | CG7: Pzas | CH7: d | CI7: M_R | CJ7: Mu/M_R | CK7: ε_t | CL7: 6.7.8 cumple | CM7: V_u por nerv. | CN7: V_cR | CO7: Estado | CP7: α_fm | CQ7: h mín. Tabla 6.7.3.1.2 / volado L/8 | CR7: h_eq / h | CS7: Estado | CT7: Capa (diafragma) | CU7: Bastón ‖ corto desde paño | CV7: Bastón ‖ largo desde paño | CW7: Casetones ‖X | CX7: Casetones ‖Y | CY7: Apoyos | CZ7: ESTADO | DA7: Nota
F8: m | G8: m | H8: m | I8: m | J8: m | K8: m | N8: cm | O8: cm | P8: cm | Q8: cm | R8: cm | S8: cm | T8: kg/m² | U8: kg/m² | V8: kg/m² | W8: kg/m² | X8: kg/m² | Y8: kg/m² | AN8: t·m | AO8: t·m | AP8: t·m | AQ8: t·m | AR8: cm² | AS8: cm² | AT8: t·m | AU8: t·m | AV8: t·m | AW8: t·m | AX8: t | BA8: kg/m (serv.) | BB8: t·m | BC8: t·m | BD8: t·m | BE8: t·m | BF8: cm | BG8: cm² | BJ8: cm | BK8: t·m | BM8: ≥ 0.005 | BN8: cm | BO8: cm² | BR8: cm | BS8: t·m | BU8: ≥ 0.005 | BV8: cm | BW8: cm² | BZ8: cm | CA8: t·m | CC8: ≥ 0.005 | CD8: cm | CE8: cm² | CH8: cm | CI8: t·m | CK8: ≥ 0.005 | CM8: t | CN8: t | CQ8: cm | CR8: cm | CU8: cm | CV8: cm
B9: F80001 N+3.00 | C9: N+3.00 | D9: PERIMETRAL | E9: HABITACIÓN | F9: 4.327 | G9: 1.002 | H9: 4.327 | I9: 1.002 | J9: =MIN(H9,I9) -> 1.002 | K9: =MAX(H9,I9) -> 4.327 | L9: =IF(K9>0,J9/K9,0) -> 0.23156922 | M9: =IF(H9<=I9,"X","Y") -> Y | N9: =MAX(0,J9*100-IF(D9="VOLADO",DATOS!$C$17/2,DATOS!$C$17)) -> 85.2 | O9: =MAX(0,K9*100-DATOS!$C$17) -> 417.7 | P9: =MIN(DATOS!$C$16,DATOS!$C$13+2*MIN(8*DATOS!$C$14,DATOS!$C$11/2,N9/8)) -> 31.3 | Q9: =MIN(DATOS!$C$16,DATOS!$C$13+2*MIN(8*DATOS!$C$14,DATOS!$C$11/2,O9/8)) -> 70 | R9: =IF(D9="VOLADO",DATOS!$C$21,IF(CL9="NO",DATOS!$C$22,DATOS!$C$20)) -> 4 | S9: =IF(OR(AND(C9="N+6.00",DATOS!$C$23="SÍ"),AND(D9="VOLADO",DATOS!$C$24="SÍ")),DATOS!$C$21,IF(CL9="NO",DATOS!$C$22,DATOS!$C$20)) -> 4 | T9: 185 | U9: =IF(E9="HABITACIÓN",DATOS!$C$89,DATOS!$C$92) -> 190 | V9: =CARGAS!$C$9 -> 293.67347 | W9: =V9+T9 -> 478.67347 | X9: =W9+U9 -> 668.67347 | Y9: =MAX(DATOS!$C$55*W9+DATOS!$C$56*U9,IF(E9="AZOTEA",DATOS!$C$57*(W9+DATOS!$C$97),0)) -> 907.27551 | Z9: =(APOYOS!$G$29="DISCONTINUO")+(APOYOS!$G$30="DISCONTINUO")+(APOYOS!$G$31="DISCONTINUO")+(APOYOS!$G$32="DISCONTINUO") -> 3 | AA9: =IF(M9="X",(APOYOS!$G$29="DISCONTINUO")+(APOYOS!$G$30="DISCONTINUO"),(APOYOS!$G$31="DISCONTINUO")+(APOYOS!$G$32="DISCONTINUO")) -> 2 | AB9: =Z9-AA9 -> 1 | AC9: =IF(Z9=0,"INTERIOR",IF(Z9=1,IF(AA9=1,"BORDE-CORTO","BORDE-LARGO"),IF(Z9=2,IF(AA9=1,"ESQUINA",IF(AA9=2,"EXTREMO-LARGO","EXTREMO-CORTO")),IF(Z9=3,IF(AA9=2,"EXTREMO-LARGO","EXTREMO-CORTO"),"AISLADO")))) -> EXTREMO-LARGO | AD9: AUTO | AE9: =IF(AD9="AUTO",AC9,AD9) -> EXTREMO-LARGO | AF9: =MATCH(L9,TABLAS!$D$5:$J$5,1) -> 1 | AG9: =IF(AF9>=7,0,(L9-INDEX(TABLAS!$D$5:$J$5,AF9))/(INDEX(TABLAS!$D$5:$J$5,AF9+1)-INDEX(TABLAS!$D$5:$J$5,AF9))) -> 0.46313843 | AH9: =INDEX(TABLAS!$D$6:$J$47,MATCH(AE9&"|NIC",TABLAS!$B$6:$B$47,0),AF9)+AG9*(INDEX(TABLAS!$D$6:$J$47,MATCH(AE9&"|NIC",TABLAS!$B$6:$B$47,0),MIN(AF9+1,7))-INDEX(TABLAS!$D$6:$J$47,MATCH(AE9&"|NIC",TABLAS!$B$6:$B$47,0),AF9)) -> 1249.8868 | AI9: =INDEX(TABLAS!$D$6:$J$47,MATCH(AE9&"|NIL",TABLAS!$B$6:$B$47,0),AF9)+AG9*(INDEX(TABLAS!$D$6:$J$47,MATCH(AE9&"|NIL",TABLAS!$B$6:$B$47,0),MIN(AF9+1,7))-INDEX(TABLAS!$D$6:$J$47,MATCH(AE9&"|NIL",TABLAS!$B$6:$B$47,0),AF9)) -> 0 | AJ9: =INDEX(TABLAS!$D$6:$J$47,MATCH(AE9&"|NDC",TABLAS!$B$6:$B$47,0),AF9)+AG9*(INDEX(TABLAS!$D$6:$J$47,MATCH(AE9&"|NDC",TABLAS!$B$6:$B$47,0),MIN(AF9+1,7))-INDEX(TABLAS!$D$6:$J$47,MATCH(AE9&"|NDC",TABLAS!$B$6:$B$47,0),AF9)) -> 520.8581 | AK9: =INDEX(TABLAS!$D$6:$J$47,MATCH(AE9&"|NDL",TABLAS!$B$6:$B$47,0),AF9)+AG9*(INDEX(TABLAS!$D$6:$J$47,MATCH(AE9&"|NDL",TABLAS!$B$6:$B$47,0),MIN(AF9+1,7))-INDEX(TABLAS!$D$6:$J$47,MATCH(AE9&"|NDL",TABLAS!$B$6:$B$47,0),AF9)) -> 285.30252 | AL9: =INDEX(TABLAS!$D$6:$J$47,MATCH(AE9&"|PC",TABLAS!$B$6:$B$47,0),AF9)+AG9*(INDEX(TABLAS!$D$6:$J$47,MATCH(AE9&"|PC",TABLAS!$B$6:$B$47,0),MIN(AF9+1,7))-INDEX(TABLAS!$D$6:$J$47,MATCH(AE9&"|PC",TABLAS!$B$6:$B$47,0),AF9)) -> 741.27409 | AM9: =INDEX(TABLAS!$D$6:$J$47,MATCH(AE9&"|PL",TABLAS!$B$6:$B$47,0),AF9)+AG9*(INDEX(TABLAS!$D$6:$J$47,MATCH(AE9&"|PL",TABLAS!$B$6:$B$47,0),MIN(AF9+1,7))-INDEX(TABLAS!$D$6:$J$47,MATCH(AE9&"|PL",TABLAS!$B$6:$B$47,0),AF9)) -> 298.46892 | AN9: =IF(D9="PERIMETRAL",IF(APOYOS!$G$29="CONTINUO",IF(M9="Y",AH9,AI9),IF(M9="Y",AJ9,AK9))*Y9*J9^2*1E-4*DATOS!$C$16/100/1000,0) -> 0.033211776 | AO9: =IF(D9="PERIMETRAL",IF(APOYOS!$G$30="CONTINUO",IF(M9="Y",AH9,AI9),IF(M9="Y",AJ9,AK9))*Y9*J9^2*1E-4*DATOS!$C$16/100/1000,0) -> 0.07969725 | AP9: =IF(D9="PERIMETRAL",IF(APOYOS!$G$31="CONTINUO",IF(M9="X",AH9,AI9),IF(M9="X",AJ9,AK9))*Y9*J9^2*1E-4*DATOS!$C$16/100/1000,0) -> 0.018191909 | AQ9: =IF(D9="PERIMETRAL",IF(APOYOS!$G$32="CONTINUO",IF(M9="X",AH9,AI9),IF(M9="X",AJ9,AK9))*Y9*J9^2*1E-4*DATOS!$C$16/100/1000,0) -> 0.018191909 | AR9: =IF(D9="PERIMETRAL",IF(M9="X",BN9,CD9)^3/(J9*100),0) -> 59.365613 | AS9: =IF(D9="PERIMETRAL",IF(M9="Y",BN9,CD9)^3/(J9*100),0) -> 72.744223 | AT9: =IF(D9="PERIMETRAL",MAX(0,IF(M9="Y",IF(AND(OR(APOYOS!$G$30="CONTINUO",APOYOS!$G$33="CONTINUO"),AO9>0,AN10>0,AN10>AO9),AO9+2/3*(AN10-AO9)*AS9/MAX(AS9+AS10,1E-9),0),0)),0) -> 0.2605174 | AU9: =IF(D9="PERIMETRAL",MAX(0,IF(M9<>"Y",IF(AND(OR(APOYOS!$G$30="CONTINUO",APOYOS!$G$33="CONTINUO"),AO9>0,AN10>0,AN10>AO9),AO9+2/3*(AN10-AO9)*AS9/MAX(AS9+AS10,1E-9),0),0)),0) -> 0 | AV9: =IF(D9="PERIMETRAL",(IF(M9="Y",IF(AND(OR(APOYOS!$G$30="CONTINUO",APOYOS!$G$33="CONTINUO"),AO9>0,AN10>0,AO9>AN10),2/3*(AO9-AN10)*AS9/MAX(AS9+AS10,1E-9),0),0))/2,0) -> 0 | AW9: =IF(D9="PERIMETRAL",(IF(M9<>"Y",IF(AND(OR(APOYOS!$G$30="CONTINUO",APOYOS!$G$33="CONTINUO"),AO9>0,AN10>0,AO9>AN10),2/3*(AO9-AN10)*AS9/MAX(AS9+AS10,1E-9),0),0))/2,0) -> 0 | AX9: =IF(D9="PERIMETRAL",MAX(0,0),0) -> 0 | AY9: =IF(D9<>"PERIMETRAL","",IF(AND(OR(APOYOS!$G$30="CONTINUO",APOYOS!$G$33="CONTINUO"),AO9>0,AN10>0,ABS(AO9-AN10)>0.5*MIN(AO9,AN10))," F80003","")) -> F80003 | AZ9: =IF(D9<>"PERIMETRAL","—",IF(AY9="","CUMPLE","FUERA con"&AY9)&IF(AND(D10="PERIMETRAL",APOYOS!$G$30<>APOYOS!$G$33)," · continuidad asimétrica con F80003 (cada uno con su momento; revisar APOYOS)","")) -> FUERA con F80003 | BA9: 0 | BB9: =IF(D9="PERIMETRAL",AL9*Y9*J9^2*1E-4*DATOS!$C$16/100/1000+AV9,0) -> 0.047266288 | BC9: =IF(D9="PERIMETRAL",MAX(MAX(AH9,AJ9)*Y9*J9^2*1E-4*DATOS!$C$16/100/1000,AT9),IF(D9="VOLADO",(Y9*(N9/100)^2/2+DATOS!$C$55*BA9*N9/100)*DATOS!$C$16/100/1000,0)) -> 0.2605174 | BD9: =IF(D9="PERIMETRAL",AM9*Y9*J9^2*1E-4*DATOS!$C$16/100/1000+AW9,0) -> 0.019031446 | BE9: =IF(D9="PERIMETRAL",MAX(MAX(AI9,AK9)*Y9*J9^2*1E-4*DATOS!$C$16/100/1000,AU9),0) -> 0.018191909 | BF9: =(DATOS!$C$15-R9-IF(DATOS!$C$25=0,0,INDEX(TABLAS!$C$52:$C$58,MATCH(DATOS!$C$25,TABLAS!$B$52:$B$58,0)))-INDEX(TABLAS!$C$52:$C$58,MATCH(DATOS!$C$26,TABLAS!$B$52:$B$58,0))/2) -> 20.365 | BG9: =IF(D9="HUECO",0,IF(IF(BB9<=0,0,IF((1-2*BB9*1E5/(DATOS!$C$58*P9*BF9^2*DATOS!$C$48))<0,-1,IF((1-SQRT((1-2*BB9*1E5/(DATOS!$C$58*P9*BF9^2*DATOS!$C$48))))*DATOS!$C$48*P9*BF9/DATOS!$C$40>DATOS!$C$82*P9*BF9,-1,(1-SQRT((1-2*BB9*1E5/(DATOS!$C$58*P9*BF9^2*DATOS!$C$48))))*DATOS!$C$48*P9*BF9/DATOS!$C$40)))<0,-1,MAX(IF(BB9<=0,0,IF((1-2*BB9*1E5/(DATOS!$C$58*P9*BF9^2*DATOS!$C$48))<0,-1,IF((1-SQRT((1-2*BB9*1E5/(DATOS!$C$58*P9*BF9^2*DATOS!$C$48))))*DATOS!$C$48*P9*BF9/DATOS!$C$40>DATOS!$C$82*P9*BF9,-1,(1-SQRT((1-2*BB9*1E5/(DATOS!$C$58*P9*BF9^2*DATOS!$C$48))))*DATOS!$C$48*P9*BF9/DATOS!$C$40))),MIN(DATOS!$C$83*DATOS!$C$13*BF9,4/3*IF(BB9<=0,0,IF((1-2*BB9*1E5/(DATOS!$C$58*P9*BF9^2*DATOS!$C$48))<0,-1,IF((1-SQRT((1-2*BB9*1E5/(DATOS!$C$58*P9*BF9^2*DATOS!$C$48))))*DATOS!$C$48*P9*BF9/DATOS!$C$40>DATOS!$C$82*P9*BF9,-1,(1-SQRT((1-2*BB9*1E5/(DATOS!$C$58*P9*BF9^2*DATOS!$C$48))))*DATOS!$C$48*P9*BF9/DATOS!$C$40))))))) -> 0.081946051 | BH9: =IF(AND(BG9>=0,IF(MAX(DATOS!$C$29,CEILING(BG9/INDEX(TABLAS!$D$52:$D$58,MIN(MATCH(DATOS!$C$26,TABLAS!$B$52:$B$58,0)+0,7)),1))*INDEX(TABLAS!$D$52:$D$58,MIN(MATCH(DATOS!$C$26,TABLAS!$B$52:$B$58,0)+0,7))>=4/3*IF(BB9<=0,0,IF((1-2*BB9*1E5/(DATOS!$C$58*P9*BF9^2*DATOS!$C$48))<0,-1,IF((1-SQRT((1-2*BB9*1E5/(DATOS!$C$58*P9*BF9^2*DATOS!$C$48))))*DATOS!$C$48*P9*BF9/DATOS!$C$40>DATOS!$C$82*P9*BF9,-1,(1-SQRT((1-2*BB9*1E5/(DATOS!$C$58*P9*BF9^2*DATOS!$C$48))))*DATOS!$C$48*P9*BF9/DATOS!$C$40)))-0.0001,MAX(DATOS!$C$29,CEILING(BG9/INDEX(TABLAS!$D$52:$D$58,MIN(MATCH(DATOS!$C$26,TABLAS!$B$52:$B$58,0)+0,7)),1)),MAX(MAX(DATOS!$C$29,CEILING(BG9/INDEX(TABLAS!$D$52:$D$58,MIN(MATCH(DATOS!$C$26,TABLAS!$B$52:$B$58,0)+0,7)),1)),2))<=MIN(DATOS!$C$28,INT(((DATOS!$C$13-2*R9-2*IF(DATOS!$C$25=0,0,INDEX(TABLAS!$C$52:$C$58,MATCH(DATOS!$C$25,TABLAS!$B$52:$B$58,0))))+MAX(DATOS!$C$32,INDEX(TABLAS!$C$52:$C$58,MIN(MATCH(DATOS!$C$26,TABLAS!$B$52:$B$58,0)+0,7))))/(INDEX(TABLAS!$C$52:$C$58,MIN(MATCH(DATOS!$C$26,TABLAS!$B$52:$B$58,0)+0,7))+MAX(DATOS!$C$32,INDEX(TABLAS!$C$52:$C$58,MIN(MATCH(DATOS!$C$26,TABLAS!$B$52:$B$58,0)+0,7))))))),INDEX(TABLAS!$B$52:$B$58,MIN(MATCH(DATOS!$C$26,TABLAS!$B$52:$B$58,0)+0,7)),IF(AND(BG9>=0,IF(MAX(DATOS!$C$29,CEILING(BG9/INDEX(TABLAS!$D$52:$D$58,MIN(MATCH(DATOS!$C$26,TABLAS!$B$52:$B$58,0)+1,7)),1))*INDEX(TABLAS!$D$52:$D$58,MIN(MATCH(DATOS!$C$26,TABLAS!$B$52:$B$58,0)+1,7))>=4/3*IF(BB9<=0,0,IF((1-2*BB9*1E5/(DATOS!$C$58*P9*BF9^2*DATOS!$C$48))<0,-1,IF((1-SQRT((1-2*BB9*1E5/(DATOS!$C$58*P9*BF9^2*DATOS!$C$48))))*DATOS!$C$48*P9*BF9/DATOS!$C$40>DATOS!$C$82*P9*BF9,-1,(1-SQRT((1-2*BB9*1E5/(DATOS!$C$58*P9*BF9^2*DATOS!$C$48))))*DATOS!$C$48*P9*BF9/DATOS!$C$40)))-0.0001,MAX(DATOS!$C$29,CEILING(BG9/INDEX(TABLAS!$D$52:$D$58,MIN(MATCH(DATOS!$C$26,TABLAS!$B$52:$B$58,0)+1,7)),1)),MAX(MAX(DATOS!$C$29,CEILING(BG9/INDEX(TABLAS!$D$52:$D$58,MIN(MATCH(DATOS!$C$26,TABLAS!$B$52:$B$58,0)+1,7)),1)),2))<=MIN(DATOS!$C$28,INT(((DATOS!$C$13-2*R9-2*IF(DATOS!$C$25=0,0,INDEX(TABLAS!$C$52:$C$58,MATCH(DATOS!$C$25,TABLAS!$B$52:$B$58,0))))+MAX(DATOS!$C$32,INDEX(TABLAS!$C$52:$C$58,MIN(MATCH(DATOS!$C$26,TABLAS!$B$52:$B$58,0)+1,7))))/(INDEX(TABLAS!$C$52:$C$58,MIN(MATCH(DATOS!$C$26,TABLAS!$B$52:$B$58,0)+1,7))+MAX(DATOS!$C$32,INDEX(TABLAS!$C$52:$C$58,MIN(MATCH(DATOS!$C$26,TABLAS!$B$52:$B$58,0)+1,7))))))),INDEX(TABLAS!$B$52:$B$58,MIN(MATCH(DATOS!$C$26,TABLAS!$B$52:$B$58,0)+1,7)),IF(AND(BG9>=0,IF(MAX(DATOS!$C$29,CEILING(BG9/INDEX(TABLAS!$D$52:$D$58,MIN(MATCH(DATOS!$C$26,TABLAS!$B$52:$B$58,0)+2,7)),1))*INDEX(TABLAS!$D$52:$D$58,MIN(MATCH(DATOS!$C$26,TABLAS!$B$52:$B$58,0)+2,7))>=4/3*IF(BB9<=0,0,IF((1-2*BB9*1E5/(DATOS!$C$58*P9*BF9^2*DATOS!$C$48))<0,-1,IF((1-SQRT((1-2*BB9*1E5/(DATOS!$C$58*P9*BF9^2*DATOS!$C$48))))*DATOS!$C$48*P9*BF9/DATOS!$C$40>DATOS!$C$82*P9*BF9,-1,(1-SQRT((1-2*BB9*1E5/(DATOS!$C$58*P9*BF9^2*DATOS!$C$48))))*DATOS!$C$48*P9*BF9/DATOS!$C$40)))-0.0001,MAX(DATOS!$C$29,CEILING(BG9/INDEX(TABLAS!$D$52:$D$58,MIN(MATCH(DATOS!$C$26,TABLAS!$B$52:$B$58,0)+2,7)),1)),MAX(MAX(DATOS!$C$29,CEILING(BG9/INDEX(TABLAS!$D$52:$D$58,MIN(MATCH(DATOS!$C$26,TABLAS!$B$52:$B$58,0)+2,7)),1)),2))<=MIN(DATOS!$C$28,INT(((DATOS!$C$13-2*R9-2*IF(DATOS!$C$25=0,0,INDEX(TABLAS!$C$52:$C$58,MATCH(DATOS!$C$25,TABLAS!$B$52:$B$58,0))))+MAX(DATOS!$C$32,INDEX(TABLAS!$C$52:$C$58,MIN(MATCH(DATOS!$C$26,TABLAS!$B$52:$B$58,0)+2,7))))/(INDEX(TABLAS!$C$52:$C$58,MIN(MATCH(DATOS!$C$26,TABLAS!$B$52:$B$58,0)+2,7))+MAX(DATOS!$C$32,INDEX(TABLAS!$C$52:$C$58,MIN(MATCH(DATOS!$C$26,TABLAS!$B$52:$B$58,0)+2,7))))))),INDEX(TABLAS!$B$52:$B$58,MIN(MATCH(DATOS!$C$26,TABLAS!$B$52:$B$58,0)+2,7)),IF(AND(BG9>=0,IF(MAX(DATOS!$C$29,CEILING(BG9/INDEX(TABLAS!$D$52:$D$58,MIN(MATCH(DATOS!$C$26,TABLAS!$B$52:$B$58,0)+3,7)),1))*INDEX(TABLAS!$D$52:$D$58,MIN(MATCH(DATOS!$C$26,TABLAS!$B$52:$B$58,0)+3,7))>=4/3*IF(BB9<=0,0,IF((1-2*BB9*1E5/(DATOS!$C$58*P9*BF9^2*DATOS!$C$48))<0,-1,IF((1-SQRT((1-2*BB9*1E5/(DATOS!$C$58*P9*BF9^2*DATOS!$C$48))))*DATOS!$C$48*P9*BF9/DATOS!$C$40>DATOS!$C$82*P9*BF9,-1,(1-SQRT((1-2*BB9*1E5/(DATOS!$C$58*P9*BF9^2*DATOS!$C$48))))*DATOS!$C$48*P9*BF9/DATOS!$C$40)))-0.0001,MAX(DATOS!$C$29,CEILING(BG9/INDEX(TABLAS!$D$52:$D$58,MIN(MATCH(DATOS!$C$26,TABLAS!$B$52:$B$58,0)+3,7)),1)),MAX(MAX(DATOS!$C$29,CEILING(BG9/INDEX(TABLAS!$D$52:$D$58,MIN(MATCH(DATOS!$C$26,TABLAS!$B$52:$B$58,0)+3,7)),1)),2))<=MIN(DATOS!$C$28,INT(((DATOS!$C$13-2*R9-2*IF(DATOS!$C$25=0,0,INDEX(TABLAS!$C$52:$C$58,MATCH(DATOS!$C$25,TABLAS!$B$52:$B$58,0))))+MAX(DATOS!$C$32,INDEX(TABLAS!$C$52:$C$58,MIN(MATCH(DATOS!$C$26,TABLAS!$B$52:$B$58,0)+3,7))))/(INDEX(TABLAS!$C$52:$C$58,MIN(MATCH(DATOS!$C$26,TABLAS!$B$52:$B$58,0)+3,7))+MAX(DATOS!$C$32,INDEX(TABLAS!$C$52:$C$58,MIN(MATCH(DATOS!$C$26,TABLAS!$B$52:$B$58,0)+3,7))))))),INDEX(TABLAS!$B$52:$B$58,MIN(MATCH(DATOS!$C$26,TABLAS!$B$52:$B$58,0)+3,7)),IF(AND(BG9>=0,IF(MAX(DATOS!$C$29,CEILING(BG9/INDEX(TABLAS!$D$52:$D$58,MIN(MATCH(DATOS!$C$26,TABLAS!$B$52:$B$58,0)+4,7)),1))*INDEX(TABLAS!$D$52:$D$58,MIN(MATCH(DATOS!$C$26,TABLAS!$B$52:$B$58,0)+4,7))>=4/3*IF(BB9<=0,0,IF((1-2*BB9*1E5/(DATOS!$C$58*P9*BF9^2*DATOS!$C$48))<0,-1,IF((1-SQRT((1-2*BB9*1E5/(DATOS!$C$58*P9*BF9^2*DATOS!$C$48))))*DATOS!$C$48*P9*BF9/DATOS!$C$40>DATOS!$C$82*P9*BF9,-1,(1-SQRT((1-2*BB9*1E5/(DATOS!$C$58*P9*BF9^2*DATOS!$C$48))))*DATOS!$C$48*P9*BF9/DATOS!$C$40)))-0.0001,MAX(DATOS!$C$29,CEILING(BG9/INDEX(TABLAS!$D$52:$D$58,MIN(MATCH(DATOS!$C$26,TABLAS!$B$52:$B$58,0)+4,7)),1)),MAX(MAX(DATOS!$C$29,CEILING(BG9/INDEX(TABLAS!$D$52:$D$58,MIN(MATCH(DATOS!$C$26,TABLAS!$B$52:$B$58,0)+4,7)),1)),2))<=MIN(DATOS!$C$28,INT(((DATOS!$C$13-2*R9-2*IF(DATOS!$C$25=0,0,INDEX(TABLAS!$C$52:$C$58,MATCH(DATOS!$C$25,TABLAS!$B$52:$B$58,0))))+MAX(DATOS!$C$32,INDEX(TABLAS!$C$52:$C$58,MIN(MATCH(DATOS!$C$26,TABLAS!$B$52:$B$58,0)+4,7))))/(INDEX(TABLAS!$C$52:$C$58,MIN(MATCH(DATOS!$C$26,TABLAS!$B$52:$B$58,0)+4,7))+MAX(DATOS!$C$32,INDEX(TABLAS!$C$52:$C$58,MIN(MATCH(DATOS!$C$26,TABLAS!$B$52:$B$58,0)+4,7))))))),INDEX(TABLAS!$B$52:$B$58,MIN(MATCH(DATOS!$C$26,TABLAS!$B$52:$B$58,0)+4,7)),INDEX(TABLAS!$B$52:$B$58,7)))))) -> 4 | BI9: =IF(D9="HUECO",0,IF(BG9<0,0,IF(MAX(DATOS!$C$29,CEILING(MAX(BG9,0)/INDEX(TABLAS!$D$52:$D$58,MATCH(BH9,TABLAS!$B$52:$B$58,0)),1))*INDEX(TABLAS!$D$52:$D$58,MATCH(BH9,TABLAS!$B$52:$B$58,0))>=4/3*IF(BB9<=0,0,IF((1-2*BB9*1E5/(DATOS!$C$58*P9*BF9^2*DATOS!$C$48))<0,-1,IF((1-SQRT((1-2*BB9*1E5/(DATOS!$C$58*P9*BF9^2*DATOS!$C$48))))*DATOS!$C$48*P9*BF9/DATOS!$C$40>DATOS!$C$82*P9*BF9,-1,(1-SQRT((1-2*BB9*1E5/(DATOS!$C$58*P9*BF9^2*DATOS!$C$48))))*DATOS!$C$48*P9*BF9/DATOS!$C$40)))-0.0001,MAX(DATOS!$C$29,CEILING(MAX(BG9,0)/INDEX(TABLAS!$D$52:$D$58,MATCH(BH9,TABLAS!$B$52:$B$58,0)),1)),MAX(MAX(DATOS!$C$29,CEILING(MAX(BG9,0)/INDEX(TABLAS!$D$52:$D$58,MATCH(BH9,TABLAS!$B$52:$B$58,0)),1)),2)))) -> 1 | BJ9: =DATOS!$C$15-R9-IF(DATOS!$C$25=0,0,INDEX(TABLAS!$C$52:$C$58,MATCH(DATOS!$C$25,TABLAS!$B$52:$B$58,0)))-INDEX(TABLAS!$C$52:$C$58,MATCH(BH9,TABLAS!$B$52:$B$58,0))/2 -> 20.365 | BK9: =IF(BI9=0,0,DATOS!$C$58*BI9*INDEX(TABLAS!$D$52:$D$58,MATCH(BH9,TABLAS!$B$52:$B$58,0))*DATOS!$C$40*(BJ9-BI9*INDEX(TABLAS!$D$52:$D$58,MATCH(BH9,TABLAS!$B$52:$B$58,0))*DATOS!$C$40/(DATOS!$C$48*P9)/2)/1E5) -> 0.95839288 | BL9: =IF(BG9<0,9.99,IF(BK9>0,BB9/BK9,0)) -> 0.049318279 | BM9: =IF(BI9=0,"—",0.003*(BJ9-(BI9*INDEX(TABLAS!$D$52:$D$58,MATCH(BH9,TABLAS!$B$52:$B$58,0))*DATOS!$C$40/(DATOS!$C$48*P9)/DATOS!$C$49))/(BI9*INDEX(TABLAS!$D$52:$D$58,MATCH(BH9,TABLAS!$B$52:$B$58,0))*DATOS!$C$40/(DATOS!$C$48*P9)/DATOS!$C$49)) -> 0.061755231 | BN9: =((DATOS!$C$15-S9-2*DATOS!$C$35-IF(DATOS!$C$25=0,0,INDEX(TABLAS!$C$52:$C$58,MATCH(DATOS!$C$25,TABLAS!$B$52:$B$58,0)))-INDEX(TABLAS!$C$52:$C$58,MATCH(DATOS!$C$27,TABLAS!$B$52:$B$58,0))/2)-IF(AND((DATOS!$C$15-S9-2*DATOS!$C$35-IF(DATOS!$C$25=0,0,INDEX(TABLAS!$C$52:$C$58,MATCH(DATOS!$C$25,TABLAS!$B$52:$B$58,0)))-INDEX(TABLAS!$C$52:$C$58,MATCH(DATOS!$C$27,TABLAS!$B$52:$B$58,0))/2)<=20,DATOS!$C$18<>"SÍ"),2,0)) -> 19.389 | BO9: =IF(D9="HUECO",0,IF(IF(BC9<=0,0,IF((1-2*BC9*1E5/(DATOS!$C$58*DATOS!$C$19*BN9^2*DATOS!$C$48))<0,-1,IF((1-SQRT((1-2*BC9*1E5/(DATOS!$C$58*DATOS!$C$19*BN9^2*DATOS!$C$48))))*DATOS!$C$48*DATOS!$C$19*BN9/DATOS!$C$40>DATOS!$C$82*DATOS!$C$19*BN9,-1,(1-SQRT((1-2*BC9*1E5/(DATOS!$C$58*DATOS!$C$19*BN9^2*DATOS!$C$48))))*DATOS!$C$48*DATOS!$C$19*BN9/DATOS!$C$40)))<0,-1,MAX(IF(BC9<=0,0,IF((1-2*BC9*1E5/(DATOS!$C$58*DATOS!$C$19*BN9^2*DATOS!$C$48))<0,-1,IF((1-SQRT((1-2*BC9*1E5/(DATOS!$C$58*DATOS!$C$19*BN9^2*DATOS!$C$48))))*DATOS!$C$48*DATOS!$C$19*BN9/DATOS!$C$40>DATOS!$C$82*DATOS!$C$19*BN9,-1,(1-SQRT((1-2*BC9*1E5/(DATOS!$C$58*DATOS!$C$19*BN9^2*DATOS!$C$48))))*DATOS!$C$48*DATOS!$C$19*BN9/DATOS!$C$40))),MIN(DATOS!$C$83*IF(D9="VOLADO",2*DATOS!$C$13,DATOS!$C$13)*BN9,4/3*IF(BC9<=0,0,IF((1-2*BC9*1E5/(DATOS!$C$58*DATOS!$C$19*BN9^2*DATOS!$C$48))<0,-1,IF((1-SQRT((1-2*BC9*1E5/(DATOS!$C$58*DATOS!$C$19*BN9^2*DATOS!$C$48))))*DATOS!$C$48*DATOS!$C$19*BN9/DATOS!$C$40>DATOS!$C$82*DATOS!$C$19*BN9,-1,(1-SQRT((1-2*BC9*1E5/(DATOS!$C$58*DATOS!$C$19*BN9^2*DATOS!$C$48))))*DATOS!$C$48*DATOS!$C$19*BN9/DATOS!$C$40))))))) -> 0.48285795 | BP9: =IF(AND(BO9>=0,IF(MAX(DATOS!$C$29,CEILING(BO9/INDEX(TABLAS!$D$52:$D$58,MIN(MATCH(DATOS!$C$27,TABLAS!$B$52:$B$58,0)+0,7)),1))*INDEX(TABLAS!$D$52:$D$58,MIN(MATCH(DATOS!$C$27,TABLAS!$B$52:$B$58,0)+0,7))>=4/3*IF(BC9<=0,0,IF((1-2*BC9*1E5/(DATOS!$C$58*DATOS!$C$19*BN9^2*DATOS!$C$48))<0,-1,IF((1-SQRT((1-2*BC9*1E5/(DATOS!$C$58*DATOS!$C$19*BN9^2*DATOS!$C$48))))*DATOS!$C$48*DATOS!$C$19*BN9/DATOS!$C$40>DATOS!$C$82*DATOS!$C$19*BN9,-1,(1-SQRT((1-2*BC9*1E5/(DATOS!$C$58*DATOS!$C$19*BN9^2*DATOS!$C$48))))*DATOS!$C$48*DATOS!$C$19*BN9/DATOS!$C$40)))-0.0001,MAX(DATOS!$C$29,CEILING(BO9/INDEX(TABLAS!$D$52:$D$58,MIN(MATCH(DATOS!$C$27,TABLAS!$B$52:$B$58,0)+0,7)),1)),MAX(MAX(DATOS!$C$29,CEILING(BO9/INDEX(TABLAS!$D$52:$D$58,MIN(MATCH(DATOS!$C$27,TABLAS!$B$52:$B$58,0)+0,7)),1)),2))<=MIN(DATOS!$C$28,INT(((DATOS!$C$13-2*S9-2*IF(DATOS!$C$25=0,0,INDEX(TABLAS!$C$52:$C$58,MATCH(DATOS!$C$25,TABLAS!$B$52:$B$58,0))))+MAX(DATOS!$C$32,INDEX(TABLAS!$C$52:$C$58,MIN(MATCH(DATOS!$C$27,TABLAS!$B$52:$B$58,0)+0,7))))/(INDEX(TABLAS!$C$52:$C$58,MIN(MATCH(DATOS!$C$27,TABLAS!$B$52:$B$58,0)+0,7))+MAX(DATOS!$C$32,INDEX(TABLAS!$C$52:$C$58,MIN(MATCH(DATOS!$C$27,TABLAS!$B$52:$B$58,0)+0,7))))))),INDEX(TABLAS!$B$52:$B$58,MIN(MATCH(DATOS!$C$27,TABLAS!$B$52:$B$58,0)+0,7)),IF(AND(BO9>=0,IF(MAX(DATOS!$C$29,CEILING(BO9/INDEX(TABLAS!$D$52:$D$58,MIN(MATCH(DATOS!$C$27,TABLAS!$B$52:$B$58,0)+1,7)),1))*INDEX(TABLAS!$D$52:$D$58,MIN(MATCH(DATOS!$C$27,TABLAS!$B$52:$B$58,0)+1,7))>=4/3*IF(BC9<=0,0,IF((1-2*BC9*1E5/(DATOS!$C$58*DATOS!$C$19*BN9^2*DATOS!$C$48))<0,-1,IF((1-SQRT((1-2*BC9*1E5/(DATOS!$C$58*DATOS!$C$19*BN9^2*DATOS!$C$48))))*DATOS!$C$48*DATOS!$C$19*BN9/DATOS!$C$40>DATOS!$C$82*DATOS!$C$19*BN9,-1,(1-SQRT((1-2*BC9*1E5/(DATOS!$C$58*DATOS!$C$19*BN9^2*DATOS!$C$48))))*DATOS!$C$48*DATOS!$C$19*BN9/DATOS!$C$40)))-0.0001,MAX(DATOS!$C$29,CEILING(BO9/INDEX(TABLAS!$D$52:$D$58,MIN(MATCH(DATOS!$C$27,TABLAS!$B$52:$B$58,0)+1,7)),1)),MAX(MAX(DATOS!$C$29,CEILING(BO9/INDEX(TABLAS!$D$52:$D$58,MIN(MATCH(DATOS!$C$27,TABLAS!$B$52:$B$58,0)+1,7)),1)),2))<=MIN(DATOS!$C$28,INT(((DATOS!$C$13-2*S9-2*IF(DATOS!$C$25=0,0,INDEX(TABLAS!$C$52:$C$58,MATCH(DATOS!$C$25,TABLAS!$B$52:$B$58,0))))+MAX(DATOS!$C$32,INDEX(TABLAS!$C$52:$C$58,MIN(MATCH(DATOS!$C$27,TABLAS!$B$52:$B$58,0)+1,7))))/(INDEX(TABLAS!$C$52:$C$58,MIN(MATCH(DATOS!$C$27,TABLAS!$B$52:$B$58,0)+1,7))+MAX(DATOS!$C$32,INDEX(TABLAS!$C$52:$C$58,MIN(MATCH(DATOS!$C$27,TABLAS!$B$52:$B$58,0)+1,7))))))),INDEX(TABLAS!$B$52:$B$58,MIN(MATCH(DATOS!$C$27,TABLAS!$B$52:$B$58,0)+1,7)),IF(AND(BO9>=0,IF(MAX(DATOS!$C$29,CEILING(BO9/INDEX(TABLAS!$D$52:$D$58,MIN(MATCH(DATOS!$C$27,TABLAS!$B$52:$B$58,0)+2,7)),1))*INDEX(TABLAS!$D$52:$D$58,MIN(MATCH(DATOS!$C$27,TABLAS!$B$52:$B$58,0)+2,7))>=4/3*IF(BC9<=0,0,IF((1-2*BC9*1E5/(DATOS!$C$58*DATOS!$C$19*BN9^2*DATOS!$C$48))<0,-1,IF((1-SQRT((1-2*BC9*1E5/(DATOS!$C$58*DATOS!$C$19*BN9^2*DATOS!$C$48))))*DATOS!$C$48*DATOS!$C$19*BN9/DATOS!$C$40>DATOS!$C$82*DATOS!$C$19*BN9,-1,(1-SQRT((1-2*BC9*1E5/(DATOS!$C$58*DATOS!$C$19*BN9^2*DATOS!$C$48))))*DATOS!$C$48*DATOS!$C$19*BN9/DATOS!$C$40)))-0.0001,MAX(DATOS!$C$29,CEILING(BO9/INDEX(TABLAS!$D$52:$D$58,MIN(MATCH(DATOS!$C$27,TABLAS!$B$52:$B$58,0)+2,7)),1)),MAX(MAX(DATOS!$C$29,CEILING(BO9/INDEX(TABLAS!$D$52:$D$58,MIN(MATCH(DATOS!$C$27,TABLAS!$B$52:$B$58,0)+2,7)),1)),2))<=MIN(DATOS!$C$28,INT(((DATOS!$C$13-2*S9-2*IF(DATOS!$C$25=0,0,INDEX(TABLAS!$C$52:$C$58,MATCH(DATOS!$C$25,TABLAS!$B$52:$B$58,0))))+MAX(DATOS!$C$32,INDEX(TABLAS!$C$52:$C$58,MIN(MATCH(DATOS!$C$27,TABLAS!$B$52:$B$58,0)+2,7))))/(INDEX(TABLAS!$C$52:$C$58,MIN(MATCH(DATOS!$C$27,TABLAS!$B$52:$B$58,0)+2,7))+MAX(DATOS!$C$32,INDEX(TABLAS!$C$52:$C$58,MIN(MATCH(DATOS!$C$27,TABLAS!$B$52:$B$58,0)+2,7))))))),INDEX(TABLAS!$B$52:$B$58,MIN(MATCH(DATOS!$C$27,TABLAS!$B$52:$B$58,0)+2,7)),IF(AND(BO9>=0,IF(MAX(DATOS!$C$29,CEILING(BO9/INDEX(TABLAS!$D$52:$D$58,MIN(MATCH(DATOS!$C$27,TABLAS!$B$52:$B$58,0)+3,7)),1))*INDEX(TABLAS!$D$52:$D$58,MIN(MATCH(DATOS!$C$27,TABLAS!$B$52:$B$58,0)+3,7))>=4/3*IF(BC9<=0,0,IF((1-2*BC9*1E5/(DATOS!$C$58*DATOS!$C$19*BN9^2*DATOS!$C$48))<0,-1,IF((1-SQRT((1-2*BC9*1E5/(DATOS!$C$58*DATOS!$C$19*BN9^2*DATOS!$C$48))))*DATOS!$C$48*DATOS!$C$19*BN9/DATOS!$C$40>DATOS!$C$82*DATOS!$C$19*BN9,-1,(1-SQRT((1-2*BC9*1E5/(DATOS!$C$58*DATOS!$C$19*BN9^2*DATOS!$C$48))))*DATOS!$C$48*DATOS!$C$19*BN9/DATOS!$C$40)))-0.0001,MAX(DATOS!$C$29,CEILING(BO9/INDEX(TABLAS!$D$52:$D$58,MIN(MATCH(DATOS!$C$27,TABLAS!$B$52:$B$58,0)+3,7)),1)),MAX(MAX(DATOS!$C$29,CEILING(BO9/INDEX(TABLAS!$D$52:$D$58,MIN(MATCH(DATOS!$C$27,TABLAS!$B$52:$B$58,0)+3,7)),1)),2))<=MIN(DATOS!$C$28,INT(((DATOS!$C$13-2*S9-2*IF(DATOS!$C$25=0,0,INDEX(TABLAS!$C$52:$C$58,MATCH(DATOS!$C$25,TABLAS!$B$52:$B$58,0))))+MAX(DATOS!$C$32,INDEX(TABLAS!$C$52:$C$58,MIN(MATCH(DATOS!$C$27,TABLAS!$B$52:$B$58,0)+3,7))))/(INDEX(TABLAS!$C$52:$C$58,MIN(MATCH(DATOS!$C$27,TABLAS!$B$52:$B$58,0)+3,7))+MAX(DATOS!$C$32,INDEX(TABLAS!$C$52:$C$58,MIN(MATCH(DATOS!$C$27,TABLAS!$B$52:$B$58,0)+3,7))))))),INDEX(TABLAS!$B$52:$B$58,MIN(MATCH(DATOS!$C$27,TABLAS!$B$52:$B$58,0)+3,7)),IF(AND(BO9>=0,IF(MAX(DATOS!$C$29,CEILING(BO9/INDEX(TABLAS!$D$52:$D$58,MIN(MATCH(DATOS!$C$27,TABLAS!$B$52:$B$58,0)+4,7)),1))*INDEX(TABLAS!$D$52:$D$58,MIN(MATCH(DATOS!$C$27,TABLAS!$B$52:$B$58,0)+4,7))>=4/3*IF(BC9<=0,0,IF((1-2*BC9*1E5/(DATOS!$C$58*DATOS!$C$19*BN9^2*DATOS!$C$48))<0,-1,IF((1-SQRT((1-2*BC9*1E5/(DATOS!$C$58*DATOS!$C$19*BN9^2*DATOS!$C$48))))*DATOS!$C$48*DATOS!$C$19*BN9/DATOS!$C$40>DATOS!$C$82*DATOS!$C$19*BN9,-1,(1-SQRT((1-2*BC9*1E5/(DATOS!$C$58*DATOS!$C$19*BN9^2*DATOS!$C$48))))*DATOS!$C$48*DATOS!$C$19*BN9/DATOS!$C$40)))-0.0001,MAX(DATOS!$C$29,CEILING(BO9/INDEX(TABLAS!$D$52:$D$58,MIN(MATCH(DATOS!$C$27,TABLAS!$B$52:$B$58,0)+4,7)),1)),MAX(MAX(DATOS!$C$29,CEILING(BO9/INDEX(TABLAS!$D$52:$D$58,MIN(MATCH(DATOS!$C$27,TABLAS!$B$52:$B$58,0)+4,7)),1)),2))<=MIN(DATOS!$C$28,INT(((DATOS!$C$13-2*S9-2*IF(DATOS!$C$25=0,0,INDEX(TABLAS!$C$52:$C$58,MATCH(DATOS!$C$25,TABLAS!$B$52:$B$58,0))))+MAX(DATOS!$C$32,INDEX(TABLAS!$C$52:$C$58,MIN(MATCH(DATOS!$C$27,TABLAS!$B$52:$B$58,0)+4,7))))/(INDEX(TABLAS!$C$52:$C$58,MIN(MATCH(DATOS!$C$27,TABLAS!$B$52:$B$58,0)+4,7))+MAX(DATOS!$C$32,INDEX(TABLAS!$C$52:$C$58,MIN(MATCH(DATOS!$C$27,TABLAS!$B$52:$B$58,0)+4,7))))))),INDEX(TABLAS!$B$52:$B$58,MIN(MATCH(DATOS!$C$27,TABLAS!$B$52:$B$58,0)+4,7)),INDEX(TABLAS!$B$52:$B$58,7)))))) -> 4 | BQ9: =IF(D9="HUECO",0,IF(BO9<0,0,IF(MAX(DATOS!$C$29,CEILING(MAX(BO9,0)/INDEX(TABLAS!$D$52:$D$58,MATCH(BP9,TABLAS!$B$52:$B$58,0)),1))*INDEX(TABLAS!$D$52:$D$58,MATCH(BP9,TABLAS!$B$52:$B$58,0))>=4/3*IF(BC9<=0,0,IF((1-2*BC9*1E5/(DATOS!$C$58*DATOS!$C$19*BN9^2*DATOS!$C$48))<0,-1,IF((1-SQRT((1-2*BC9*1E5/(DATOS!$C$58*DATOS!$C$19*BN9^2*DATOS!$C$48))))*DATOS!$C$48*DATOS!$C$19*BN9/DATOS!$C$40>DATOS!$C$82*DATOS!$C$19*BN9,-1,(1-SQRT((1-2*BC9*1E5/(DATOS!$C$58*DATOS!$C$19*BN9^2*DATOS!$C$48))))*DATOS!$C$48*DATOS!$C$19*BN9/DATOS!$C$40)))-0.0001,MAX(DATOS!$C$29,CEILING(MAX(BO9,0)/INDEX(TABLAS!$D$52:$D$58,MATCH(BP9,TABLAS!$B$52:$B$58,0)),1)),MAX(MAX(DATOS!$C$29,CEILING(MAX(BO9,0)/INDEX(TABLAS!$D$52:$D$58,MATCH(BP9,TABLAS!$B$52:$B$58,0)),1)),2)))) -> 1 | BR9: =((DATOS!$C$15-S9-2*DATOS!$C$35-IF(DATOS!$C$25=0,0,INDEX(TABLAS!$C$52:$C$58,MATCH(DATOS!$C$25,TABLAS!$B$52:$B$58,0)))-INDEX(TABLAS!$C$52:$C$58,MATCH(BP9,TABLAS!$B$52:$B$58,0))/2)-IF(AND((DATOS!$C$15-S9-2*DATOS!$C$35-IF(DATOS!$C$25=0,0,INDEX(TABLAS!$C$52:$C$58,MATCH(DATOS!$C$25,TABLAS!$B$52:$B$58,0)))-INDEX(TABLAS!$C$52:$C$58,MATCH(BP9,TABLAS!$B$52:$B$58,0))/2)<=20,DATOS!$C$18<>"SÍ"),2,0)) -> 19.389 | BS9: =IF(BQ9=0,0,DATOS!$C$58*BQ9*INDEX(TABLAS!$D$52:$D$58,MATCH(BP9,TABLAS!$B$52:$B$58,0))*DATOS!$C$40*(BR9-BQ9*INDEX(TABLAS!$D$52:$D$58,MATCH(BP9,TABLAS!$B$52:$B$58,0))*DATOS!$C$40/(DATOS!$C$48*DATOS!$C$19)/2)/1E5) -> 0.87053798 | BT9: =IF(BO9<0,9.99,IF(BS9>0,BC9/BS9,0)) -> 0.29926023 | BU9: =IF(BQ9=0,"—",0.003*(BR9-(BQ9*INDEX(TABLAS!$D$52:$D$58,MATCH(BP9,TABLAS!$B$52:$B$58,0))*DATOS!$C$40/(DATOS!$C$48*DATOS!$C$19)/DATOS!$C$49))/(BQ9*INDEX(TABLAS!$D$52:$D$58,MATCH(BP9,TABLAS!$B$52:$B$58,0))*DATOS!$C$40/(DATOS!$C$48*DATOS!$C$19)/DATOS!$C$49)) -> 0.016697065 | BV9: =(DATOS!$C$15-R9-IF(DATOS!$C$25=0,0,INDEX(TABLAS!$C$52:$C$58,MATCH(DATOS!$C$25,TABLAS!$B$52:$B$58,0)))-INDEX(TABLAS!$C$52:$C$58,MATCH(DATOS!$C$26,TABLAS!$B$52:$B$58,0))-INDEX(TABLAS!$C$52:$C$58,MATCH(DATOS!$C$26,TABLAS!$B$52:$B$58,0))/2) -> 19.095 | BW9: =IF(D9="HUECO",0,IF(IF(BD9<=0,0,IF((1-2*BD9*1E5/(DATOS!$C$58*Q9*BV9^2*DATOS!$C$48))<0,-1,IF((1-SQRT((1-2*BD9*1E5/(DATOS!$C$58*Q9*BV9^2*DATOS!$C$48))))*DATOS!$C$48*Q9*BV9/DATOS!$C$40>DATOS!$C$82*Q9*BV9,-1,(1-SQRT((1-2*BD9*1E5/(DATOS!$C$58*Q9*BV9^2*DATOS!$C$48))))*DATOS!$C$48*Q9*BV9/DATOS!$C$40)))<0,-1,MAX(IF(BD9<=0,0,IF((1-2*BD9*1E5/(DATOS!$C$58*Q9*BV9^2*DATOS!$C$48))<0,-1,IF((1-SQRT((1-2*BD9*1E5/(DATOS!$C$58*Q9*BV9^2*DATOS!$C$48))))*DATOS!$C$48*Q9*BV9/DATOS!$C$40>DATOS!$C$82*Q9*BV9,-1,(1-SQRT((1-2*BD9*1E5/(DATOS!$C$58*Q9*BV9^2*DATOS!$C$48))))*DATOS!$C$48*Q9*BV9/DATOS!$C$40))),MIN(DATOS!$C$83*DATOS!$C$13*BV9,4/3*IF(BD9<=0,0,IF((1-2*BD9*1E5/(DATOS!$C$58*Q9*BV9^2*DATOS!$C$48))<0,-1,IF((1-SQRT((1-2*BD9*1E5/(DATOS!$C$58*Q9*BV9^2*DATOS!$C$48))))*DATOS!$C$48*Q9*BV9/DATOS!$C$40>DATOS!$C$82*Q9*BV9,-1,(1-SQRT((1-2*BD9*1E5/(DATOS!$C$58*Q9*BV9^2*DATOS!$C$48))))*DATOS!$C$48*Q9*BV9/DATOS!$C$40))))))) -> 0.035162823 | BX9: =IF(AND(BW9>=0,IF(MAX(DATOS!$C$29,CEILING(BW9/INDEX(TABLAS!$D$52:$D$58,MIN(MATCH(DATOS!$C$26,TABLAS!$B$52:$B$58,0)+0,7)),1))*INDEX(TABLAS!$D$52:$D$58,MIN(MATCH(DATOS!$C$26,TABLAS!$B$52:$B$58,0)+0,7))>=4/3*IF(BD9<=0,0,IF((1-2*BD9*1E5/(DATOS!$C$58*Q9*BV9^2*DATOS!$C$48))<0,-1,IF((1-SQRT((1-2*BD9*1E5/(DATOS!$C$58*Q9*BV9^2*DATOS!$C$48))))*DATOS!$C$48*Q9*BV9/DATOS!$C$40>DATOS!$C$82*Q9*BV9,-1,(1-SQRT((1-2*BD9*1E5/(DATOS!$C$58*Q9*BV9^2*DATOS!$C$48))))*DATOS!$C$48*Q9*BV9/DATOS!$C$40)))-0.0001,MAX(DATOS!$C$29,CEILING(BW9/INDEX(TABLAS!$D$52:$D$58,MIN(MATCH(DATOS!$C$26,TABLAS!$B$52:$B$58,0)+0,7)),1)),MAX(MAX(DATOS!$C$29,CEILING(BW9/INDEX(TABLAS!$D$52:$D$58,MIN(MATCH(DATOS!$C$26,TABLAS!$B$52:$B$58,0)+0,7)),1)),2))<=MIN(DATOS!$C$28,INT(((DATOS!$C$13-2*R9-2*IF(DATOS!$C$25=0,0,INDEX(TABLAS!$C$52:$C$58,MATCH(DATOS!$C$25,TABLAS!$B$52:$B$58,0))))+MAX(DATOS!$C$32,INDEX(TABLAS!$C$52:$C$58,MIN(MATCH(DATOS!$C$26,TABLAS!$B$52:$B$58,0)+0,7))))/(INDEX(TABLAS!$C$52:$C$58,MIN(MATCH(DATOS!$C$26,TABLAS!$B$52:$B$58,0)+0,7))+MAX(DATOS!$C$32,INDEX(TABLAS!$C$52:$C$58,MIN(MATCH(DATOS!$C$26,TABLAS!$B$52:$B$58,0)+0,7))))))),INDEX(TABLAS!$B$52:$B$58,MIN(MATCH(DATOS!$C$26,TABLAS!$B$52:$B$58,0)+0,7)),IF(AND(BW9>=0,IF(MAX(DATOS!$C$29,CEILING(BW9/INDEX(TABLAS!$D$52:$D$58,MIN(MATCH(DATOS!$C$26,TABLAS!$B$52:$B$58,0)+1,7)),1))*INDEX(TABLAS!$D$52:$D$58,MIN(MATCH(DATOS!$C$26,TABLAS!$B$52:$B$58,0)+1,7))>=4/3*IF(BD9<=0,0,IF((1-2*BD9*1E5/(DATOS!$C$58*Q9*BV9^2*DATOS!$C$48))<0,-1,IF((1-SQRT((1-2*BD9*1E5/(DATOS!$C$58*Q9*BV9^2*DATOS!$C$48))))*DATOS!$C$48*Q9*BV9/DATOS!$C$40>DATOS!$C$82*Q9*BV9,-1,(1-SQRT((1-2*BD9*1E5/(DATOS!$C$58*Q9*BV9^2*DATOS!$C$48))))*DATOS!$C$48*Q9*BV9/DATOS!$C$40)))-0.0001,MAX(DATOS!$C$29,CEILING(BW9/INDEX(TABLAS!$D$52:$D$58,MIN(MATCH(DATOS!$C$26,TABLAS!$B$52:$B$58,0)+1,7)),1)),MAX(MAX(DATOS!$C$29,CEILING(BW9/INDEX(TABLAS!$D$52:$D$58,MIN(MATCH(DATOS!$C$26,TABLAS!$B$52:$B$58,0)+1,7)),1)),2))<=MIN(DATOS!$C$28,INT(((DATOS!$C$13-2*R9-2*IF(DATOS!$C$25=0,0,INDEX(TABLAS!$C$52:$C$58,MATCH(DATOS!$C$25,TABLAS!$B$52:$B$58,0))))+MAX(DATOS!$C$32,INDEX(TABLAS!$C$52:$C$58,MIN(MATCH(DATOS!$C$26,TABLAS!$B$52:$B$58,0)+1,7))))/(INDEX(TABLAS!$C$52:$C$58,MIN(MATCH(DATOS!$C$26,TABLAS!$B$52:$B$58,0)+1,7))+MAX(DATOS!$C$32,INDEX(TABLAS!$C$52:$C$58,MIN(MATCH(DATOS!$C$26,TABLAS!$B$52:$B$58,0)+1,7))))))),INDEX(TABLAS!$B$52:$B$58,MIN(MATCH(DATOS!$C$26,TABLAS!$B$52:$B$58,0)+1,7)),IF(AND(BW9>=0,IF(MAX(DATOS!$C$29,CEILING(BW9/INDEX(TABLAS!$D$52:$D$58,MIN(MATCH(DATOS!$C$26,TABLAS!$B$52:$B$58,0)+2,7)),1))*INDEX(TABLAS!$D$52:$D$58,MIN(MATCH(DATOS!$C$26,TABLAS!$B$52:$B$58,0)+2,7))>=4/3*IF(BD9<=0,0,IF((1-2*BD9*1E5/(DATOS!$C$58*Q9*BV9^2*DATOS!$C$48))<0,-1,IF((1-SQRT((1-2*BD9*1E5/(DATOS!$C$58*Q9*BV9^2*DATOS!$C$48))))*DATOS!$C$48*Q9*BV9/DATOS!$C$40>DATOS!$C$82*Q9*BV9,-1,(1-SQRT((1-2*BD9*1E5/(DATOS!$C$58*Q9*BV9^2*DATOS!$C$48))))*DATOS!$C$48*Q9*BV9/DATOS!$C$40)))-0.0001,MAX(DATOS!$C$29,CEILING(BW9/INDEX(TABLAS!$D$52:$D$58,MIN(MATCH(DATOS!$C$26,TABLAS!$B$52:$B$58,0)+2,7)),1)),MAX(MAX(DATOS!$C$29,CEILING(BW9/INDEX(TABLAS!$D$52:$D$58,MIN(MATCH(DATOS!$C$26,TABLAS!$B$52:$B$58,0)+2,7)),1)),2))<=MIN(DATOS!$C$28,INT(((DATOS!$C$13-2*R9-2*IF(DATOS!$C$25=0,0,INDEX(TABLAS!$C$52:$C$58,MATCH(DATOS!$C$25,TABLAS!$B$52:$B$58,0))))+MAX(DATOS!$C$32,INDEX(TABLAS!$C$52:$C$58,MIN(MATCH(DATOS!$C$26,TABLAS!$B$52:$B$58,0)+2,7))))/(INDEX(TABLAS!$C$52:$C$58,MIN(MATCH(DATOS!$C$26,TABLAS!$B$52:$B$58,0)+2,7))+MAX(DATOS!$C$32,INDEX(TABLAS!$C$52:$C$58,MIN(MATCH(DATOS!$C$26,TABLAS!$B$52:$B$58,0)+2,7))))))),INDEX(TABLAS!$B$52:$B$58,MIN(MATCH(DATOS!$C$26,TABLAS!$B$52:$B$58,0)+2,7)),IF(AND(BW9>=0,IF(MAX(DATOS!$C$29,CEILING(BW9/INDEX(TABLAS!$D$52:$D$58,MIN(MATCH(DATOS!$C$26,TABLAS!$B$52:$B$58,0)+3,7)),1))*INDEX(TABLAS!$D$52:$D$58,MIN(MATCH(DATOS!$C$26,TABLAS!$B$52:$B$58,0)+3,7))>=4/3*IF(BD9<=0,0,IF((1-2*BD9*1E5/(DATOS!$C$58*Q9*BV9^2*DATOS!$C$48))<0,-1,IF((1-SQRT((1-2*BD9*1E5/(DATOS!$C$58*Q9*BV9^2*DATOS!$C$48))))*DATOS!$C$48*Q9*BV9/DATOS!$C$40>DATOS!$C$82*Q9*BV9,-1,(1-SQRT((1-2*BD9*1E5/(DATOS!$C$58*Q9*BV9^2*DATOS!$C$48))))*DATOS!$C$48*Q9*BV9/DATOS!$C$40)))-0.0001,MAX(DATOS!$C$29,CEILING(BW9/INDEX(TABLAS!$D$52:$D$58,MIN(MATCH(DATOS!$C$26,TABLAS!$B$52:$B$58,0)+3,7)),1)),MAX(MAX(DATOS!$C$29,CEILING(BW9/INDEX(TABLAS!$D$52:$D$58,MIN(MATCH(DATOS!$C$26,TABLAS!$B$52:$B$58,0)+3,7)),1)),2))<=MIN(DATOS!$C$28,INT(((DATOS!$C$13-2*R9-2*IF(DATOS!$C$25=0,0,INDEX(TABLAS!$C$52:$C$58,MATCH(DATOS!$C$25,TABLAS!$B$52:$B$58,0))))+MAX(DATOS!$C$32,INDEX(TABLAS!$C$52:$C$58,MIN(MATCH(DATOS!$C$26,TABLAS!$B$52:$B$58,0)+3,7))))/(INDEX(TABLAS!$C$52:$C$58,MIN(MATCH(DATOS!$C$26,TABLAS!$B$52:$B$58,0)+3,7))+MAX(DATOS!$C$32,INDEX(TABLAS!$C$52:$C$58,MIN(MATCH(DATOS!$C$26,TABLAS!$B$52:$B$58,0)+3,7))))))),INDEX(TABLAS!$B$52:$B$58,MIN(MATCH(DATOS!$C$26,TABLAS!$B$52:$B$58,0)+3,7)),IF(AND(BW9>=0,IF(MAX(DATOS!$C$29,CEILING(BW9/INDEX(TABLAS!$D$52:$D$58,MIN(MATCH(DATOS!$C$26,TABLAS!$B$52:$B$58,0)+4,7)),1))*INDEX(TABLAS!$D$52:$D$58,MIN(MATCH(DATOS!$C$26,TABLAS!$B$52:$B$58,0)+4,7))>=4/3*IF(BD9<=0,0,IF((1-2*BD9*1E5/(DATOS!$C$58*Q9*BV9^2*DATOS!$C$48))<0,-1,IF((1-SQRT((1-2*BD9*1E5/(DATOS!$C$58*Q9*BV9^2*DATOS!$C$48))))*DATOS!$C$48*Q9*BV9/DATOS!$C$40>DATOS!$C$82*Q9*BV9,-1,(1-SQRT((1-2*BD9*1E5/(DATOS!$C$58*Q9*BV9^2*DATOS!$C$48))))*DATOS!$C$48*Q9*BV9/DATOS!$C$40)))-0.0001,MAX(DATOS!$C$29,CEILING(BW9/INDEX(TABLAS!$D$52:$D$58,MIN(MATCH(DATOS!$C$26,TABLAS!$B$52:$B$58,0)+4,7)),1)),MAX(MAX(DATOS!$C$29,CEILING(BW9/INDEX(TABLAS!$D$52:$D$58,MIN(MATCH(DATOS!$C$26,TABLAS!$B$52:$B$58,0)+4,7)),1)),2))<=MIN(DATOS!$C$28,INT(((DATOS!$C$13-2*R9-2*IF(DATOS!$C$25=0,0,INDEX(TABLAS!$C$52:$C$58,MATCH(DATOS!$C$25,TABLAS!$B$52:$B$58,0))))+MAX(DATOS!$C$32,INDEX(TABLAS!$C$52:$C$58,MIN(MATCH(DATOS!$C$26,TABLAS!$B$52:$B$58,0)+4,7))))/(INDEX(TABLAS!$C$52:$C$58,MIN(MATCH(DATOS!$C$26,TABLAS!$B$52:$B$58,0)+4,7))+MAX(DATOS!$C$32,INDEX(TABLAS!$C$52:$C$58,MIN(MATCH(DATOS!$C$26,TABLAS!$B$52:$B$58,0)+4,7))))))),INDEX(TABLAS!$B$52:$B$58,MIN(MATCH(DATOS!$C$26,TABLAS!$B$52:$B$58,0)+4,7)),INDEX(TABLAS!$B$52:$B$58,7)))))) -> 4 | BY9: =IF(D9="HUECO",0,IF(BW9<0,0,IF(MAX(DATOS!$C$29,CEILING(MAX(BW9,0)/INDEX(TABLAS!$D$52:$D$58,MATCH(BX9,TABLAS!$B$52:$B$58,0)),1))*INDEX(TABLAS!$D$52:$D$58,MATCH(BX9,TABLAS!$B$52:$B$58,0))>=4/3*IF(BD9<=0,0,IF((1-2*BD9*1E5/(DATOS!$C$58*Q9*BV9^2*DATOS!$C$48))<0,-1,IF((1-SQRT((1-2*BD9*1E5/(DATOS!$C$58*Q9*BV9^2*DATOS!$C$48))))*DATOS!$C$48*Q9*BV9/DATOS!$C$40>DATOS!$C$82*Q9*BV9,-1,(1-SQRT((1-2*BD9*1E5/(DATOS!$C$58*Q9*BV9^2*DATOS!$C$48))))*DATOS!$C$48*Q9*BV9/DATOS!$C$40)))-0.0001,MAX(DATOS!$C$29,CEILING(MAX(BW9,0)/INDEX(TABLAS!$D$52:$D$58,MATCH(BX9,TABLAS!$B$52:$B$58,0)),1)),MAX(MAX(DATOS!$C$29,CEILING(MAX(BW9,0)/INDEX(TABLAS!$D$52:$D$58,MATCH(BX9,TABLAS!$B$52:$B$58,0)),1)),2)))) -> 1 | BZ9: =DATOS!$C$15-R9-IF(DATOS!$C$25=0,0,INDEX(TABLAS!$C$52:$C$58,MATCH(DATOS!$C$25,TABLAS!$B$52:$B$58,0)))-INDEX(TABLAS!$C$52:$C$58,MATCH(BH9,TABLAS!$B$52:$B$58,0))-INDEX(TABLAS!$C$52:$C$58,MATCH(BX9,TABLAS!$B$52:$B$58,0))/2 -> 19.095 | CA9: =IF(BY9=0,0,DATOS!$C$58*BY9*INDEX(TABLAS!$D$52:$D$58,MATCH(BX9,TABLAS!$B$52:$B$58,0))*DATOS!$C$40*(BZ9-BY9*INDEX(TABLAS!$D$52:$D$58,MATCH(BX9,TABLAS!$B$52:$B$58,0))*DATOS!$C$40/(DATOS!$C$48*Q9)/2)/1E5) -> 0.90806738 | CB9: =IF(BW9<0,9.99,IF(CA9>0,BD9/CA9,0)) -> 0.020958187 | CC9: =IF(BY9=0,"—",0.003*(BZ9-(BY9*INDEX(TABLAS!$D$52:$D$58,MATCH(BX9,TABLAS!$B$52:$B$58,0))*DATOS!$C$40/(DATOS!$C$48*Q9)/DATOS!$C$49))/(BY9*INDEX(TABLAS!$D$52:$D$58,MATCH(BX9,TABLAS!$B$52:$B$58,0))*DATOS!$C$40/(DATOS!$C$48*Q9)/DATOS!$C$49)) -> 0.13278875 | CD9: =((DATOS!$C$15-S9-2*DATOS!$C$35-IF(DATOS!$C$25=0,0,INDEX(TABLAS!$C$52:$C$58,MATCH(DATOS!$C$25,TABLAS!$B$52:$B$58,0)))-INDEX(TABLAS!$C$52:$C$58,MATCH(DATOS!$C$27,TABLAS!$B$52:$B$58,0))-INDEX(TABLAS!$C$52:$C$58,MATCH(DATOS!$C$27,TABLAS!$B$52:$B$58,0))/2)-IF(AND((DATOS!$C$15-S9-2*DATOS!$C$35-IF(DATOS!$C$25=0,0,INDEX(TABLAS!$C$52:$C$58,MATCH(DATOS!$C$25,TABLAS!$B$52:$B$58,0)))-INDEX(TABLAS!$C$52:$C$58,MATCH(DATOS!$C$27,TABLAS!$B$52:$B$58,0))-INDEX(TABLAS!$C$52:$C$58,MATCH(DATOS!$C$27,TABLAS!$B$52:$B$58,0))/2)<=20,DATOS!$C$18<>"SÍ"),2,0)) -> 18.119 | CE9: =IF(D9="HUECO",0,IF(IF(BE9<=0,0,IF((1-2*BE9*1E5/(DATOS!$C$58*DATOS!$C$19*CD9^2*DATOS!$C$48))<0,-1,IF((1-SQRT((1-2*BE9*1E5/(DATOS!$C$58*DATOS!$C$19*CD9^2*DATOS!$C$48))))*DATOS!$C$48*DATOS!$C$19*CD9/DATOS!$C$40>DATOS!$C$82*DATOS!$C$19*CD9,-1,(1-SQRT((1-2*BE9*1E5/(DATOS!$C$58*DATOS!$C$19*CD9^2*DATOS!$C$48))))*DATOS!$C$48*DATOS!$C$19*CD9/DATOS!$C$40)))<0,-1,MAX(IF(BE9<=0,0,IF((1-2*BE9*1E5/(DATOS!$C$58*DATOS!$C$19*CD9^2*DATOS!$C$48))<0,-1,IF((1-SQRT((1-2*BE9*1E5/(DATOS!$C$58*DATOS!$C$19*CD9^2*DATOS!$C$48))))*DATOS!$C$48*DATOS!$C$19*CD9/DATOS!$C$40>DATOS!$C$82*DATOS!$C$19*CD9,-1,(1-SQRT((1-2*BE9*1E5/(DATOS!$C$58*DATOS!$C$19*CD9^2*DATOS!$C$48))))*DATOS!$C$48*DATOS!$C$19*CD9/DATOS!$C$40))),MIN(DATOS!$C$83*DATOS!$C$13*CD9,4/3*IF(BE9<=0,0,IF((1-2*BE9*1E5/(DATOS!$C$58*DATOS!$C$19*CD9^2*DATOS!$C$48))<0,-1,IF((1-SQRT((1-2*BE9*1E5/(DATOS!$C$58*DATOS!$C$19*CD9^2*DATOS!$C$48))))*DATOS!$C$48*DATOS!$C$19*CD9/DATOS!$C$40>DATOS!$C$82*DATOS!$C$19*CD9,-1,(1-SQRT((1-2*BE9*1E5/(DATOS!$C$58*DATOS!$C$19*CD9^2*DATOS!$C$48))))*DATOS!$C$48*DATOS!$C$19*CD9/DATOS!$C$40))))))) -> 0.035466761 | CF9: =IF(AND(CE9>=0,IF(MAX(DATOS!$C$29,CEILING(CE9/INDEX(TABLAS!$D$52:$D$58,MIN(MATCH(DATOS!$C$27,TABLAS!$B$52:$B$58,0)+0,7)),1))*INDEX(TABLAS!$D$52:$D$58,MIN(MATCH(DATOS!$C$27,TABLAS!$B$52:$B$58,0)+0,7))>=4/3*IF(BE9<=0,0,IF((1-2*BE9*1E5/(DATOS!$C$58*DATOS!$C$19*CD9^2*DATOS!$C$48))<0,-1,IF((1-SQRT((1-2*BE9*1E5/(DATOS!$C$58*DATOS!$C$19*CD9^2*DATOS!$C$48))))*DATOS!$C$48*DATOS!$C$19*CD9/DATOS!$C$40>DATOS!$C$82*DATOS!$C$19*CD9,-1,(1-SQRT((1-2*BE9*1E5/(DATOS!$C$58*DATOS!$C$19*CD9^2*DATOS!$C$48))))*DATOS!$C$48*DATOS!$C$19*CD9/DATOS!$C$40)))-0.0001,MAX(DATOS!$C$29,CEILING(CE9/INDEX(TABLAS!$D$52:$D$58,MIN(MATCH(DATOS!$C$27,TABLAS!$B$52:$B$58,0)+0,7)),1)),MAX(MAX(DATOS!$C$29,CEILING(CE9/INDEX(TABLAS!$D$52:$D$58,MIN(MATCH(DATOS!$C$27,TABLAS!$B$52:$B$58,0)+0,7)),1)),2))<=MIN(DATOS!$C$28,INT(((DATOS!$C$13-2*S9-2*IF(DATOS!$C$25=0,0,INDEX(TABLAS!$C$52:$C$58,MATCH(DATOS!$C$25,TABLAS!$B$52:$B$58,0))))+MAX(DATOS!$C$32,INDEX(TABLAS!$C$52:$C$58,MIN(MATCH(DATOS!$C$27,TABLAS!$B$52:$B$58,0)+0,7))))/(INDEX(TABLAS!$C$52:$C$58,MIN(MATCH(DATOS!$C$27,TABLAS!$B$52:$B$58,0)+0,7))+MAX(DATOS!$C$32,INDEX(TABLAS!$C$52:$C$58,MIN(MATCH(DATOS!$C$27,TABLAS!$B$52:$B$58,0)+0,7))))))),INDEX(TABLAS!$B$52:$B$58,MIN(MATCH(DATOS!$C$27,TABLAS!$B$52:$B$58,0)+0,7)),IF(AND(CE9>=0,IF(MAX(DATOS!$C$29,CEILING(CE9/INDEX(TABLAS!$D$52:$D$58,MIN(MATCH(DATOS!$C$27,TABLAS!$B$52:$B$58,0)+1,7)),1))*INDEX(TABLAS!$D$52:$D$58,MIN(MATCH(DATOS!$C$27,TABLAS!$B$52:$B$58,0)+1,7))>=4/3*IF(BE9<=0,0,IF((1-2*BE9*1E5/(DATOS!$C$58*DATOS!$C$19*CD9^2*DATOS!$C$48))<0,-1,IF((1-SQRT((1-2*BE9*1E5/(DATOS!$C$58*DATOS!$C$19*CD9^2*DATOS!$C$48))))*DATOS!$C$48*DATOS!$C$19*CD9/DATOS!$C$40>DATOS!$C$82*DATOS!$C$19*CD9,-1,(1-SQRT((1-2*BE9*1E5/(DATOS!$C$58*DATOS!$C$19*CD9^2*DATOS!$C$48))))*DATOS!$C$48*DATOS!$C$19*CD9/DATOS!$C$40)))-0.0001,MAX(DATOS!$C$29,CEILING(CE9/INDEX(TABLAS!$D$52:$D$58,MIN(MATCH(DATOS!$C$27,TABLAS!$B$52:$B$58,0)+1,7)),1)),MAX(MAX(DATOS!$C$29,CEILING(CE9/INDEX(TABLAS!$D$52:$D$58,MIN(MATCH(DATOS!$C$27,TABLAS!$B$52:$B$58,0)+1,7)),1)),2))<=MIN(DATOS!$C$28,INT(((DATOS!$C$13-2*S9-2*IF(DATOS!$C$25=0,0,INDEX(TABLAS!$C$52:$C$58,MATCH(DATOS!$C$25,TABLAS!$B$52:$B$58,0))))+MAX(DATOS!$C$32,INDEX(TABLAS!$C$52:$C$58,MIN(MATCH(DATOS!$C$27,TABLAS!$B$52:$B$58,0)+1,7))))/(INDEX(TABLAS!$C$52:$C$58,MIN(MATCH(DATOS!$C$27,TABLAS!$B$52:$B$58,0)+1,7))+MAX(DATOS!$C$32,INDEX(TABLAS!$C$52:$C$58,MIN(MATCH(DATOS!$C$27,TABLAS!$B$52:$B$58,0)+1,7))))))),INDEX(TABLAS!$B$52:$B$58,MIN(MATCH(DATOS!$C$27,TABLAS!$B$52:$B$58,0)+1,7)),IF(AND(CE9>=0,IF(MAX(DATOS!$C$29,CEILING(CE9/INDEX(TABLAS!$D$52:$D$58,MIN(MATCH(DATOS!$C$27,TABLAS!$B$52:$B$58,0)+2,7)),1))*INDEX(TABLAS!$D$52:$D$58,MIN(MATCH(DATOS!$C$27,TABLAS!$B$52:$B$58,0)+2,7))>=4/3*IF(BE9<=0,0,IF((1-2*BE9*1E5/(DATOS!$C$58*DATOS!$C$19*CD9^2*DATOS!$C$48))<0,-1,IF((1-SQRT((1-2*BE9*1E5/(DATOS!$C$58*DATOS!$C$19*CD9^2*DATOS!$C$48))))*DATOS!$C$48*DATOS!$C$19*CD9/DATOS!$C$40>DATOS!$C$82*DATOS!$C$19*CD9,-1,(1-SQRT((1-2*BE9*1E5/(DATOS!$C$58*DATOS!$C$19*CD9^2*DATOS!$C$48))))*DATOS!$C$48*DATOS!$C$19*CD9/DATOS!$C$40)))-0.0001,MAX(DATOS!$C$29,CEILING(CE9/INDEX(TABLAS!$D$52:$D$58,MIN(MATCH(DATOS!$C$27,TABLAS!$B$52:$B$58,0)+2,7)),1)),MAX(MAX(DATOS!$C$29,CEILING(CE9/INDEX(TABLAS!$D$52:$D$58,MIN(MATCH(DATOS!$C$27,TABLAS!$B$52:$B$58,0)+2,7)),1)),2))<=MIN(DATOS!$C$28,INT(((DATOS!$C$13-2*S9-2*IF(DATOS!$C$25=0,0,INDEX(TABLAS!$C$52:$C$58,MATCH(DATOS!$C$25,TABLAS!$B$52:$B$58,0))))+MAX(DATOS!$C$32,INDEX(TABLAS!$C$52:$C$58,MIN(MATCH(DATOS!$C$27,TABLAS!$B$52:$B$58,0)+2,7))))/(INDEX(TABLAS!$C$52:$C$58,MIN(MATCH(DATOS!$C$27,TABLAS!$B$52:$B$58,0)+2,7))+MAX(DATOS!$C$32,INDEX(TABLAS!$C$52:$C$58,MIN(MATCH(DATOS!$C$27,TABLAS!$B$52:$B$58,0)+2,7))))))),INDEX(TABLAS!$B$52:$B$58,MIN(MATCH(DATOS!$C$27,TABLAS!$B$52:$B$58,0)+2,7)),IF(AND(CE9>=0,IF(MAX(DATOS!$C$29,CEILING(CE9/INDEX(TABLAS!$D$52:$D$58,MIN(MATCH(DATOS!$C$27,TABLAS!$B$52:$B$58,0)+3,7)),1))*INDEX(TABLAS!$D$52:$D$58,MIN(MATCH(DATOS!$C$27,TABLAS!$B$52:$B$58,0)+3,7))>=4/3*IF(BE9<=0,0,IF((1-2*BE9*1E5/(DATOS!$C$58*DATOS!$C$19*CD9^2*DATOS!$C$48))<0,-1,IF((1-SQRT((1-2*BE9*1E5/(DATOS!$C$58*DATOS!$C$19*CD9^2*DATOS!$C$48))))*DATOS!$C$48*DATOS!$C$19*CD9/DATOS!$C$40>DATOS!$C$82*DATOS!$C$19*CD9,-1,(1-SQRT((1-2*BE9*1E5/(DATOS!$C$58*DATOS!$C$19*CD9^2*DATOS!$C$48))))*DATOS!$C$48*DATOS!$C$19*CD9/DATOS!$C$40)))-0.0001,MAX(DATOS!$C$29,CEILING(CE9/INDEX(TABLAS!$D$52:$D$58,MIN(MATCH(DATOS!$C$27,TABLAS!$B$52:$B$58,0)+3,7)),1)),MAX(MAX(DATOS!$C$29,CEILING(CE9/INDEX(TABLAS!$D$52:$D$58,MIN(MATCH(DATOS!$C$27,TABLAS!$B$52:$B$58,0)+3,7)),1)),2))<=MIN(DATOS!$C$28,INT(((DATOS!$C$13-2*S9-2*IF(DATOS!$C$25=0,0,INDEX(TABLAS!$C$52:$C$58,MATCH(DATOS!$C$25,TABLAS!$B$52:$B$58,0))))+MAX(DATOS!$C$32,INDEX(TABLAS!$C$52:$C$58,MIN(MATCH(DATOS!$C$27,TABLAS!$B$52:$B$58,0)+3,7))))/(INDEX(TABLAS!$C$52:$C$58,MIN(MATCH(DATOS!$C$27,TABLAS!$B$52:$B$58,0)+3,7))+MAX(DATOS!$C$32,INDEX(TABLAS!$C$52:$C$58,MIN(MATCH(DATOS!$C$27,TABLAS!$B$52:$B$58,0)+3,7))))))),INDEX(TABLAS!$B$52:$B$58,MIN(MATCH(DATOS!$C$27,TABLAS!$B$52:$B$58,0)+3,7)),IF(AND(CE9>=0,IF(MAX(DATOS!$C$29,CEILING(CE9/INDEX(TABLAS!$D$52:$D$58,MIN(MATCH(DATOS!$C$27,TABLAS!$B$52:$B$58,0)+4,7)),1))*INDEX(TABLAS!$D$52:$D$58,MIN(MATCH(DATOS!$C$27,TABLAS!$B$52:$B$58,0)+4,7))>=4/3*IF(BE9<=0,0,IF((1-2*BE9*1E5/(DATOS!$C$58*DATOS!$C$19*CD9^2*DATOS!$C$48))<0,-1,IF((1-SQRT((1-2*BE9*1E5/(DATOS!$C$58*DATOS!$C$19*CD9^2*DATOS!$C$48))))*DATOS!$C$48*DATOS!$C$19*CD9/DATOS!$C$40>DATOS!$C$82*DATOS!$C$19*CD9,-1,(1-SQRT((1-2*BE9*1E5/(DATOS!$C$58*DATOS!$C$19*CD9^2*DATOS!$C$48))))*DATOS!$C$48*DATOS!$C$19*CD9/DATOS!$C$40)))-0.0001,MAX(DATOS!$C$29,CEILING(CE9/INDEX(TABLAS!$D$52:$D$58,MIN(MATCH(DATOS!$C$27,TABLAS!$B$52:$B$58,0)+4,7)),1)),MAX(MAX(DATOS!$C$29,CEILING(CE9/INDEX(TABLAS!$D$52:$D$58,MIN(MATCH(DATOS!$C$27,TABLAS!$B$52:$B$58,0)+4,7)),1)),2))<=MIN(DATOS!$C$28,INT(((DATOS!$C$13-2*S9-2*IF(DATOS!$C$25=0,0,INDEX(TABLAS!$C$52:$C$58,MATCH(DATOS!$C$25,TABLAS!$B$52:$B$58,0))))+MAX(DATOS!$C$32,INDEX(TABLAS!$C$52:$C$58,MIN(MATCH(DATOS!$C$27,TABLAS!$B$52:$B$58,0)+4,7))))/(INDEX(TABLAS!$C$52:$C$58,MIN(MATCH(DATOS!$C$27,TABLAS!$B$52:$B$58,0)+4,7))+MAX(DATOS!$C$32,INDEX(TABLAS!$C$52:$C$58,MIN(MATCH(DATOS!$C$27,TABLAS!$B$52:$B$58,0)+4,7))))))),INDEX(TABLAS!$B$52:$B$58,MIN(MATCH(DATOS!$C$27,TABLAS!$B$52:$B$58,0)+4,7)),INDEX(TABLAS!$B$52:$B$58,7)))))) -> 4 | CG9: =IF(D9="HUECO",0,IF(CE9<0,0,IF(MAX(DATOS!$C$29,CEILING(MAX(CE9,0)/INDEX(TABLAS!$D$52:$D$58,MATCH(CF9,TABLAS!$B$52:$B$58,0)),1))*INDEX(TABLAS!$D$52:$D$58,MATCH(CF9,TABLAS!$B$52:$B$58,0))>=4/3*IF(BE9<=0,0,IF((1-2*BE9*1E5/(DATOS!$C$58*DATOS!$C$19*CD9^2*DATOS!$C$48))<0,-1,IF((1-SQRT((1-2*BE9*1E5/(DATOS!$C$58*DATOS!$C$19*CD9^2*DATOS!$C$48))))*DATOS!$C$48*DATOS!$C$19*CD9/DATOS!$C$40>DATOS!$C$82*DATOS!$C$19*CD9,-1,(1-SQRT((1-2*BE9*1E5/(DATOS!$C$58*DATOS!$C$19*CD9^2*DATOS!$C$48))))*DATOS!$C$48*DATOS!$C$19*CD9/DATOS!$C$40)))-0.0001,MAX(DATOS!$C$29,CEILING(MAX(CE9,0)/INDEX(TABLAS!$D$52:$D$58,MATCH(CF9,TABLAS!$B$52:$B$58,0)),1)),MAX(MAX(DATOS!$C$29,CEILING(MAX(CE9,0)/INDEX(TABLAS!$D$52:$D$58,MATCH(CF9,TABLAS!$B$52:$B$58,0)),1)),2)))) -> 1 | CH9: =((DATOS!$C$15-S9-2*DATOS!$C$35-IF(DATOS!$C$25=0,0,INDEX(TABLAS!$C$52:$C$58,MATCH(DATOS!$C$25,TABLAS!$B$52:$B$58,0)))-INDEX(TABLAS!$C$52:$C$58,MATCH(BP9,TABLAS!$B$52:$B$58,0))-INDEX(TABLAS!$C$52:$C$58,MATCH(CF9,TABLAS!$B$52:$B$58,0))/2)-IF(AND((DATOS!$C$15-S9-2*DATOS!$C$35-IF(DATOS!$C$25=0,0,INDEX(TABLAS!$C$52:$C$58,MATCH(DATOS!$C$25,TABLAS!$B$52:$B$58,0)))-INDEX(TABLAS!$C$52:$C$58,MATCH(BP9,TABLAS!$B$52:$B$58,0))-INDEX(TABLAS!$C$52:$C$58,MATCH(CF9,TABLAS!$B$52:$B$58,0))/2)<=20,DATOS!$C$18<>"SÍ"),2,0)) -> 18.119 | CI9: =IF(CG9=0,0,DATOS!$C$58*CG9*INDEX(TABLAS!$D$52:$D$58,MATCH(CF9,TABLAS!$B$52:$B$58,0))*DATOS!$C$40*(CH9-CG9*INDEX(TABLAS!$D$52:$D$58,MATCH(CF9,TABLAS!$B$52:$B$58,0))*DATOS!$C$40/(DATOS!$C$48*DATOS!$C$19)/2)/1E5) -> 0.80957036 | CJ9: =IF(CE9<0,9.99,IF(CI9>0,BE9/CI9,0)) -> 0.022471066 | CK9: =IF(CG9=0,"—",0.003*(CH9-(CG9*INDEX(TABLAS!$D$52:$D$58,MATCH(CF9,TABLAS!$B$52:$B$58,0))*DATOS!$C$40/(DATOS!$C$48*DATOS!$C$19)/DATOS!$C$49))/(CG9*INDEX(TABLAS!$D$52:$D$58,MATCH(CF9,TABLAS!$B$52:$B$58,0))*DATOS!$C$40/(DATOS!$C$48*DATOS!$C$19)/DATOS!$C$49)) -> 0.015406886 | CL9: =IF(D9="HUECO","—",IF(AND(D9="PERIMETRAL",J9*100>=6*DATOS!$C$11,DATOS!$C$11<=80,DATOS!$C$13>=10,DATOS!$C$15<=3.5*DATOS!$C$13,DATOS!$C$14>=MAX(DATOS!$C$11/13,5)),"SÍ","NO")) -> NO | CM9: =IF(D9="PERIMETRAL",MAX(0,(N9/2-BR9)/100)*(0.95-0.5*L9)*Y9*IF(AND(Z9>0,Z9<4),DATOS!$C$63,1)*DATOS!$C$16/100/1000+AX9,IF(D9="VOLADO",(Y9*MAX(0,N9-BR9)/100+DATOS!$C$55*BA9)*DATOS!$C$16/100/1000,0)) -> 0.14141879 | CN9: =IF(D9="HUECO",0,DATOS!$C$59*2*MIN(1,SQRT(2/(1+0.04*BR9)))*(BQ9*INDEX(TABLAS!$D$52:$D$58,MATCH(BP9,TABLAS!$B$52:$B$58,0))/(DATOS!$C$19*BR9))^(1/3)*SQRT(DATOS!$C$39)*DATOS!$C$19*BR9*IF(CL9="SÍ",DATOS!$C$62,1)/1000) -> 0.8603981 | CO9: =IF(D9="HUECO","—",IF(CM9<=CN9,"CUMPLE",IF(MAX(0,CEILING((IF(D9="VOLADO",(N9-(CN9*1E5/DATOS!$C$16-DATOS!$C$55*BA9)*100/Y9),IF(CN9<=AX9,N9,N9/2-(CN9-AX9)/MAX(CM9-AX9,1E-9)*(N9/2-BR9)))-IF(INT((J9*100-DATOS!$C$17+DATOS!$C$13)/DATOS!$C$16)>0,(J9*100-DATOS!$C$17-(INT((J9*100-DATOS!$C$17+DATOS!$C$13)/DATOS!$C$16)*DATOS!$C$11+(INT((J9*100-DATOS!$C$17+DATOS!$C$13)/DATOS!$C$16)-1)*DATOS!$C$13))/2,J9*100/2))/DATOS!$C$16,1))<=0,"CUMPLE (basta el macizo de orilla)","MACIZAR "&MAX(0,CEILING((IF(D9="VOLADO",(N9-(CN9*1E5/DATOS!$C$16-DATOS!$C$55*BA9)*100/Y9),IF(CN9<=AX9,N9,N9/2-(CN9-AX9)/MAX(CM9-AX9,1E-9)*(N9/2-BR9)))-IF(INT((J9*100-DATOS!$C$17+DATOS!$C$13)/DATOS!$C$16)>0,(J9*100-DATOS!$C$17-(INT((J9*100-DATOS!$C$17+DATOS!$C$13)/DATOS!$C$16)*DATOS!$C$11+(INT((J9*100-DATOS!$C$17+DATOS!$C$13)/DATOS!$C$16)-1)*DATOS!$C$13))/2,J9*100/2))/DATOS!$C$16,1))&" hilera(s)"))) -> CUMPLE | CP9: =IF(D9="PERIMETRAL",((PRINCIPALES!$N$9*PRINCIPALES!$O$9^3/12/(1.002*100*IF(APOYOS!$G$29="CONTINUO",1,0.5)*DATOS!$C$77^3/12))+(PRINCIPALES!$N$10*PRINCIPALES!$O$10^3/12/(1.002*100*IF(APOYOS!$G$30="CONTINUO",1,0.5)*DATOS!$C$77^3/12))+99+(PRINCIPALES!$N$28*PRINCIPALES!$O$28^3/12/(4.327*100*IF(APOYOS!$G$32="CONTINUO",1,0.5)*DATOS!$C$77^3/12)))/4,0) -> 30.662737 | CQ9: =IF(D9="PERIMETRAL",IF(CP9>2,MAX(9,O9*(0.8+DATOS!$C$40/14000)/(36+9*(O9/MAX(N9,1)))),IF(CP9>0.2,MAX(13,O9*(0.8+DATOS!$C$40/14000)/(36+5*(O9/MAX(N9,1))*(CP9-0.2))),MAX(13,O9/IF(Z9>0,30,33))))*IF(AND(CP9>0.2,OR(AND((APOYOS!$G$29="DISCONTINUO"),(PRINCIPALES!$N$9*PRINCIPALES!$O$9^3/12/(1.002*100*IF(APOYOS!$G$29="CONTINUO",1,0.5)*DATOS!$C$77^3/12))<0.8),AND((APOYOS!$G$30="DISCONTINUO"),(PRINCIPALES!$N$10*PRINCIPALES!$O$10^3/12/(1.002*100*IF(APOYOS!$G$30="CONTINUO",1,0.5)*DATOS!$C$77^3/12))<0.8),AND((APOYOS!$G$31="DISCONTINUO"),99<0.8),AND((APOYOS!$G$32="DISCONTINUO"),(PRINCIPALES!$N$28*PRINCIPALES!$O$28^3/12/(4.327*100*IF(APOYOS!$G$32="CONTINUO",1,0.5)*DATOS!$C$77^3/12))<0.8))),1.1,1),IF(D9="VOLADO",MAX(25,J9*100/8),0)) -> 9.9 | CR9: =IF(D9="VOLADO",DATOS!$C$15,DATOS!$C$77) -> 16.723256 | CS9: =IF(D9="HUECO","—",IF(CR9>=CQ9,"CUMPLE",IF(D9="VOLADO","NO CUMPLE","CALCULAR FLECHA"))) -> CUMPLE | CT9: =IF(D9="HUECO","—",IF(DATOS!$C$14>=IF(IF(D9="VOLADO",J9,K9)>=6,6,5),"CUMPLE","CAPA ≥ 6 cm")) -> CUMPLE | CU9: =IF(D9="HUECO",0,IF(((4*((AL9*Y9*J9^2*1E-4*DATOS!$C$16/100/1000)+((MAX(AH9,AJ9)*Y9*J9^2*1E-4*DATOS!$C$16/100/1000)+(IF(AND(AH9>0,AJ9>0),MIN(AH9,AJ9),MAX(AH9,AJ9))*Y9*J9^2*1E-4*DATOS!$C$16/100/1000))/2)+BC9-(IF(AND(AH9>0,AJ9>0),MIN(AH9,AJ9),MAX(AH9,AJ9))*Y9*J9^2*1E-4*DATOS!$C$16/100/1000))^2-16*((AL9*Y9*J9^2*1E-4*DATOS!$C$16/100/1000)+((MAX(AH9,AJ9)*Y9*J9^2*1E-4*DATOS!$C$16/100/1000)+(IF(AND(AH9>0,AJ9>0),MIN(AH9,AJ9),MAX(AH9,AJ9))*Y9*J9^2*1E-4*DATOS!$C$16/100/1000))/2)*BC9)<0,CEILING(N9,5),CEILING(MAX(N9*((4*((AL9*Y9*J9^2*1E-4*DATOS!$C$16/100/1000)+((MAX(AH9,AJ9)*Y9*J9^2*1E-4*DATOS!$C$16/100/1000)+(IF(AND(AH9>0,AJ9>0),MIN(AH9,AJ9),MAX(AH9,AJ9))*Y9*J9^2*1E-4*DATOS!$C$16/100/1000))/2)+BC9-(IF(AND(AH9>0,AJ9>0),MIN(AH9,AJ9),MAX(AH9,AJ9))*Y9*J9^2*1E-4*DATOS!$C$16/100/1000))-SQRT(MAX(0,((4*((AL9*Y9*J9^2*1E-4*DATOS!$C$16/100/1000)+((MAX(AH9,AJ9)*Y9*J9^2*1E-4*DATOS!$C$16/100/1000)+(IF(AND(AH9>0,AJ9>0),MIN(AH9,AJ9),MAX(AH9,AJ9))*Y9*J9^2*1E-4*DATOS!$C$16/100/1000))/2)+BC9-(IF(AND(AH9>0,AJ9>0),MIN(AH9,AJ9),MAX(AH9,AJ9))*Y9*J9^2*1E-4*DATOS!$C$16/100/1000))^2-16*((AL9*Y9*J9^2*1E-4*DATOS!$C$16/100/1000)+((MAX(AH9,AJ9)*Y9*J9^2*1E-4*DATOS!$C$16/100/1000)+(IF(AND(AH9>0,AJ9>0),MIN(AH9,AJ9),MAX(AH9,AJ9))*Y9*J9^2*1E-4*DATOS!$C$16/100/1000))/2)*BC9))))/(8*MAX(((AL9*Y9*J9^2*1E-4*DATOS!$C$16/100/1000)+((MAX(AH9,AJ9)*Y9*J9^2*1E-4*DATOS!$C$16/100/1000)+(IF(AND(AH9>0,AJ9>0),MIN(AH9,AJ9),MAX(AH9,AJ9))*Y9*J9^2*1E-4*DATOS!$C$16/100/1000))/2),1E-9))+MAX(BR9,12*INDEX(TABLAS!$C$52:$C$58,MATCH(BP9,TABLAS!$B$52:$B$58,0)),N9/16),IF(OR(S9<INDEX(TABLAS!$C$52:$C$58,MATCH(BP9,TABLAS!$B$52:$B$58,0)),AND(BQ9>=2,(DATOS!$C$13-2*S9-2*IF(DATOS!$C$25=0,0,INDEX(TABLAS!$C$52:$C$58,MATCH(DATOS!$C$25,TABLAS!$B$52:$B$58,0)))-BQ9*INDEX(TABLAS!$C$52:$C$58,MATCH(BP9,TABLAS!$B$52:$B$58,0)))/MAX(BQ9-1,1)<2*INDEX(TABLAS!$C$52:$C$58,MATCH(BP9,TABLAS!$B$52:$B$58,0)))),INDEX(TABLAS!$I$52:$I$58,MATCH(BP9,TABLAS!$B$52:$B$58,0)),INDEX(TABLAS!$F$52:$F$58,MATCH(BP9,TABLAS!$B$52:$B$58,0)))),5))) -> 90 | CV9: =IF(D9="HUECO",0,IF(((4*((AM9*Y9*J9^2*1E-4*DATOS!$C$16/100/1000)+((MAX(AI9,AK9)*Y9*J9^2*1E-4*DATOS!$C$16/100/1000)+(IF(AND(AI9>0,AK9>0),MIN(AI9,AK9),MAX(AI9,AK9))*Y9*J9^2*1E-4*DATOS!$C$16/100/1000))/2)+BE9-(IF(AND(AI9>0,AK9>0),MIN(AI9,AK9),MAX(AI9,AK9))*Y9*J9^2*1E-4*DATOS!$C$16/100/1000))^2-16*((AM9*Y9*J9^2*1E-4*DATOS!$C$16/100/1000)+((MAX(AI9,AK9)*Y9*J9^2*1E-4*DATOS!$C$16/100/1000)+(IF(AND(AI9>0,AK9>0),MIN(AI9,AK9),MAX(AI9,AK9))*Y9*J9^2*1E-4*DATOS!$C$16/100/1000))/2)*BE9)<0,CEILING(O9,5),CEILING(MAX(O9*((4*((AM9*Y9*J9^2*1E-4*DATOS!$C$16/100/1000)+((MAX(AI9,AK9)*Y9*J9^2*1E-4*DATOS!$C$16/100/1000)+(IF(AND(AI9>0,AK9>0),MIN(AI9,AK9),MAX(AI9,AK9))*Y9*J9^2*1E-4*DATOS!$C$16/100/1000))/2)+BE9-(IF(AND(AI9>0,AK9>0),MIN(AI9,AK9),MAX(AI9,AK9))*Y9*J9^2*1E-4*DATOS!$C$16/100/1000))-SQRT(MAX(0,((4*((AM9*Y9*J9^2*1E-4*DATOS!$C$16/100/1000)+((MAX(AI9,AK9)*Y9*J9^2*1E-4*DATOS!$C$16/100/1000)+(IF(AND(AI9>0,AK9>0),MIN(AI9,AK9),MAX(AI9,AK9))*Y9*J9^2*1E-4*DATOS!$C$16/100/1000))/2)+BE9-(IF(AND(AI9>0,AK9>0),MIN(AI9,AK9),MAX(AI9,AK9))*Y9*J9^2*1E-4*DATOS!$C$16/100/1000))^2-16*((AM9*Y9*J9^2*1E-4*DATOS!$C$16/100/1000)+((MAX(AI9,AK9)*Y9*J9^2*1E-4*DATOS!$C$16/100/1000)+(IF(AND(AI9>0,AK9>0),MIN(AI9,AK9),MAX(AI9,AK9))*Y9*J9^2*1E-4*DATOS!$C$16/100/1000))/2)*BE9))))/(8*MAX(((AM9*Y9*J9^2*1E-4*DATOS!$C$16/100/1000)+((MAX(AI9,AK9)*Y9*J9^2*1E-4*DATOS!$C$16/100/1000)+(IF(AND(AI9>0,AK9>0),MIN(AI9,AK9),MAX(AI9,AK9))*Y9*J9^2*1E-4*DATOS!$C$16/100/1000))/2),1E-9))+MAX(CH9,12*INDEX(TABLAS!$C$52:$C$58,MATCH(CF9,TABLAS!$B$52:$B$58,0)),O9/16),IF(OR(S9<INDEX(TABLAS!$C$52:$C$58,MATCH(CF9,TABLAS!$B$52:$B$58,0)),AND(CG9>=2,(DATOS!$C$13-2*S9-2*IF(DATOS!$C$25=0,0,INDEX(TABLAS!$C$52:$C$58,MATCH(DATOS!$C$25,TABLAS!$B$52:$B$58,0)))-CG9*INDEX(TABLAS!$C$52:$C$58,MATCH(CF9,TABLAS!$B$52:$B$58,0)))/MAX(CG9-1,1)<2*INDEX(TABLAS!$C$52:$C$58,MATCH(CF9,TABLAS!$B$52:$B$58,0)))),INDEX(TABLAS!$I$52:$I$58,MATCH(CF9,TABLAS!$B$52:$B$58,0)),INDEX(TABLAS!$F$52:$F$58,MATCH(CF9,TABLAS!$B$52:$B$58,0)))),5))) -> 90 | CW9: =MAX(0,INT((F9*100-DATOS!$C$17+DATOS!$C$13)/DATOS!$C$16)) -> 6 | CX9: =MAX(0,INT((G9*100-DATOS!$C$17+DATOS!$C$13)/DATOS!$C$16)) -> 1 | CY9: =IF(COUNTIFS(TRIB!$C$6:$C$255,B9,TRIB!$K$6:$K$255,"NO CUMPLE*")+COUNTIFS(TRIB!$C$6:$C$255,B9,TRIB!$K$6:$K$255,"SIN APOYO*")>0,"VER PRINCIPALES",IF((APOYOS!$F$29="LIBRE")+(APOYOS!$F$30="LIBRE")+(APOYOS!$F$31="LIBRE")+(APOYOS!$F$32="LIBRE")>0,"REVISAR: borde libre","OK")) -> OK | CZ9: =IF(D9="HUECO","HUECO — marco de nervaduras principales",IF(AND(MAX(BL9,BT9,CB9,CJ9)<=1,NOT(OR(BI9>MIN(DATOS!$C$28,INT(((DATOS!$C$13-2*R9-2*IF(DATOS!$C$25=0,0,INDEX(TABLAS!$C$52:$C$58,MATCH(DATOS!$C$25,TABLAS!$B$52:$B$58,0))))+DATOS!$C$32)/(INDEX(TABLAS!$C$52:$C$58,MATCH(BH9,TABLAS!$B$52:$B$58,0))+DATOS!$C$32))),BQ9>MIN(DATOS!$C$28,INT(((DATOS!$C$13-2*S9-2*IF(DATOS!$C$25=0,0,INDEX(TABLAS!$C$52:$C$58,MATCH(DATOS!$C$25,TABLAS!$B$52:$B$58,0))))+DATOS!$C$32)/(INDEX(TABLAS!$C$52:$C$58,MATCH(BP9,TABLAS!$B$52:$B$58,0))+DATOS!$C$32))),BY9>MIN(DATOS!$C$28,INT(((DATOS!$C$13-2*R9-2*IF(DATOS!$C$25=0,0,INDEX(TABLAS!$C$52:$C$58,MATCH(DATOS!$C$25,TABLAS!$B$52:$B$58,0))))+DATOS!$C$32)/(INDEX(TABLAS!$C$52:$C$58,MATCH(BX9,TABLAS!$B$52:$B$58,0))+DATOS!$C$32))),CG9>MIN(DATOS!$C$28,INT(((DATOS!$C$13-2*S9-2*IF(DATOS!$C$25=0,0,INDEX(TABLAS!$C$52:$C$58,MATCH(DATOS!$C$25,TABLAS!$B$52:$B$58,0))))+DATOS!$C$32)/(INDEX(TABLAS!$C$52:$C$58,MATCH(CF9,TABLAS!$B$52:$B$58,0))+DATOS!$C$32))))),NOT(OR(AND(ISNUMBER(BM9),BM9<0.005),AND(ISNUMBER(BU9),BU9<0.005),AND(ISNUMBER(CC9),CC9<0.005),AND(ISNUMBER(CK9),CK9<0.005))),CS9="CUMPLE",CT9="CUMPLE"),IF(CY9="OK",IF(LEFT(CO9,6)="CUMPLE","CUMPLE","CUMPLE — "&CO9)&IF(LEFT(AZ9,5)="FUERA"," · fuera de 3.4.2.1 c)",""),IF(CY9="VER PRINCIPALES","VER PRINCIPALES","REVISAR APOYOS")),IF(AND(MAX(BL9,BT9,CB9,CJ9)<=1,NOT(OR(BI9>MIN(DATOS!$C$28,INT(((DATOS!$C$13-2*R9-2*IF(DATOS!$C$25=0,0,INDEX(TABLAS!$C$52:$C$58,MATCH(DATOS!$C$25,TABLAS!$B$52:$B$58,0))))+DATOS!$C$32)/(INDEX(TABLAS!$C$52:$C$58,MATCH(BH9,TABLAS!$B$52:$B$58,0))+DATOS!$C$32))),BQ9>MIN(DATOS!$C$28,INT(((DATOS!$C$13-2*S9-2*IF(DATOS!$C$25=0,0,INDEX(TABLAS!$C$52:$C$58,MATCH(DATOS!$C$25,TABLAS!$B$52:$B$58,0))))+DATOS!$C$32)/(INDEX(TABLAS!$C$52:$C$58,MATCH(BP9,TABLAS!$B$52:$B$58,0))+DATOS!$C$32))),BY9>MIN(DATOS!$C$28,INT(((DATOS!$C$13-2*R9-2*IF(DATOS!$C$25=0,0,INDEX(TABLAS!$C$52:$C$58,MATCH(DATOS!$C$25,TABLAS!$B$52:$B$58,0))))+DATOS!$C$32)/(INDEX(TABLAS!$C$52:$C$58,MATCH(BX9,TABLAS!$B$52:$B$58,0))+DATOS!$C$32))),CG9>MIN(DATOS!$C$28,INT(((DATOS!$C$13-2*S9-2*IF(DATOS!$C$25=0,0,INDEX(TABLAS!$C$52:$C$58,MATCH(DATOS!$C$25,TABLAS!$B$52:$B$58,0))))+DATOS!$C$32)/(INDEX(TABLAS!$C$52:$C$58,MATCH(CF9,TABLAS!$B$52:$B$58,0))+DATOS!$C$32))))),NOT(OR(AND(ISNUMBER(BM9),BM9<0.005),AND(ISNUMBER(BU9),BU9<0.005),AND(ISNUMBER(CC9),CC9<0.005),AND(ISNUMBER(CK9),CK9<0.005))),CS9="CALCULAR FLECHA"),"REVISAR: calcular flecha (h_eq < h mín.)","NO CUMPLE: "&IF(MAX(BL9,BT9,CB9,CJ9)>1,"flexión ","")&IF(OR(BI9>MIN(DATOS!$C$28,INT(((DATOS!$C$13-2*R9-2*IF(DATOS!$C$25=0,0,INDEX(TABLAS!$C$52:$C$58,MATCH(DATOS!$C$25,TABLAS!$B$52:$B$58,0))))+DATOS!$C$32)/(INDEX(TABLAS!$C$52:$C$58,MATCH(BH9,TABLAS!$B$52:$B$58,0))+DATOS!$C$32))),BQ9>MIN(DATOS!$C$28,INT(((DATOS!$C$13-2*S9-2*IF(DATOS!$C$25=0,0,INDEX(TABLAS!$C$52:$C$58,MATCH(DATOS!$C$25,TABLAS!$B$52:$B$58,0))))+DATOS!$C$32)/(INDEX(TABLAS!$C$52:$C$58,MATCH(BP9,TABLAS!$B$52:$B$58,0))+DATOS!$C$32))),BY9>MIN(DATOS!$C$28,INT(((DATOS!$C$13-2*R9-2*IF(DATOS!$C$25=0,0,INDEX(TABLAS!$C$52:$C$58,MATCH(DATOS!$C$25,TABLAS!$B$52:$B$58,0))))+DATOS!$C$32)/(INDEX(TABLAS!$C$52:$C$58,MATCH(BX9,TABLAS!$B$52:$B$58,0))+DATOS!$C$32))),CG9>MIN(DATOS!$C$28,INT(((DATOS!$C$13-2*S9-2*IF(DATOS!$C$25=0,0,INDEX(TABLAS!$C$52:$C$58,MATCH(DATOS!$C$25,TABLAS!$B$52:$B$58,0))))+DATOS!$C$32)/(INDEX(TABLAS!$C$52:$C$58,MATCH(CF9,TABLAS!$B$52:$B$58,0))+DATOS!$C$32)))),"no caben ","")&IF(OR(AND(ISNUMBER(BM9),BM9<0.005),AND(ISNUMBER(BU9),BU9<0.005),AND(ISNUMBER(CC9),CC9<0.005),AND(ISNUMBER(CK9),CK9<0.005)),"ε_t < 0.005 ","")&IF(CS9="NO CUMPLE","peralte ","")&IF(CT9<>"CUMPLE","capa < 6 cm","")))) -> CUMPLE · fuera de 3.4.2.1 c) | DA9: =IF(AND(D9="PERIMETRAL",MIN(CW9,CX9)=0),"Tablero macizo (no cabe un casetón en el claro corto): no aplica 6.7.8. La resistencia se revisa con una nervadura de 10 cm cada 70 cm y r_np (conservador); "&"como losa maciza lleva además As,mín = 0.0018·Ag en cada dirección cerca de la cara a tensión (6.7.6.1.1, p. 175). ",IF(AND(CL9="NO",D9="PERIMETRAL"),"No cumple 6.7.8.1.4 (a_c = "&DATOS!$C$11&" cm > claro corto/6 = "&TEXT(J9*100/6,"0")&" cm): se diseña como losa apoyada en vigas (6.7.8.1.9): nervaduras con recubrimiento de viga r_np = "&DATOS!$C$22&" cm (Tabla 4.14.16.a), V_cR sin ×1.1 y cortante sin estribos por 5.5.3.8.1 (criterio del Proyectista). Para que cuente como encasetonada: casetón de "&TEXT(FLOOR(MIN(80,J9*100/6),1),"0")&" cm o menor. ",""))&IF(LEFT(AZ9,5)="FUERA","M⁻ del borde común "&AZ9&": difieren más de 50% (3.4.2.1 c); se distribuyen 2/3 del desequilibrio (3.4.3.1) y conviene confirmar los momentos con el modelo. ","")&"—" -> No cumple 6.7.8.1.4 (a_c = 60 cm > claro corto/6 = 17 cm): se diseña como losa apoyada en vigas (6.7.8.1.9): nervaduras con recubrimiento de viga r_np = 4 cm (Tabla 4.14.16.a), V_cR sin ×1.1 y cortante sin estribos por 5.5.3.8.1 (criterio del Proyectista). Para que cuente como encasetonada: casetón de 16 cm o menor. M⁻ del borde común FUERA con F80003: difieren más de 50% (3.4.2.1 c); se distribuyen 2/3 del desequilibrio (3.4.3.1) y conviene confirmar los momentos con el modelo. —
B10: F80003 N+3.00 | C10: N+3.00 | D10: PERIMETRAL | E10: HABITACIÓN | F10: 4.327 | G10: 3.025 | H10: 4.327 | I10: 3.025 | J10: =MIN(H10,I10) -> 3.025 | K10: =MAX(H10,I10) -> 4.327 | L10: =IF(K10>0,J10/K10,0) -> 0.69909868 | M10: =IF(H10<=I10,"X","Y") -> Y | N10: =MAX(0,J10*100-IF(D10="VOLADO",DATOS!$C$17/2,DATOS!$C$17)) -> 287.5 | O10: =MAX(0,K10*100-DATOS!$C$17) -> 417.7 | P10: =MIN(DATOS!$C$16,DATOS!$C$13+2*MIN(8*DATOS!$C$14,DATOS!$C$11/2,N10/8)) -> 70 | Q10: =MIN(DATOS!$C$16,DATOS!$C$13+2*MIN(8*DATOS!$C$14,DATOS!$C$11/2,O10/8)) -> 70 | R10: =IF(D10="VOLADO",DATOS!$C$21,IF(CL10="NO",DATOS!$C$22,DATOS!$C$20)) -> 4 | S10: =IF(OR(AND(C10="N+6.00",DATOS!$C$23="SÍ"),AND(D10="VOLADO",DATOS!$C$24="SÍ")),DATOS!$C$21,IF(CL10="NO",DATOS!$C$22,DATOS!$C$20)) -> 4 | T10: 160 | U10: =IF(E10="HABITACIÓN",DATOS!$C$89,DATOS!$C$92) -> 190 | V10: =CARGAS!$C$9 -> 293.67347 | W10: =V10+T10 -> 453.67347 | X10: =W10+U10 -> 643.67347 | Y10: =MAX(DATOS!$C$55*W10+DATOS!$C$56*U10,IF(E10="AZOTEA",DATOS!$C$57*(W10+DATOS!$C$97),0)) -> 874.77551 | Z10: =(APOYOS!$G$33="DISCONTINUO")+(APOYOS!$G$34="DISCONTINUO")+(APOYOS!$G$35="DISCONTINUO")+(APOYOS!$G$36="DISCONTINUO") -> 1 | AA10: =IF(M10="X",(APOYOS!$G$33="DISCONTINUO")+(APOYOS!$G$34="DISCONTINUO"),(APOYOS!$G$35="DISCONTINUO")+(APOYOS!$G$36="DISCONTINUO")) -> 1 | AB10: =Z10-AA10 -> 0 | AC10: =IF(Z10=0,"INTERIOR",IF(Z10=1,IF(AA10=1,"BORDE-CORTO","BORDE-LARGO"),IF(Z10=2,IF(AA10=1,"ESQUINA",IF(AA10=2,"EXTREMO-LARGO","EXTREMO-CORTO")),IF(Z10=3,IF(AA10=2,"EXTREMO-LARGO","EXTREMO-CORTO"),"AISLADO")))) -> BORDE-CORTO | AD10: AUTO | AE10: =IF(AD10="AUTO",AC10,AD10) -> BORDE-CORTO | AF10: =MATCH(L10,TABLAS!$D$5:$J$5,1) -> 3 | AG10: =IF(AF10>=7,0,(L10-INDEX(TABLAS!$D$5:$J$5,AF10))/(INDEX(TABLAS!$D$5:$J$5,AF10+1)-INDEX(TABLAS!$D$5:$J$5,AF10))) -> 0.99098683 | AH10: =INDEX(TABLAS!$D$6:$J$47,MATCH(AE10&"|NIC",TABLAS!$B$6:$B$47,0),AF10)+AG10*(INDEX(TABLAS!$D$6:$J$47,MATCH(AE10&"|NIC",TABLAS!$B$6:$B$47,0),MIN(AF10+1,7))-INDEX(TABLAS!$D$6:$J$47,MATCH(AE10&"|NIC",TABLAS!$B$6:$B$47,0),AF10)) -> 786.62237 | AI10: =INDEX(TABLAS!$D$6:$J$47,MATCH(AE10&"|NIL",TABLAS!$B$6:$B$47,0),AF10)+AG10*(INDEX(TABLAS!$D$6:$J$47,MATCH(AE10&"|NIL",TABLAS!$B$6:$B$47,0),MIN(AF10+1,7))-INDEX(TABLAS!$D$6:$J$47,MATCH(AE10&"|NIL",TABLAS!$B$6:$B$47,0),AF10)) -> 498.24336 | AJ10: =INDEX(TABLAS!$D$6:$J$47,MATCH(AE10&"|NDC",TABLAS!$B$6:$B$47,0),AF10)+AG10*(INDEX(TABLAS!$D$6:$J$47,MATCH(AE10&"|NDC",TABLAS!$B$6:$B$47,0),MIN(AF10+1,7))-INDEX(TABLAS!$D$6:$J$47,MATCH(AE10&"|NDC",TABLAS!$B$6:$B$47,0),AF10)) -> 0 | AK10: =INDEX(TABLAS!$D$6:$J$47,MATCH(AE10&"|NDL",TABLAS!$B$6:$B$47,0),AF10)+AG10*(INDEX(TABLAS!$D$6:$J$47,MATCH(AE10&"|NDL",TABLAS!$B$6:$B$47,0),MIN(AF10+1,7))-INDEX(TABLAS!$D$6:$J$47,MATCH(AE10&"|NDL",TABLAS!$B$6:$B$47,0),AF10)) -> 236.10816 | AL10: =INDEX(TABLAS!$D$6:$J$47,MATCH(AE10&"|PC",TABLAS!$B$6:$B$47,0),AF10)+AG10*(INDEX(TABLAS!$D$6:$J$47,MATCH(AE10&"|PC",TABLAS!$B$6:$B$47,0),MIN(AF10+1,7))-INDEX(TABLAS!$D$6:$J$47,MATCH(AE10&"|PC",TABLAS!$B$6:$B$47,0),AF10)) -> 330.64849 | AM10: =INDEX(TABLAS!$D$6:$J$47,MATCH(AE10&"|PL",TABLAS!$B$6:$B$47,0),AF10)+AG10*(INDEX(TABLAS!$D$6:$J$47,MATCH(AE10&"|PL",TABLAS!$B$6:$B$47,0),MIN(AF10+1,7))-INDEX(TABLAS!$D$6:$J$47,MATCH(AE10&"|PL",TABLAS!$B$6:$B$47,0),AF10)) -> 265.97296 | AN10: =IF(D10="PERIMETRAL",IF(APOYOS!$G$33="CONTINUO",IF(M10="Y",AH10,AI10),IF(M10="Y",AJ10,AK10))*Y10*J10^2*1E-4*DATOS!$C$16/100/1000,0) -> 0.44076968 | AO10: =IF(D10="PERIMETRAL",IF(APOYOS!$G$34="CONTINUO",IF(M10="Y",AH10,AI10),IF(M10="Y",AJ10,AK10))*Y10*J10^2*1E-4*DATOS!$C$16/100/1000,0) -> 0.44076968 | AP10: =IF(D10="PERIMETRAL",IF(APOYOS!$G$35="CONTINUO",IF(M10="X",AH10,AI10),IF(M10="X",AJ10,AK10))*Y10*J10^2*1E-4*DATOS!$C$16/100/1000,0) -> 0.13229895 | AQ10: =IF(D10="PERIMETRAL",IF(APOYOS!$G$36="CONTINUO",IF(M10="X",AH10,AI10),IF(M10="X",AJ10,AK10))*Y10*J10^2*1E-4*DATOS!$C$16/100/1000,0) -> 0.27918169 | AR10: =IF(D10="PERIMETRAL",IF(M10="X",BN10,CD10)^3/(J10*100),0) -> 19.664246 | AS10: =IF(D10="PERIMETRAL",IF(M10="Y",BN10,CD10)^3/(J10*100),0) -> 24.095772 | AT10: =IF(D10="PERIMETRAL",MAX(0,IF(M10="Y",IF(AND(OR(APOYOS!$G$33="CONTINUO",APOYOS!$G$30="CONTINUO"),AN10>0,AO9>0,AO9>AN10),AN10+2/3*(AO9-AN10)*AS10/MAX(AS10+AS9,1E-9),0),0),IF(M10="Y",IF(AND(OR(APOYOS!$G$34="CONTINUO",APOYOS!$G$41="CONTINUO"),AO10>0,AN12>0,AN12>AO10),AO10+2/3*(AN12-AO10)*AS10/MAX(AS10+AS12,1E-9),0),0),IF(M10="Y",IF(AND(OR(APOYOS!$G$34="CONTINUO",APOYOS!$G$45="CONTINUO"),AO10>0,AN13>0,AN13>AO10),AO10+2/3*(AN13-AO10)*AS10/MAX(AS10+AS13,1E-9),0),0),IF(M10="X",IF(AND(OR(APOYOS!$G$35="CONTINUO",APOYOS!$G$44="CONTINUO"),AP10>0,AQ12>0,AQ12>AP10),AP10+2/3*(AQ12-AP10)*AR10/MAX(AR10+AR12,1E-9),0),0),IF(M10="X",IF(AND(OR(APOYOS!$G$36="CONTINUO",APOYOS!$G$39="CONTINUO"),AQ10>0,AP11>0,AP11>AQ10),AQ10+2/3*(AP11-AQ10)*AR10/MAX(AR10+AR11,1E-9),0),0)),0) -> 0 | AU10: =IF(D10="PERIMETRAL",MAX(0,IF(M10<>"Y",IF(AND(OR(APOYOS!$G$33="CONTINUO",APOYOS!$G$30="CONTINUO"),AN10>0,AO9>0,AO9>AN10),AN10+2/3*(AO9-AN10)*AS10/MAX(AS10+AS9,1E-9),0),0),IF(M10<>"Y",IF(AND(OR(APOYOS!$G$34="CONTINUO",APOYOS!$G$41="CONTINUO"),AO10>0,AN12>0,AN12>AO10),AO10+2/3*(AN12-AO10)*AS10/MAX(AS10+AS12,1E-9),0),0),IF(M10<>"Y",IF(AND(OR(APOYOS!$G$34="CONTINUO",APOYOS!$G$45="CONTINUO"),AO10>0,AN13>0,AN13>AO10),AO10+2/3*(AN13-AO10)*AS10/MAX(AS10+AS13,1E-9),0),0),IF(M10<>"X",IF(AND(OR(APOYOS!$G$35="CONTINUO",APOYOS!$G$44="CONTINUO"),AP10>0,AQ12>0,AQ12>AP10),AP10+2/3*(AQ12-AP10)*AR10/MAX(AR10+AR12,1E-9),0),0),IF(M10<>"X",IF(AND(OR(APOYOS!$G$36="CONTINUO",APOYOS!$G$39="CONTINUO"),AQ10>0,AP11>0,AP11>AQ10),AQ10+2/3*(AP11-AQ10)*AR10/MAX(AR10+AR11,1E-9),0),0)),0) -> 0 | AV10: =IF(D10="PERIMETRAL",(IF(M10="Y",IF(AND(OR(APOYOS!$G$33="CONTINUO",APOYOS!$G$30="CONTINUO"),AN10>0,AO9>0,AN10>AO9),2/3*(AN10-AO9)*AS10/MAX(AS10+AS9,1E-9),0),0)+IF(M10="Y",MAX(IF(AND(OR(APOYOS!$G$34="CONTINUO",APOYOS!$G$41="CONTINUO"),AO10>0,AN12>0,AO10>AN12),2/3*(AO10-AN12)*AS10/MAX(AS10+AS12,1E-9),0),IF(AND(OR(APOYOS!$G$34="CONTINUO",APOYOS!$G$45="CONTINUO"),AO10>0,AN13>0,AO10>AN13),2/3*(AO10-AN13)*AS10/MAX(AS10+AS13,1E-9),0)),0)+IF(M10="X",IF(AND(OR(APOYOS!$G$35="CONTINUO",APOYOS!$G$44="CONTINUO"),AP10>0,AQ12>0,AP10>AQ12),2/3*(AP10-AQ12)*AR10/MAX(AR10+AR12,1E-9),0),0)+IF(M10="X",IF(AND(OR(APOYOS!$G$36="CONTINUO",APOYOS!$G$39="CONTINUO"),AQ10>0,AP11>0,AQ10>AP11),2/3*(AQ10-AP11)*AR10/MAX(AR10+AR11,1E-9),0),0))/2,0) -> 0.062848608 | AW10: =IF(D10="PERIMETRAL",(IF(M10<>"Y",IF(AND(OR(APOYOS!$G$33="CONTINUO",APOYOS!$G$30="CONTINUO"),AN10>0,AO9>0,AN10>AO9),2/3*(AN10-AO9)*AS10/MAX(AS10+AS9,1E-9),0),0)+IF(M10<>"Y",MAX(IF(AND(OR(APOYOS!$G$34="CONTINUO",APOYOS!$G$41="CONTINUO"),AO10>0,AN12>0,AO10>AN12),2/3*(AO10-AN12)*AS10/MAX(AS10+AS12,1E-9),0),IF(AND(OR(APOYOS!$G$34="CONTINUO",APOYOS!$G$45="CONTINUO"),AO10>0,AN13>0,AO10>AN13),2/3*(AO10-AN13)*AS10/MAX(AS10+AS13,1E-9),0)),0)+IF(M10<>"X",IF(AND(OR(APOYOS!$G$35="CONTINUO",APOYOS!$G$44="CONTINUO"),AP10>0,AQ12>0,AP10>AQ12),2/3*(AP10-AQ12)*AR10/MAX(AR10+AR12,1E-9),0),0)+IF(M10<>"X",IF(AND(OR(APOYOS!$G$36="CONTINUO",APOYOS!$G$39="CONTINUO"),AQ10>0,AP11>0,AQ10>AP11),2/3*(AQ10-AP11)*AR10/MAX(AR10+AR11,1E-9),0),0))/2,0) -> 0.011140717 | AX10: =IF(D10="PERIMETRAL",MAX(0,0),0) -> 0 | AY10: =IF(D10<>"PERIMETRAL","",IF(AND(OR(APOYOS!$G$33="CONTINUO",APOYOS!$G$30="CONTINUO"),AN10>0,AO9>0,ABS(AN10-AO9)>0.5*MIN(AN10,AO9))," F80001","")&IF(OR(AND(OR(APOYOS!$G$34="CONTINUO",APOYOS!$G$41="CONTINUO"),AO10>0,AN12>0,ABS(AO10-AN12)>0.5*MIN(AO10,AN12)),AND(OR(APOYOS!$G$35="CONTINUO",APOYOS!$G$44="CONTINUO"),AP10>0,AQ12>0,ABS(AP10-AQ12)>0.5*MIN(AP10,AQ12)))," F80005","")&IF(AND(OR(APOYOS!$G$34="CONTINUO",APOYOS!$G$45="CONTINUO"),AO10>0,AN13>0,ABS(AO10-AN13)>0.5*MIN(AO10,AN13))," F80006","")&IF(AND(OR(APOYOS!$G$36="CONTINUO",APOYOS!$G$39="CONTINUO"),AQ10>0,AP11>0,ABS(AQ10-AP11)>0.5*MIN(AQ10,AP11))," F80004","")) -> F80001 F80005 F80006 | AZ10: =IF(D10<>"PERIMETRAL","—",IF(AY10="","CUMPLE","FUERA con"&AY10)&IF(AND(D9="PERIMETRAL",APOYOS!$G$33<>APOYOS!$G$30)," · continuidad asimétrica con F80001 (cada uno con su momento; revisar APOYOS)","")&IF(AND(D12="PERIMETRAL",APOYOS!$G$34<>APOYOS!$G$41)," · continuidad asimétrica con F80005 (cada uno con su momento; revisar APOYOS)","")&IF(AND(D13="PERIMETRAL",APOYOS!$G$34<>APOYOS!$G$45)," · continuidad asimétrica con F80006 (cada uno con su momento; revisar APOYOS)","")&IF(AND(D11="PERIMETRAL",APOYOS!$G$36<>APOYOS!$G$39)," · continuidad asimétrica con F80004 (cada uno con su momento; revisar APOYOS)","")) -> FUERA con F80001 F80005 F80006 | BA10: 0 | BB10: =IF(D10="PERIMETRAL",AL10*Y10*J10^2*1E-4*DATOS!$C$16/100/1000+AV10,0) -> 0.24812153 | BC10: =IF(D10="PERIMETRAL",MAX(MAX(AH10,AJ10)*Y10*J10^2*1E-4*DATOS!$C$16/100/1000,AT10),IF(D10="VOLADO",(Y10*(N10/100)^2/2+DATOS!$C$55*BA10*N10/100)*DATOS!$C$16/100/1000,0)) -> 0.44076968 | BD10: =IF(D10="PERIMETRAL",AM10*Y10*J10^2*1E-4*DATOS!$C$16/100/1000+AW10,0) -> 0.16017387 | BE10: =IF(D10="PERIMETRAL",MAX(MAX(AI10,AK10)*Y10*J10^2*1E-4*DATOS!$C$16/100/1000,AU10),0) -> 0.27918169 | BF10: =(DATOS!$C$15-R10-IF(DATOS!$C$25=0,0,INDEX(TABLAS!$C$52:$C$58,MATCH(DATOS!$C$25,TABLAS!$B$52:$B$58,0)))-INDEX(TABLAS!$C$52:$C$58,MATCH(DATOS!$C$26,TABLAS!$B$52:$B$58,0))/2) -> 20.365 | BG10: =IF(D10="HUECO",0,IF(IF(BB10<=0,0,IF((1-2*BB10*1E5/(DATOS!$C$58*P10*BF10^2*DATOS!$C$48))<0,-1,IF((1-SQRT((1-2*BB10*1E5/(DATOS!$C$58*P10*BF10^2*DATOS!$C$48))))*DATOS!$C$48*P10*BF10/DATOS!$C$40>DATOS!$C$82*P10*BF10,-1,(1-SQRT((1-2*BB10*1E5/(DATOS!$C$58*P10*BF10^2*DATOS!$C$48))))*DATOS!$C$48*P10*BF10/DATOS!$C$40)))<0,-1,MAX(IF(BB10<=0,0,IF((1-2*BB10*1E5/(DATOS!$C$58*P10*BF10^2*DATOS!$C$48))<0,-1,IF((1-SQRT((1-2*BB10*1E5/(DATOS!$C$58*P10*BF10^2*DATOS!$C$48))))*DATOS!$C$48*P10*BF10/DATOS!$C$40>DATOS!$C$82*P10*BF10,-1,(1-SQRT((1-2*BB10*1E5/(DATOS!$C$58*P10*BF10^2*DATOS!$C$48))))*DATOS!$C$48*P10*BF10/DATOS!$C$40))),MIN(DATOS!$C$83*DATOS!$C$13*BF10,4/3*IF(BB10<=0,0,IF((1-2*BB10*1E5/(DATOS!$C$58*P10*BF10^2*DATOS!$C$48))<0,-1,IF((1-SQRT((1-2*BB10*1E5/(DATOS!$C$58*P10*BF10^2*DATOS!$C$48))))*DATOS!$C$48*P10*BF10/DATOS!$C$40>DATOS!$C$82*P10*BF10,-1,(1-SQRT((1-2*BB10*1E5/(DATOS!$C$58*P10*BF10^2*DATOS!$C$48))))*DATOS!$C$48*P10*BF10/DATOS!$C$40))))))) -> 0.43072556 | BH10: =IF(AND(BG10>=0,IF(MAX(DATOS!$C$29,CEILING(BG10/INDEX(TABLAS!$D$52:$D$58,MIN(MATCH(DATOS!$C$26,TABLAS!$B$52:$B$58,0)+0,7)),1))*INDEX(TABLAS!$D$52:$D$58,MIN(MATCH(DATOS!$C$26,TABLAS!$B$52:$B$58,0)+0,7))>=4/3*IF(BB10<=0,0,IF((1-2*BB10*1E5/(DATOS!$C$58*P10*BF10^2*DATOS!$C$48))<0,-1,IF((1-SQRT((1-2*BB10*1E5/(DATOS!$C$58*P10*BF10^2*DATOS!$C$48))))*DATOS!$C$48*P10*BF10/DATOS!$C$40>DATOS!$C$82*P10*BF10,-1,(1-SQRT((1-2*BB10*1E5/(DATOS!$C$58*P10*BF10^2*DATOS!$C$48))))*DATOS!$C$48*P10*BF10/DATOS!$C$40)))-0.0001,MAX(DATOS!$C$29,CEILING(BG10/INDEX(TABLAS!$D$52:$D$58,MIN(MATCH(DATOS!$C$26,TABLAS!$B$52:$B$58,0)+0,7)),1)),MAX(MAX(DATOS!$C$29,CEILING(BG10/INDEX(TABLAS!$D$52:$D$58,MIN(MATCH(DATOS!$C$26,TABLAS!$B$52:$B$58,0)+0,7)),1)),2))<=MIN(DATOS!$C$28,INT(((DATOS!$C$13-2*R10-2*IF(DATOS!$C$25=0,0,INDEX(TABLAS!$C$52:$C$58,MATCH(DATOS!$C$25,TABLAS!$B$52:$B$58,0))))+MAX(DATOS!$C$32,INDEX(TABLAS!$C$52:$C$58,MIN(MATCH(DATOS!$C$26,TABLAS!$B$52:$B$58,0)+0,7))))/(INDEX(TABLAS!$C$52:$C$58,MIN(MATCH(DATOS!$C$26,TABLAS!$B$52:$B$58,0)+0,7))+MAX(DATOS!$C$32,INDEX(TABLAS!$C$52:$C$58,MIN(MATCH(DATOS!$C$26,TABLAS!$B$52:$B$58,0)+0,7))))))),INDEX(TABLAS!$B$52:$B$58,MIN(MATCH(DATOS!$C$26,TABLAS!$B$52:$B$58,0)+0,7)),IF(AND(BG10>=0,IF(MAX(DATOS!$C$29,CEILING(BG10/INDEX(TABLAS!$D$52:$D$58,MIN(MATCH(DATOS!$C$26,TABLAS!$B$52:$B$58,0)+1,7)),1))*INDEX(TABLAS!$D$52:$D$58,MIN(MATCH(DATOS!$C$26,TABLAS!$B$52:$B$58,0)+1,7))>=4/3*IF(BB10<=0,0,IF((1-2*BB10*1E5/(DATOS!$C$58*P10*BF10^2*DATOS!$C$48))<0,-1,IF((1-SQRT((1-2*BB10*1E5/(DATOS!$C$58*P10*BF10^2*DATOS!$C$48))))*DATOS!$C$48*P10*BF10/DATOS!$C$40>DATOS!$C$82*P10*BF10,-1,(1-SQRT((1-2*BB10*1E5/(DATOS!$C$58*P10*BF10^2*DATOS!$C$48))))*DATOS!$C$48*P10*BF10/DATOS!$C$40)))-0.0001,MAX(DATOS!$C$29,CEILING(BG10/INDEX(TABLAS!$D$52:$D$58,MIN(MATCH(DATOS!$C$26,TABLAS!$B$52:$B$58,0)+1,7)),1)),MAX(MAX(DATOS!$C$29,CEILING(BG10/INDEX(TABLAS!$D$52:$D$58,MIN(MATCH(DATOS!$C$26,TABLAS!$B$52:$B$58,0)+1,7)),1)),2))<=MIN(DATOS!$C$28,INT(((DATOS!$C$13-2*R10-2*IF(DATOS!$C$25=0,0,INDEX(TABLAS!$C$52:$C$58,MATCH(DATOS!$C$25,TABLAS!$B$52:$B$58,0))))+MAX(DATOS!$C$32,INDEX(TABLAS!$C$52:$C$58,MIN(MATCH(DATOS!$C$26,TABLAS!$B$52:$B$58,0)+1,7))))/(INDEX(TABLAS!$C$52:$C$58,MIN(MATCH(DATOS!$C$26,TABLAS!$B$52:$B$58,0)+1,7))+MAX(DATOS!$C$32,INDEX(TABLAS!$C$52:$C$58,MIN(MATCH(DATOS!$C$26,TABLAS!$B$52:$B$58,0)+1,7))))))),INDEX(TABLAS!$B$52:$B$58,MIN(MATCH(DATOS!$C$26,TABLAS!$B$52:$B$58,0)+1,7)),IF(AND(BG10>=0,IF(MAX(DATOS!$C$29,CEILING(BG10/INDEX(TABLAS!$D$52:$D$58,MIN(MATCH(DATOS!$C$26,TABLAS!$B$52:$B$58,0)+2,7)),1))*INDEX(TABLAS!$D$52:$D$58,MIN(MATCH(DATOS!$C$26,TABLAS!$B$52:$B$58,0)+2,7))>=4/3*IF(BB10<=0,0,IF((1-2*BB10*1E5/(DATOS!$C$58*P10*BF10^2*DATOS!$C$48))<0,-1,IF((1-SQRT((1-2*BB10*1E5/(DATOS!$C$58*P10*BF10^2*DATOS!$C$48))))*DATOS!$C$48*P10*BF10/DATOS!$C$40>DATOS!$C$82*P10*BF10,-1,(1-SQRT((1-2*BB10*1E5/(DATOS!$C$58*P10*BF10^2*DATOS!$C$48))))*DATOS!$C$48*P10*BF10/DATOS!$C$40)))-0.0001,MAX(DATOS!$C$29,CEILING(BG10/INDEX(TABLAS!$D$52:$D$58,MIN(MATCH(DATOS!$C$26,TABLAS!$B$52:$B$58,0)+2,7)),1)),MAX(MAX(DATOS!$C$29,CEILING(BG10/INDEX(TABLAS!$D$52:$D$58,MIN(MATCH(DATOS!$C$26,TABLAS!$B$52:$B$58,0)+2,7)),1)),2))<=MIN(DATOS!$C$28,INT(((DATOS!$C$13-2*R10-2*IF(DATOS!$C$25=0,0,INDEX(TABLAS!$C$52:$C$58,MATCH(DATOS!$C$25,TABLAS!$B$52:$B$58,0))))+MAX(DATOS!$C$32,INDEX(TABLAS!$C$52:$C$58,MIN(MATCH(DATOS!$C$26,TABLAS!$B$52:$B$58,0)+2,7))))/(INDEX(TABLAS!$C$52:$C$58,MIN(MATCH(DATOS!$C$26,TABLAS!$B$52:$B$58,0)+2,7))+MAX(DATOS!$C$32,INDEX(TABLAS!$C$52:$C$58,MIN(MATCH(DATOS!$C$26,TABLAS!$B$52:$B$58,0)+2,7))))))),INDEX(TABLAS!$B$52:$B$58,MIN(MATCH(DATOS!$C$26,TABLAS!$B$52:$B$58,0)+2,7)),IF(AND(BG10>=0,IF(MAX(DATOS!$C$29,CEILING(BG10/INDEX(TABLAS!$D$52:$D$58,MIN(MATCH(DATOS!$C$26,TABLAS!$B$52:$B$58,0)+3,7)),1))*INDEX(TABLAS!$D$52:$D$58,MIN(MATCH(DATOS!$C$26,TABLAS!$B$52:$B$58,0)+3,7))>=4/3*IF(BB10<=0,0,IF((1-2*BB10*1E5/(DATOS!$C$58*P10*BF10^2*DATOS!$C$48))<0,-1,IF((1-SQRT((1-2*BB10*1E5/(DATOS!$C$58*P10*BF10^2*DATOS!$C$48))))*DATOS!$C$48*P10*BF10/DATOS!$C$40>DATOS!$C$82*P10*BF10,-1,(1-SQRT((1-2*BB10*1E5/(DATOS!$C$58*P10*BF10^2*DATOS!$C$48))))*DATOS!$C$48*P10*BF10/DATOS!$C$40)))-0.0001,MAX(DATOS!$C$29,CEILING(BG10/INDEX(TABLAS!$D$52:$D$58,MIN(MATCH(DATOS!$C$26,TABLAS!$B$52:$B$58,0)+3,7)),1)),MAX(MAX(DATOS!$C$29,CEILING(BG10/INDEX(TABLAS!$D$52:$D$58,MIN(MATCH(DATOS!$C$26,TABLAS!$B$52:$B$58,0)+3,7)),1)),2))<=MIN(DATOS!$C$28,INT(((DATOS!$C$13-2*R10-2*IF(DATOS!$C$25=0,0,INDEX(TABLAS!$C$52:$C$58,MATCH(DATOS!$C$25,TABLAS!$B$52:$B$58,0))))+MAX(DATOS!$C$32,INDEX(TABLAS!$C$52:$C$58,MIN(MATCH(DATOS!$C$26,TABLAS!$B$52:$B$58,0)+3,7))))/(INDEX(TABLAS!$C$52:$C$58,MIN(MATCH(DATOS!$C$26,TABLAS!$B$52:$B$58,0)+3,7))+MAX(DATOS!$C$32,INDEX(TABLAS!$C$52:$C$58,MIN(MATCH(DATOS!$C$26,TABLAS!$B$52:$B$58,0)+3,7))))))),INDEX(TABLAS!$B$52:$B$58,MIN(MATCH(DATOS!$C$26,TABLAS!$B$52:$B$58,0)+3,7)),IF(AND(BG10>=0,IF(MAX(DATOS!$C$29,CEILING(BG10/INDEX(TABLAS!$D$52:$D$58,MIN(MATCH(DATOS!$C$26,TABLAS!$B$52:$B$58,0)+4,7)),1))*INDEX(TABLAS!$D$52:$D$58,MIN(MATCH(DATOS!$C$26,TABLAS!$B$52:$B$58,0)+4,7))>=4/3*IF(BB10<=0,0,IF((1-2*BB10*1E5/(DATOS!$C$58*P10*BF10^2*DATOS!$C$48))<0,-1,IF((1-SQRT((1-2*BB10*1E5/(DATOS!$C$58*P10*BF10^2*DATOS!$C$48))))*DATOS!$C$48*P10*BF10/DATOS!$C$40>DATOS!$C$82*P10*BF10,-1,(1-SQRT((1-2*BB10*1E5/(DATOS!$C$58*P10*BF10^2*DATOS!$C$48))))*DATOS!$C$48*P10*BF10/DATOS!$C$40)))-0.0001,MAX(DATOS!$C$29,CEILING(BG10/INDEX(TABLAS!$D$52:$D$58,MIN(MATCH(DATOS!$C$26,TABLAS!$B$52:$B$58,0)+4,7)),1)),MAX(MAX(DATOS!$C$29,CEILING(BG10/INDEX(TABLAS!$D$52:$D$58,MIN(MATCH(DATOS!$C$26,TABLAS!$B$52:$B$58,0)+4,7)),1)),2))<=MIN(DATOS!$C$28,INT(((DATOS!$C$13-2*R10-2*IF(DATOS!$C$25=0,0,INDEX(TABLAS!$C$52:$C$58,MATCH(DATOS!$C$25,TABLAS!$B$52:$B$58,0))))+MAX(DATOS!$C$32,INDEX(TABLAS!$C$52:$C$58,MIN(MATCH(DATOS!$C$26,TABLAS!$B$52:$B$58,0)+4,7))))/(INDEX(TABLAS!$C$52:$C$58,MIN(MATCH(DATOS!$C$26,TABLAS!$B$52:$B$58,0)+4,7))+MAX(DATOS!$C$32,INDEX(TABLAS!$C$52:$C$58,MIN(MATCH(DATOS!$C$26,TABLAS!$B$52:$B$58,0)+4,7))))))),INDEX(TABLAS!$B$52:$B$58,MIN(MATCH(DATOS!$C$26,TABLAS!$B$52:$B$58,0)+4,7)),INDEX(TABLAS!$B$52:$B$58,7)))))) -> 4 | BI10: =IF(D10="HUECO",0,IF(BG10<0,0,IF(MAX(DATOS!$C$29,CEILING(MAX(BG10,0)/INDEX(TABLAS!$D$52:$D$58,MATCH(BH10,TABLAS!$B$52:$B$58,0)),1))*INDEX(TABLAS!$D$52:$D$58,MATCH(BH10,TABLAS!$B$52:$B$58,0))>=4/3*IF(BB10<=0,0,IF((1-2*BB10*1E5/(DATOS!$C$58*P10*BF10^2*DATOS!$C$48))<0,-1,IF((1-SQRT((1-2*BB10*1E5/(DATOS!$C$58*P10*BF10^2*DATOS!$C$48))))*DATOS!$C$48*P10*BF10/DATOS!$C$40>DATOS!$C$82*P10*BF10,-1,(1-SQRT((1-2*BB10*1E5/(DATOS!$C$58*P10*BF10^2*DATOS!$C$48))))*DATOS!$C$48*P10*BF10/DATOS!$C$40)))-0.0001,MAX(DATOS!$C$29,CEILING(MAX(BG10,0)/INDEX(TABLAS!$D$52:$D$58,MATCH(BH10,TABLAS!$B$52:$B$58,0)),1)),MAX(MAX(DATOS!$C$29,CEILING(MAX(BG10,0)/INDEX(TABLAS!$D$52:$D$58,MATCH(BH10,TABLAS!$B$52:$B$58,0)),1)),2)))) -> 1 | BJ10: =DATOS!$C$15-R10-IF(DATOS!$C$25=0,0,INDEX(TABLAS!$C$52:$C$58,MATCH(DATOS!$C$25,TABLAS!$B$52:$B$58,0)))-INDEX(TABLAS!$C$52:$C$58,MATCH(BH10,TABLAS!$B$52:$B$58,0))/2 -> 20.365 | BK10: =IF(BI10=0,0,DATOS!$C$58*BI10*INDEX(TABLAS!$D$52:$D$58,MATCH(BH10,TABLAS!$B$52:$B$58,0))*DATOS!$C$40*(BJ10-BI10*INDEX(TABLAS!$D$52:$D$58,MATCH(BH10,TABLAS!$B$52:$B$58,0))*DATOS!$C$40/(DATOS!$C$48*P10)/2)/1E5) -> 0.969035 | BL10: =IF(BG10<0,9.99,IF(BK10>0,BB10/BK10,0)) -> 0.25605012 | BM10: =IF(BI10=0,"—",0.003*(BJ10-(BI10*INDEX(TABLAS!$D$52:$D$58,MATCH(BH10,TABLAS!$B$52:$B$58,0))*DATOS!$C$40/(DATOS!$C$48*P10)/DATOS!$C$49))/(BI10*INDEX(TABLAS!$D$52:$D$58,MATCH(BH10,TABLAS!$B$52:$B$58,0))*DATOS!$C$40/(DATOS!$C$48*P10)/DATOS!$C$49)) -> 0.14182 | BN10: =((DATOS!$C$15-S10-2*DATOS!$C$35-IF(DATOS!$C$25=0,0,INDEX(TABLAS!$C$52:$C$58,MATCH(DATOS!$C$25,TABLAS!$B$52:$B$58,0)))-INDEX(TABLAS!$C$52:$C$58,MATCH(DATOS!$C$27,TABLAS!$B$52:$B$58,0))/2)-IF(AND((DATOS!$C$15-S10-2*DATOS!$C$35-IF(DATOS!$C$25=0,0,INDEX(TABLAS!$C$52:$C$58,MATCH(DATOS!$C$25,TABLAS!$B$52:$B$58,0)))-INDEX(TABLAS!$C$52:$C$58,MATCH(DATOS!$C$27,TABLAS!$B$52:$B$58,0))/2)<=20,DATOS!$C$18<>"SÍ"),2,0)) -> 19.389 | BO10: =IF(D10="HUECO",0,IF(IF(BC10<=0,0,IF((1-2*BC10*1E5/(DATOS!$C$58*DATOS!$C$19*BN10^2*DATOS!$C$48))<0,-1,IF((1-SQRT((1-2*BC10*1E5/(DATOS!$C$58*DATOS!$C$19*BN10^2*DATOS!$C$48))))*DATOS!$C$48*DATOS!$C$19*BN10/DATOS!$C$40>DATOS!$C$82*DATOS!$C$19*BN10,-1,(1-SQRT((1-2*BC10*1E5/(DATOS!$C$58*DATOS!$C$19*BN10^2*DATOS!$C$48))))*DATOS!$C$48*DATOS!$C$19*BN10/DATOS!$C$40)))<0,-1,MAX(IF(BC10<=0,0,IF((1-2*BC10*1E5/(DATOS!$C$58*DATOS!$C$19*BN10^2*DATOS!$C$48))<0,-1,IF((1-SQRT((1-2*BC10*1E5/(DATOS!$C$58*DATOS!$C$19*BN10^2*DATOS!$C$48))))*DATOS!$C$48*DATOS!$C$19*BN10/DATOS!$C$40>DATOS!$C$82*DATOS!$C$19*BN10,-1,(1-SQRT((1-2*BC10*1E5/(DATOS!$C$58*DATOS!$C$19*BN10^2*DATOS!$C$48))))*DATOS!$C$48*DATOS!$C$19*BN10/DATOS!$C$40))),MIN(DATOS!$C$83*IF(D10="VOLADO",2*DATOS!$C$13,DATOS!$C$13)*BN10,4/3*IF(BC10<=0,0,IF((1-2*BC10*1E5/(DATOS!$C$58*DATOS!$C$19*BN10^2*DATOS!$C$48))<0,-1,IF((1-SQRT((1-2*BC10*1E5/(DATOS!$C$58*DATOS!$C$19*BN10^2*DATOS!$C$48))))*DATOS!$C$48*DATOS!$C$19*BN10/DATOS!$C$40>DATOS!$C$82*DATOS!$C$19*BN10,-1,(1-SQRT((1-2*BC10*1E5/(DATOS!$C$58*DATOS!$C$19*BN10^2*DATOS!$C$48))))*DATOS!$C$48*DATOS!$C$19*BN10/DATOS!$C$40))))))) -> 0.6463 | BP10: =IF(AND(BO10>=0,IF(MAX(DATOS!$C$29,CEILING(BO10/INDEX(TABLAS!$D$52:$D$58,MIN(MATCH(DATOS!$C$27,TABLAS!$B$52:$B$58,0)+0,7)),1))*INDEX(TABLAS!$D$52:$D$58,MIN(MATCH(DATOS!$C$27,TABLAS!$B$52:$B$58,0)+0,7))>=4/3*IF(BC10<=0,0,IF((1-2*BC10*1E5/(DATOS!$C$58*DATOS!$C$19*BN10^2*DATOS!$C$48))<0,-1,IF((1-SQRT((1-2*BC10*1E5/(DATOS!$C$58*DATOS!$C$19*BN10^2*DATOS!$C$48))))*DATOS!$C$48*DATOS!$C$19*BN10/DATOS!$C$40>DATOS!$C$82*DATOS!$C$19*BN10,-1,(1-SQRT((1-2*BC10*1E5/(DATOS!$C$58*DATOS!$C$19*BN10^2*DATOS!$C$48))))*DATOS!$C$48*DATOS!$C$19*BN10/DATOS!$C$40)))-0.0001,MAX(DATOS!$C$29,CEILING(BO10/INDEX(TABLAS!$D$52:$D$58,MIN(MATCH(DATOS!$C$27,TABLAS!$B$52:$B$58,0)+0,7)),1)),MAX(MAX(DATOS!$C$29,CEILING(BO10/INDEX(TABLAS!$D$52:$D$58,MIN(MATCH(DATOS!$C$27,TABLAS!$B$52:$B$58,0)+0,7)),1)),2))<=MIN(DATOS!$C$28,INT(((DATOS!$C$13-2*S10-2*IF(DATOS!$C$25=0,0,INDEX(TABLAS!$C$52:$C$58,MATCH(DATOS!$C$25,TABLAS!$B$52:$B$58,0))))+MAX(DATOS!$C$32,INDEX(TABLAS!$C$52:$C$58,MIN(MATCH(DATOS!$C$27,TABLAS!$B$52:$B$58,0)+0,7))))/(INDEX(TABLAS!$C$52:$C$58,MIN(MATCH(DATOS!$C$27,TABLAS!$B$52:$B$58,0)+0,7))+MAX(DATOS!$C$32,INDEX(TABLAS!$C$52:$C$58,MIN(MATCH(DATOS!$C$27,TABLAS!$B$52:$B$58,0)+0,7))))))),INDEX(TABLAS!$B$52:$B$58,MIN(MATCH(DATOS!$C$27,TABLAS!$B$52:$B$58,0)+0,7)),IF(AND(BO10>=0,IF(MAX(DATOS!$C$29,CEILING(BO10/INDEX(TABLAS!$D$52:$D$58,MIN(MATCH(DATOS!$C$27,TABLAS!$B$52:$B$58,0)+1,7)),1))*INDEX(TABLAS!$D$52:$D$58,MIN(MATCH(DATOS!$C$27,TABLAS!$B$52:$B$58,0)+1,7))>=4/3*IF(BC10<=0,0,IF((1-2*BC10*1E5/(DATOS!$C$58*DATOS!$C$19*BN10^2*DATOS!$C$48))<0,-1,IF((1-SQRT((1-2*BC10*1E5/(DATOS!$C$58*DATOS!$C$19*BN10^2*DATOS!$C$48))))*DATOS!$C$48*DATOS!$C$19*BN10/DATOS!$C$40>DATOS!$C$82*DATOS!$C$19*BN10,-1,(1-SQRT((1-2*BC10*1E5/(DATOS!$C$58*DATOS!$C$19*BN10^2*DATOS!$C$48))))*DATOS!$C$48*DATOS!$C$19*BN10/DATOS!$C$40)))-0.0001,MAX(DATOS!$C$29,CEILING(BO10/INDEX(TABLAS!$D$52:$D$58,MIN(MATCH(DATOS!$C$27,TABLAS!$B$52:$B$58,0)+1,7)),1)),MAX(MAX(DATOS!$C$29,CEILING(BO10/INDEX(TABLAS!$D$52:$D$58,MIN(MATCH(DATOS!$C$27,TABLAS!$B$52:$B$58,0)+1,7)),1)),2))<=MIN(DATOS!$C$28,INT(((DATOS!$C$13-2*S10-2*IF(DATOS!$C$25=0,0,INDEX(TABLAS!$C$52:$C$58,MATCH(DATOS!$C$25,TABLAS!$B$52:$B$58,0))))+MAX(DATOS!$C$32,INDEX(TABLAS!$C$52:$C$58,MIN(MATCH(DATOS!$C$27,TABLAS!$B$52:$B$58,0)+1,7))))/(INDEX(TABLAS!$C$52:$C$58,MIN(MATCH(DATOS!$C$27,TABLAS!$B$52:$B$58,0)+1,7))+MAX(DATOS!$C$32,INDEX(TABLAS!$C$52:$C$58,MIN(MATCH(DATOS!$C$27,TABLAS!$B$52:$B$58,0)+1,7))))))),INDEX(TABLAS!$B$52:$B$58,MIN(MATCH(DATOS!$C$27,TABLAS!$B$52:$B$58,0)+1,7)),IF(AND(BO10>=0,IF(MAX(DATOS!$C$29,CEILING(BO10/INDEX(TABLAS!$D$52:$D$58,MIN(MATCH(DATOS!$C$27,TABLAS!$B$52:$B$58,0)+2,7)),1))*INDEX(TABLAS!$D$52:$D$58,MIN(MATCH(DATOS!$C$27,TABLAS!$B$52:$B$58,0)+2,7))>=4/3*IF(BC10<=0,0,IF((1-2*BC10*1E5/(DATOS!$C$58*DATOS!$C$19*BN10^2*DATOS!$C$48))<0,-1,IF((1-SQRT((1-2*BC10*1E5/(DATOS!$C$58*DATOS!$C$19*BN10^2*DATOS!$C$48))))*DATOS!$C$48*DATOS!$C$19*BN10/DATOS!$C$40>DATOS!$C$82*DATOS!$C$19*BN10,-1,(1-SQRT((1-2*BC10*1E5/(DATOS!$C$58*DATOS!$C$19*BN10^2*DATOS!$C$48))))*DATOS!$C$48*DATOS!$C$19*BN10/DATOS!$C$40)))-0.0001,MAX(DATOS!$C$29,CEILING(BO10/INDEX(TABLAS!$D$52:$D$58,MIN(MATCH(DATOS!$C$27,TABLAS!$B$52:$B$58,0)+2,7)),1)),MAX(MAX(DATOS!$C$29,CEILING(BO10/INDEX(TABLAS!$D$52:$D$58,MIN(MATCH(DATOS!$C$27,TABLAS!$B$52:$B$58,0)+2,7)),1)),2))<=MIN(DATOS!$C$28,INT(((DATOS!$C$13-2*S10-2*IF(DATOS!$C$25=0,0,INDEX(TABLAS!$C$52:$C$58,MATCH(DATOS!$C$25,TABLAS!$B$52:$B$58,0))))+MAX(DATOS!$C$32,INDEX(TABLAS!$C$52:$C$58,MIN(MATCH(DATOS!$C$27,TABLAS!$B$52:$B$58,0)+2,7))))/(INDEX(TABLAS!$C$52:$C$58,MIN(MATCH(DATOS!$C$27,TABLAS!$B$52:$B$58,0)+2,7))+MAX(DATOS!$C$32,INDEX(TABLAS!$C$52:$C$58,MIN(MATCH(DATOS!$C$27,TABLAS!$B$52:$B$58,0)+2,7))))))),INDEX(TABLAS!$B$52:$B$58,MIN(MATCH(DATOS!$C$27,TABLAS!$B$52:$B$58,0)+2,7)),IF(AND(BO10>=0,IF(MAX(DATOS!$C$29,CEILING(BO10/INDEX(TABLAS!$D$52:$D$58,MIN(MATCH(DATOS!$C$27,TABLAS!$B$52:$B$58,0)+3,7)),1))*INDEX(TABLAS!$D$52:$D$58,MIN(MATCH(DATOS!$C$27,TABLAS!$B$52:$B$58,0)+3,7))>=4/3*IF(BC10<=0,0,IF((1-2*BC10*1E5/(DATOS!$C$58*DATOS!$C$19*BN10^2*DATOS!$C$48))<0,-1,IF((1-SQRT((1-2*BC10*1E5/(DATOS!$C$58*DATOS!$C$19*BN10^2*DATOS!$C$48))))*DATOS!$C$48*DATOS!$C$19*BN10/DATOS!$C$40>DATOS!$C$82*DATOS!$C$19*BN10,-1,(1-SQRT((1-2*BC10*1E5/(DATOS!$C$58*DATOS!$C$19*BN10^2*DATOS!$C$48))))*DATOS!$C$48*DATOS!$C$19*BN10/DATOS!$C$40)))-0.0001,MAX(DATOS!$C$29,CEILING(BO10/INDEX(TABLAS!$D$52:$D$58,MIN(MATCH(DATOS!$C$27,TABLAS!$B$52:$B$58,0)+3,7)),1)),MAX(MAX(DATOS!$C$29,CEILING(BO10/INDEX(TABLAS!$D$52:$D$58,MIN(MATCH(DATOS!$C$27,TABLAS!$B$52:$B$58,0)+3,7)),1)),2))<=MIN(DATOS!$C$28,INT(((DATOS!$C$13-2*S10-2*IF(DATOS!$C$25=0,0,INDEX(TABLAS!$C$52:$C$58,MATCH(DATOS!$C$25,TABLAS!$B$52:$B$58,0))))+MAX(DATOS!$C$32,INDEX(TABLAS!$C$52:$C$58,MIN(MATCH(DATOS!$C$27,TABLAS!$B$52:$B$58,0)+3,7))))/(INDEX(TABLAS!$C$52:$C$58,MIN(MATCH(DATOS!$C$27,TABLAS!$B$52:$B$58,0)+3,7))+MAX(DATOS!$C$32,INDEX(TABLAS!$C$52:$C$58,MIN(MATCH(DATOS!$C$27,TABLAS!$B$52:$B$58,0)+3,7))))))),INDEX(TABLAS!$B$52:$B$58,MIN(MATCH(DATOS!$C$27,TABLAS!$B$52:$B$58,0)+3,7)),IF(AND(BO10>=0,IF(MAX(DATOS!$C$29,CEILING(BO10/INDEX(TABLAS!$D$52:$D$58,MIN(MATCH(DATOS!$C$27,TABLAS!$B$52:$B$58,0)+4,7)),1))*INDEX(TABLAS!$D$52:$D$58,MIN(MATCH(DATOS!$C$27,TABLAS!$B$52:$B$58,0)+4,7))>=4/3*IF(BC10<=0,0,IF((1-2*BC10*1E5/(DATOS!$C$58*DATOS!$C$19*BN10^2*DATOS!$C$48))<0,-1,IF((1-SQRT((1-2*BC10*1E5/(DATOS!$C$58*DATOS!$C$19*BN10^2*DATOS!$C$48))))*DATOS!$C$48*DATOS!$C$19*BN10/DATOS!$C$40>DATOS!$C$82*DATOS!$C$19*BN10,-1,(1-SQRT((1-2*BC10*1E5/(DATOS!$C$58*DATOS!$C$19*BN10^2*DATOS!$C$48))))*DATOS!$C$48*DATOS!$C$19*BN10/DATOS!$C$40)))-0.0001,MAX(DATOS!$C$29,CEILING(BO10/INDEX(TABLAS!$D$52:$D$58,MIN(MATCH(DATOS!$C$27,TABLAS!$B$52:$B$58,0)+4,7)),1)),MAX(MAX(DATOS!$C$29,CEILING(BO10/INDEX(TABLAS!$D$52:$D$58,MIN(MATCH(DATOS!$C$27,TABLAS!$B$52:$B$58,0)+4,7)),1)),2))<=MIN(DATOS!$C$28,INT(((DATOS!$C$13-2*S10-2*IF(DATOS!$C$25=0,0,INDEX(TABLAS!$C$52:$C$58,MATCH(DATOS!$C$25,TABLAS!$B$52:$B$58,0))))+MAX(DATOS!$C$32,INDEX(TABLAS!$C$52:$C$58,MIN(MATCH(DATOS!$C$27,TABLAS!$B$52:$B$58,0)+4,7))))/(INDEX(TABLAS!$C$52:$C$58,MIN(MATCH(DATOS!$C$27,TABLAS!$B$52:$B$58,0)+4,7))+MAX(DATOS!$C$32,INDEX(TABLAS!$C$52:$C$58,MIN(MATCH(DATOS!$C$27,TABLAS!$B$52:$B$58,0)+4,7))))))),INDEX(TABLAS!$B$52:$B$58,MIN(MATCH(DATOS!$C$27,TABLAS!$B$52:$B$58,0)+4,7)),INDEX(TABLAS!$B$52:$B$58,7)))))) -> 4 | BQ10: =IF(D10="HUECO",0,IF(BO10<0,0,IF(MAX(DATOS!$C$29,CEILING(MAX(BO10,0)/INDEX(TABLAS!$D$52:$D$58,MATCH(BP10,TABLAS!$B$52:$B$58,0)),1))*INDEX(TABLAS!$D$52:$D$58,MATCH(BP10,TABLAS!$B$52:$B$58,0))>=4/3*IF(BC10<=0,0,IF((1-2*BC10*1E5/(DATOS!$C$58*DATOS!$C$19*BN10^2*DATOS!$C$48))<0,-1,IF((1-SQRT((1-2*BC10*1E5/(DATOS!$C$58*DATOS!$C$19*BN10^2*DATOS!$C$48))))*DATOS!$C$48*DATOS!$C$19*BN10/DATOS!$C$40>DATOS!$C$82*DATOS!$C$19*BN10,-1,(1-SQRT((1-2*BC10*1E5/(DATOS!$C$58*DATOS!$C$19*BN10^2*DATOS!$C$48))))*DATOS!$C$48*DATOS!$C$19*BN10/DATOS!$C$40)))-0.0001,MAX(DATOS!$C$29,CEILING(MAX(BO10,0)/INDEX(TABLAS!$D$52:$D$58,MATCH(BP10,TABLAS!$B$52:$B$58,0)),1)),MAX(MAX(DATOS!$C$29,CEILING(MAX(BO10,0)/INDEX(TABLAS!$D$52:$D$58,MATCH(BP10,TABLAS!$B$52:$B$58,0)),1)),2)))) -> 1 | BR10: =((DATOS!$C$15-S10-2*DATOS!$C$35-IF(DATOS!$C$25=0,0,INDEX(TABLAS!$C$52:$C$58,MATCH(DATOS!$C$25,TABLAS!$B$52:$B$58,0)))-INDEX(TABLAS!$C$52:$C$58,MATCH(BP10,TABLAS!$B$52:$B$58,0))/2)-IF(AND((DATOS!$C$15-S10-2*DATOS!$C$35-IF(DATOS!$C$25=0,0,INDEX(TABLAS!$C$52:$C$58,MATCH(DATOS!$C$25,TABLAS!$B$52:$B$58,0)))-INDEX(TABLAS!$C$52:$C$58,MATCH(BP10,TABLAS!$B$52:$B$58,0))/2)<=20,DATOS!$C$18<>"SÍ"),2,0)) -> 19.389 | BS10: =IF(BQ10=0,0,DATOS!$C$58*BQ10*INDEX(TABLAS!$D$52:$D$58,MATCH(BP10,TABLAS!$B$52:$B$58,0))*DATOS!$C$40*(BR10-BQ10*INDEX(TABLAS!$D$52:$D$58,MATCH(BP10,TABLAS!$B$52:$B$58,0))*DATOS!$C$40/(DATOS!$C$48*DATOS!$C$19)/2)/1E5) -> 0.87053798 | BT10: =IF(BO10<0,9.99,IF(BS10>0,BC10/BS10,0)) -> 0.50631872 | BU10: =IF(BQ10=0,"—",0.003*(BR10-(BQ10*INDEX(TABLAS!$D$52:$D$58,MATCH(BP10,TABLAS!$B$52:$B$58,0))*DATOS!$C$40/(DATOS!$C$48*DATOS!$C$19)/DATOS!$C$49))/(BQ10*INDEX(TABLAS!$D$52:$D$58,MATCH(BP10,TABLAS!$B$52:$B$58,0))*DATOS!$C$40/(DATOS!$C$48*DATOS!$C$19)/DATOS!$C$49)) -> 0.016697065 | BV10: =(DATOS!$C$15-R10-IF(DATOS!$C$25=0,0,INDEX(TABLAS!$C$52:$C$58,MATCH(DATOS!$C$25,TABLAS!$B$52:$B$58,0)))-INDEX(TABLAS!$C$52:$C$58,MATCH(DATOS!$C$26,TABLAS!$B$52:$B$58,0))-INDEX(TABLAS!$C$52:$C$58,MATCH(DATOS!$C$26,TABLAS!$B$52:$B$58,0))/2) -> 19.095 | BW10: =IF(D10="HUECO",0,IF(IF(BD10<=0,0,IF((1-2*BD10*1E5/(DATOS!$C$58*Q10*BV10^2*DATOS!$C$48))<0,-1,IF((1-SQRT((1-2*BD10*1E5/(DATOS!$C$58*Q10*BV10^2*DATOS!$C$48))))*DATOS!$C$48*Q10*BV10/DATOS!$C$40>DATOS!$C$82*Q10*BV10,-1,(1-SQRT((1-2*BD10*1E5/(DATOS!$C$58*Q10*BV10^2*DATOS!$C$48))))*DATOS!$C$48*Q10*BV10/DATOS!$C$40)))<0,-1,MAX(IF(BD10<=0,0,IF((1-2*BD10*1E5/(DATOS!$C$58*Q10*BV10^2*DATOS!$C$48))<0,-1,IF((1-SQRT((1-2*BD10*1E5/(DATOS!$C$58*Q10*BV10^2*DATOS!$C$48))))*DATOS!$C$48*Q10*BV10/DATOS!$C$40>DATOS!$C$82*Q10*BV10,-1,(1-SQRT((1-2*BD10*1E5/(DATOS!$C$58*Q10*BV10^2*DATOS!$C$48))))*DATOS!$C$48*Q10*BV10/DATOS!$C$40))),MIN(DATOS!$C$83*DATOS!$C$13*BV10,4/3*IF(BD10<=0,0,IF((1-2*BD10*1E5/(DATOS!$C$58*Q10*BV10^2*DATOS!$C$48))<0,-1,IF((1-SQRT((1-2*BD10*1E5/(DATOS!$C$58*Q10*BV10^2*DATOS!$C$48))))*DATOS!$C$48*Q10*BV10/DATOS!$C$40>DATOS!$C$82*Q10*BV10,-1,(1-SQRT((1-2*BD10*1E5/(DATOS!$C$58*Q10*BV10^2*DATOS!$C$48))))*DATOS!$C$48*Q10*BV10/DATOS!$C$40))))))) -> 0.29636932 | BX10: =IF(AND(BW10>=0,IF(MAX(DATOS!$C$29,CEILING(BW10/INDEX(TABLAS!$D$52:$D$58,MIN(MATCH(DATOS!$C$26,TABLAS!$B$52:$B$58,0)+0,7)),1))*INDEX(TABLAS!$D$52:$D$58,MIN(MATCH(DATOS!$C$26,TABLAS!$B$52:$B$58,0)+0,7))>=4/3*IF(BD10<=0,0,IF((1-2*BD10*1E5/(DATOS!$C$58*Q10*BV10^2*DATOS!$C$48))<0,-1,IF((1-SQRT((1-2*BD10*1E5/(DATOS!$C$58*Q10*BV10^2*DATOS!$C$48))))*DATOS!$C$48*Q10*BV10/DATOS!$C$40>DATOS!$C$82*Q10*BV10,-1,(1-SQRT((1-2*BD10*1E5/(DATOS!$C$58*Q10*BV10^2*DATOS!$C$48))))*DATOS!$C$48*Q10*BV10/DATOS!$C$40)))-0.0001,MAX(DATOS!$C$29,CEILING(BW10/INDEX(TABLAS!$D$52:$D$58,MIN(MATCH(DATOS!$C$26,TABLAS!$B$52:$B$58,0)+0,7)),1)),MAX(MAX(DATOS!$C$29,CEILING(BW10/INDEX(TABLAS!$D$52:$D$58,MIN(MATCH(DATOS!$C$26,TABLAS!$B$52:$B$58,0)+0,7)),1)),2))<=MIN(DATOS!$C$28,INT(((DATOS!$C$13-2*R10-2*IF(DATOS!$C$25=0,0,INDEX(TABLAS!$C$52:$C$58,MATCH(DATOS!$C$25,TABLAS!$B$52:$B$58,0))))+MAX(DATOS!$C$32,INDEX(TABLAS!$C$52:$C$58,MIN(MATCH(DATOS!$C$26,TABLAS!$B$52:$B$58,0)+0,7))))/(INDEX(TABLAS!$C$52:$C$58,MIN(MATCH(DATOS!$C$26,TABLAS!$B$52:$B$58,0)+0,7))+MAX(DATOS!$C$32,INDEX(TABLAS!$C$52:$C$58,MIN(MATCH(DATOS!$C$26,TABLAS!$B$52:$B$58,0)+0,7))))))),INDEX(TABLAS!$B$52:$B$58,MIN(MATCH(DATOS!$C$26,TABLAS!$B$52:$B$58,0)+0,7)),IF(AND(BW10>=0,IF(MAX(DATOS!$C$29,CEILING(BW10/INDEX(TABLAS!$D$52:$D$58,MIN(MATCH(DATOS!$C$26,TABLAS!$B$52:$B$58,0)+1,7)),1))*INDEX(TABLAS!$D$52:$D$58,MIN(MATCH(DATOS!$C$26,TABLAS!$B$52:$B$58,0)+1,7))>=4/3*IF(BD10<=0,0,IF((1-2*BD10*1E5/(DATOS!$C$58*Q10*BV10^2*DATOS!$C$48))<0,-1,IF((1-SQRT((1-2*BD10*1E5/(DATOS!$C$58*Q10*BV10^2*DATOS!$C$48))))*DATOS!$C$48*Q10*BV10/DATOS!$C$40>DATOS!$C$82*Q10*BV10,-1,(1-SQRT((1-2*BD10*1E5/(DATOS!$C$58*Q10*BV10^2*DATOS!$C$48))))*DATOS!$C$48*Q10*BV10/DATOS!$C$40)))-0.0001,MAX(DATOS!$C$29,CEILING(BW10/INDEX(TABLAS!$D$52:$D$58,MIN(MATCH(DATOS!$C$26,TABLAS!$B$52:$B$58,0)+1,7)),1)),MAX(MAX(DATOS!$C$29,CEILING(BW10/INDEX(TABLAS!$D$52:$D$58,MIN(MATCH(DATOS!$C$26,TABLAS!$B$52:$B$58,0)+1,7)),1)),2))<=MIN(DATOS!$C$28,INT(((DATOS!$C$13-2*R10-2*IF(DATOS!$C$25=0,0,INDEX(TABLAS!$C$52:$C$58,MATCH(DATOS!$C$25,TABLAS!$B$52:$B$58,0))))+MAX(DATOS!$C$32,INDEX(TABLAS!$C$52:$C$58,MIN(MATCH(DATOS!$C$26,TABLAS!$B$52:$B$58,0)+1,7))))/(INDEX(TABLAS!$C$52:$C$58,MIN(MATCH(DATOS!$C$26,TABLAS!$B$52:$B$58,0)+1,7))+MAX(DATOS!$C$32,INDEX(TABLAS!$C$52:$C$58,MIN(MATCH(DATOS!$C$26,TABLAS!$B$52:$B$58,0)+1,7))))))),INDEX(TABLAS!$B$52:$B$58,MIN(MATCH(DATOS!$C$26,TABLAS!$B$52:$B$58,0)+1,7)),IF(AND(BW10>=0,IF(MAX(DATOS!$C$29,CEILING(BW10/INDEX(TABLAS!$D$52:$D$58,MIN(MATCH(DATOS!$C$26,TABLAS!$B$52:$B$58,0)+2,7)),1))*INDEX(TABLAS!$D$52:$D$58,MIN(MATCH(DATOS!$C$26,TABLAS!$B$52:$B$58,0)+2,7))>=4/3*IF(BD10<=0,0,IF((1-2*BD10*1E5/(DATOS!$C$58*Q10*BV10^2*DATOS!$C$48))<0,-1,IF((1-SQRT((1-2*BD10*1E5/(DATOS!$C$58*Q10*BV10^2*DATOS!$C$48))))*DATOS!$C$48*Q10*BV10/DATOS!$C$40>DATOS!$C$82*Q10*BV10,-1,(1-SQRT((1-2*BD10*1E5/(DATOS!$C$58*Q10*BV10^2*DATOS!$C$48))))*DATOS!$C$48*Q10*BV10/DATOS!$C$40)))-0.0001,MAX(DATOS!$C$29,CEILING(BW10/INDEX(TABLAS!$D$52:$D$58,MIN(MATCH(DATOS!$C$26,TABLAS!$B$52:$B$58,0)+2,7)),1)),MAX(MAX(DATOS!$C$29,CEILING(BW10/INDEX(TABLAS!$D$52:$D$58,MIN(MATCH(DATOS!$C$26,TABLAS!$B$52:$B$58,0)+2,7)),1)),2))<=MIN(DATOS!$C$28,INT(((DATOS!$C$13-2*R10-2*IF(DATOS!$C$25=0,0,INDEX(TABLAS!$C$52:$C$58,MATCH(DATOS!$C$25,TABLAS!$B$52:$B$58,0))))+MAX(DATOS!$C$32,INDEX(TABLAS!$C$52:$C$58,MIN(MATCH(DATOS!$C$26,TABLAS!$B$52:$B$58,0)+2,7))))/(INDEX(TABLAS!$C$52:$C$58,MIN(MATCH(DATOS!$C$26,TABLAS!$B$52:$B$58,0)+2,7))+MAX(DATOS!$C$32,INDEX(TABLAS!$C$52:$C$58,MIN(MATCH(DATOS!$C$26,TABLAS!$B$52:$B$58,0)+2,7))))))),INDEX(TABLAS!$B$52:$B$58,MIN(MATCH(DATOS!$C$26,TABLAS!$B$52:$B$58,0)+2,7)),IF(AND(BW10>=0,IF(MAX(DATOS!$C$29,CEILING(BW10/INDEX(TABLAS!$D$52:$D$58,MIN(MATCH(DATOS!$C$26,TABLAS!$B$52:$B$58,0)+3,7)),1))*INDEX(TABLAS!$D$52:$D$58,MIN(MATCH(DATOS!$C$26,TABLAS!$B$52:$B$58,0)+3,7))>=4/3*IF(BD10<=0,0,IF((1-2*BD10*1E5/(DATOS!$C$58*Q10*BV10^2*DATOS!$C$48))<0,-1,IF((1-SQRT((1-2*BD10*1E5/(DATOS!$C$58*Q10*BV10^2*DATOS!$C$48))))*DATOS!$C$48*Q10*BV10/DATOS!$C$40>DATOS!$C$82*Q10*BV10,-1,(1-SQRT((1-2*BD10*1E5/(DATOS!$C$58*Q10*BV10^2*DATOS!$C$48))))*DATOS!$C$48*Q10*BV10/DATOS!$C$40)))-0.0001,MAX(DATOS!$C$29,CEILING(BW10/INDEX(TABLAS!$D$52:$D$58,MIN(MATCH(DATOS!$C$26,TABLAS!$B$52:$B$58,0)+3,7)),1)),MAX(MAX(DATOS!$C$29,CEILING(BW10/INDEX(TABLAS!$D$52:$D$58,MIN(MATCH(DATOS!$C$26,TABLAS!$B$52:$B$58,0)+3,7)),1)),2))<=MIN(DATOS!$C$28,INT(((DATOS!$C$13-2*R10-2*IF(DATOS!$C$25=0,0,INDEX(TABLAS!$C$52:$C$58,MATCH(DATOS!$C$25,TABLAS!$B$52:$B$58,0))))+MAX(DATOS!$C$32,INDEX(TABLAS!$C$52:$C$58,MIN(MATCH(DATOS!$C$26,TABLAS!$B$52:$B$58,0)+3,7))))/(INDEX(TABLAS!$C$52:$C$58,MIN(MATCH(DATOS!$C$26,TABLAS!$B$52:$B$58,0)+3,7))+MAX(DATOS!$C$32,INDEX(TABLAS!$C$52:$C$58,MIN(MATCH(DATOS!$C$26,TABLAS!$B$52:$B$58,0)+3,7))))))),INDEX(TABLAS!$B$52:$B$58,MIN(MATCH(DATOS!$C$26,TABLAS!$B$52:$B$58,0)+3,7)),IF(AND(BW10>=0,IF(MAX(DATOS!$C$29,CEILING(BW10/INDEX(TABLAS!$D$52:$D$58,MIN(MATCH(DATOS!$C$26,TABLAS!$B$52:$B$58,0)+4,7)),1))*INDEX(TABLAS!$D$52:$D$58,MIN(MATCH(DATOS!$C$26,TABLAS!$B$52:$B$58,0)+4,7))>=4/3*IF(BD10<=0,0,IF((1-2*BD10*1E5/(DATOS!$C$58*Q10*BV10^2*DATOS!$C$48))<0,-1,IF((1-SQRT((1-2*BD10*1E5/(DATOS!$C$58*Q10*BV10^2*DATOS!$C$48))))*DATOS!$C$48*Q10*BV10/DATOS!$C$40>DATOS!$C$82*Q10*BV10,-1,(1-SQRT((1-2*BD10*1E5/(DATOS!$C$58*Q10*BV10^2*DATOS!$C$48))))*DATOS!$C$48*Q10*BV10/DATOS!$C$40)))-0.0001,MAX(DATOS!$C$29,CEILING(BW10/INDEX(TABLAS!$D$52:$D$58,MIN(MATCH(DATOS!$C$26,TABLAS!$B$52:$B$58,0)+4,7)),1)),MAX(MAX(DATOS!$C$29,CEILING(BW10/INDEX(TABLAS!$D$52:$D$58,MIN(MATCH(DATOS!$C$26,TABLAS!$B$52:$B$58,0)+4,7)),1)),2))<=MIN(DATOS!$C$28,INT(((DATOS!$C$13-2*R10-2*IF(DATOS!$C$25=0,0,INDEX(TABLAS!$C$52:$C$58,MATCH(DATOS!$C$25,TABLAS!$B$52:$B$58,0))))+MAX(DATOS!$C$32,INDEX(TABLAS!$C$52:$C$58,MIN(MATCH(DATOS!$C$26,TABLAS!$B$52:$B$58,0)+4,7))))/(INDEX(TABLAS!$C$52:$C$58,MIN(MATCH(DATOS!$C$26,TABLAS!$B$52:$B$58,0)+4,7))+MAX(DATOS!$C$32,INDEX(TABLAS!$C$52:$C$58,MIN(MATCH(DATOS!$C$26,TABLAS!$B$52:$B$58,0)+4,7))))))),INDEX(TABLAS!$B$52:$B$58,MIN(MATCH(DATOS!$C$26,TABLAS!$B$52:$B$58,0)+4,7)),INDEX(TABLAS!$B$52:$B$58,7)))))) -> 4 | BY10: =IF(D10="HUECO",0,IF(BW10<0,0,IF(MAX(DATOS!$C$29,CEILING(MAX(BW10,0)/INDEX(TABLAS!$D$52:$D$58,MATCH(BX10,TABLAS!$B$52:$B$58,0)),1))*INDEX(TABLAS!$D$52:$D$58,MATCH(BX10,TABLAS!$B$52:$B$58,0))>=4/3*IF(BD10<=0,0,IF((1-2*BD10*1E5/(DATOS!$C$58*Q10*BV10^2*DATOS!$C$48))<0,-1,IF((1-SQRT((1-2*BD10*1E5/(DATOS!$C$58*Q10*BV10^2*DATOS!$C$48))))*DATOS!$C$48*Q10*BV10/DATOS!$C$40>DATOS!$C$82*Q10*BV10,-1,(1-SQRT((1-2*BD10*1E5/(DATOS!$C$58*Q10*BV10^2*DATOS!$C$48))))*DATOS!$C$48*Q10*BV10/DATOS!$C$40)))-0.0001,MAX(DATOS!$C$29,CEILING(MAX(BW10,0)/INDEX(TABLAS!$D$52:$D$58,MATCH(BX10,TABLAS!$B$52:$B$58,0)),1)),MAX(MAX(DATOS!$C$29,CEILING(MAX(BW10,0)/INDEX(TABLAS!$D$52:$D$58,MATCH(BX10,TABLAS!$B$52:$B$58,0)),1)),2)))) -> 1 | BZ10: =DATOS!$C$15-R10-IF(DATOS!$C$25=0,0,INDEX(TABLAS!$C$52:$C$58,MATCH(DATOS!$C$25,TABLAS!$B$52:$B$58,0)))-INDEX(TABLAS!$C$52:$C$58,MATCH(BH10,TABLAS!$B$52:$B$58,0))-INDEX(TABLAS!$C$52:$C$58,MATCH(BX10,TABLAS!$B$52:$B$58,0))/2 -> 19.095 | CA10: =IF(BY10=0,0,DATOS!$C$58*BY10*INDEX(TABLAS!$D$52:$D$58,MATCH(BX10,TABLAS!$B$52:$B$58,0))*DATOS!$C$40*(BZ10-BY10*INDEX(TABLAS!$D$52:$D$58,MATCH(BX10,TABLAS!$B$52:$B$58,0))*DATOS!$C$40/(DATOS!$C$48*Q10)/2)/1E5) -> 0.90806738 | CB10: =IF(BW10<0,9.99,IF(CA10>0,BD10/CA10,0)) -> 0.17638986 | CC10: =IF(BY10=0,"—",0.003*(BZ10-(BY10*INDEX(TABLAS!$D$52:$D$58,MATCH(BX10,TABLAS!$B$52:$B$58,0))*DATOS!$C$40/(DATOS!$C$48*Q10)/DATOS!$C$49))/(BY10*INDEX(TABLAS!$D$52:$D$58,MATCH(BX10,TABLAS!$B$52:$B$58,0))*DATOS!$C$40/(DATOS!$C$48*Q10)/DATOS!$C$49)) -> 0.13278875 | CD10: =((DATOS!$C$15-S10-2*DATOS!$C$35-IF(DATOS!$C$25=0,0,INDEX(TABLAS!$C$52:$C$58,MATCH(DATOS!$C$25,TABLAS!$B$52:$B$58,0)))-INDEX(TABLAS!$C$52:$C$58,MATCH(DATOS!$C$27,TABLAS!$B$52:$B$58,0))-INDEX(TABLAS!$C$52:$C$58,MATCH(DATOS!$C$27,TABLAS!$B$52:$B$58,0))/2)-IF(AND((DATOS!$C$15-S10-2*DATOS!$C$35-IF(DATOS!$C$25=0,0,INDEX(TABLAS!$C$52:$C$58,MATCH(DATOS!$C$25,TABLAS!$B$52:$B$58,0)))-INDEX(TABLAS!$C$52:$C$58,MATCH(DATOS!$C$27,TABLAS!$B$52:$B$58,0))-INDEX(TABLAS!$C$52:$C$58,MATCH(DATOS!$C$27,TABLAS!$B$52:$B$58,0))/2)<=20,DATOS!$C$18<>"SÍ"),2,0)) -> 18.119 | CE10: =IF(D10="HUECO",0,IF(IF(BE10<=0,0,IF((1-2*BE10*1E5/(DATOS!$C$58*DATOS!$C$19*CD10^2*DATOS!$C$48))<0,-1,IF((1-SQRT((1-2*BE10*1E5/(DATOS!$C$58*DATOS!$C$19*CD10^2*DATOS!$C$48))))*DATOS!$C$48*DATOS!$C$19*CD10/DATOS!$C$40>DATOS!$C$82*DATOS!$C$19*CD10,-1,(1-SQRT((1-2*BE10*1E5/(DATOS!$C$58*DATOS!$C$19*CD10^2*DATOS!$C$48))))*DATOS!$C$48*DATOS!$C$19*CD10/DATOS!$C$40)))<0,-1,MAX(IF(BE10<=0,0,IF((1-2*BE10*1E5/(DATOS!$C$58*DATOS!$C$19*CD10^2*DATOS!$C$48))<0,-1,IF((1-SQRT((1-2*BE10*1E5/(DATOS!$C$58*DATOS!$C$19*CD10^2*DATOS!$C$48))))*DATOS!$C$48*DATOS!$C$19*CD10/DATOS!$C$40>DATOS!$C$82*DATOS!$C$19*CD10,-1,(1-SQRT((1-2*BE10*1E5/(DATOS!$C$58*DATOS!$C$19*CD10^2*DATOS!$C$48))))*DATOS!$C$48*DATOS!$C$19*CD10/DATOS!$C$40))),MIN(DATOS!$C$83*DATOS!$C$13*CD10,4/3*IF(BE10<=0,0,IF((1-2*BE10*1E5/(DATOS!$C$58*DATOS!$C$19*CD10^2*DATOS!$C$48))<0,-1,IF((1-SQRT((1-2*BE10*1E5/(DATOS!$C$58*DATOS!$C$19*CD10^2*DATOS!$C$48))))*DATOS!$C$48*DATOS!$C$19*CD10/DATOS!$C$40>DATOS!$C$82*DATOS!$C$19*CD10,-1,(1-SQRT((1-2*BE10*1E5/(DATOS!$C$58*DATOS!$C$19*CD10^2*DATOS!$C$48))))*DATOS!$C$48*DATOS!$C$19*CD10/DATOS!$C$40))))))) -> 0.55615259 | CF10: =IF(AND(CE10>=0,IF(MAX(DATOS!$C$29,CEILING(CE10/INDEX(TABLAS!$D$52:$D$58,MIN(MATCH(DATOS!$C$27,TABLAS!$B$52:$B$58,0)+0,7)),1))*INDEX(TABLAS!$D$52:$D$58,MIN(MATCH(DATOS!$C$27,TABLAS!$B$52:$B$58,0)+0,7))>=4/3*IF(BE10<=0,0,IF((1-2*BE10*1E5/(DATOS!$C$58*DATOS!$C$19*CD10^2*DATOS!$C$48))<0,-1,IF((1-SQRT((1-2*BE10*1E5/(DATOS!$C$58*DATOS!$C$19*CD10^2*DATOS!$C$48))))*DATOS!$C$48*DATOS!$C$19*CD10/DATOS!$C$40>DATOS!$C$82*DATOS!$C$19*CD10,-1,(1-SQRT((1-2*BE10*1E5/(DATOS!$C$58*DATOS!$C$19*CD10^2*DATOS!$C$48))))*DATOS!$C$48*DATOS!$C$19*CD10/DATOS!$C$40)))-0.0001,MAX(DATOS!$C$29,CEILING(CE10/INDEX(TABLAS!$D$52:$D$58,MIN(MATCH(DATOS!$C$27,TABLAS!$B$52:$B$58,0)+0,7)),1)),MAX(MAX(DATOS!$C$29,CEILING(CE10/INDEX(TABLAS!$D$52:$D$58,MIN(MATCH(DATOS!$C$27,TABLAS!$B$52:$B$58,0)+0,7)),1)),2))<=MIN(DATOS!$C$28,INT(((DATOS!$C$13-2*S10-2*IF(DATOS!$C$25=0,0,INDEX(TABLAS!$C$52:$C$58,MATCH(DATOS!$C$25,TABLAS!$B$52:$B$58,0))))+MAX(DATOS!$C$32,INDEX(TABLAS!$C$52:$C$58,MIN(MATCH(DATOS!$C$27,TABLAS!$B$52:$B$58,0)+0,7))))/(INDEX(TABLAS!$C$52:$C$58,MIN(MATCH(DATOS!$C$27,TABLAS!$B$52:$B$58,0)+0,7))+MAX(DATOS!$C$32,INDEX(TABLAS!$C$52:$C$58,MIN(MATCH(DATOS!$C$27,TABLAS!$B$52:$B$58,0)+0,7))))))),INDEX(TABLAS!$B$52:$B$58,MIN(MATCH(DATOS!$C$27,TABLAS!$B$52:$B$58,0)+0,7)),IF(AND(CE10>=0,IF(MAX(DATOS!$C$29,CEILING(CE10/INDEX(TABLAS!$D$52:$D$58,MIN(MATCH(DATOS!$C$27,TABLAS!$B$52:$B$58,0)+1,7)),1))*INDEX(TABLAS!$D$52:$D$58,MIN(MATCH(DATOS!$C$27,TABLAS!$B$52:$B$58,0)+1,7))>=4/3*IF(BE10<=0,0,IF((1-2*BE10*1E5/(DATOS!$C$58*DATOS!$C$19*CD10^2*DATOS!$C$48))<0,-1,IF((1-SQRT((1-2*BE10*1E5/(DATOS!$C$58*DATOS!$C$19*CD10^2*DATOS!$C$48))))*DATOS!$C$48*DATOS!$C$19*CD10/DATOS!$C$40>DATOS!$C$82*DATOS!$C$19*CD10,-1,(1-SQRT((1-2*BE10*1E5/(DATOS!$C$58*DATOS!$C$19*CD10^2*DATOS!$C$48))))*DATOS!$C$48*DATOS!$C$19*CD10/DATOS!$C$40)))-0.0001,MAX(DATOS!$C$29,CEILING(CE10/INDEX(TABLAS!$D$52:$D$58,MIN(MATCH(DATOS!$C$27,TABLAS!$B$52:$B$58,0)+1,7)),1)),MAX(MAX(DATOS!$C$29,CEILING(CE10/INDEX(TABLAS!$D$52:$D$58,MIN(MATCH(DATOS!$C$27,TABLAS!$B$52:$B$58,0)+1,7)),1)),2))<=MIN(DATOS!$C$28,INT(((DATOS!$C$13-2*S10-2*IF(DATOS!$C$25=0,0,INDEX(TABLAS!$C$52:$C$58,MATCH(DATOS!$C$25,TABLAS!$B$52:$B$58,0))))+MAX(DATOS!$C$32,INDEX(TABLAS!$C$52:$C$58,MIN(MATCH(DATOS!$C$27,TABLAS!$B$52:$B$58,0)+1,7))))/(INDEX(TABLAS!$C$52:$C$58,MIN(MATCH(DATOS!$C$27,TABLAS!$B$52:$B$58,0)+1,7))+MAX(DATOS!$C$32,INDEX(TABLAS!$C$52:$C$58,MIN(MATCH(DATOS!$C$27,TABLAS!$B$52:$B$58,0)+1,7))))))),INDEX(TABLAS!$B$52:$B$58,MIN(MATCH(DATOS!$C$27,TABLAS!$B$52:$B$58,0)+1,7)),IF(AND(CE10>=0,IF(MAX(DATOS!$C$29,CEILING(CE10/INDEX(TABLAS!$D$52:$D$58,MIN(MATCH(DATOS!$C$27,TABLAS!$B$52:$B$58,0)+2,7)),1))*INDEX(TABLAS!$D$52:$D$58,MIN(MATCH(DATOS!$C$27,TABLAS!$B$52:$B$58,0)+2,7))>=4/3*IF(BE10<=0,0,IF((1-2*BE10*1E5/(DATOS!$C$58*DATOS!$C$19*CD10^2*DATOS!$C$48))<0,-1,IF((1-SQRT((1-2*BE10*1E5/(DATOS!$C$58*DATOS!$C$19*CD10^2*DATOS!$C$48))))*DATOS!$C$48*DATOS!$C$19*CD10/DATOS!$C$40>DATOS!$C$82*DATOS!$C$19*CD10,-1,(1-SQRT((1-2*BE10*1E5/(DATOS!$C$58*DATOS!$C$19*CD10^2*DATOS!$C$48))))*DATOS!$C$48*DATOS!$C$19*CD10/DATOS!$C$40)))-0.0001,MAX(DATOS!$C$29,CEILING(CE10/INDEX(TABLAS!$D$52:$D$58,MIN(MATCH(DATOS!$C$27,TABLAS!$B$52:$B$58,0)+2,7)),1)),MAX(MAX(DATOS!$C$29,CEILING(CE10/INDEX(TABLAS!$D$52:$D$58,MIN(MATCH(DATOS!$C$27,TABLAS!$B$52:$B$58,0)+2,7)),1)),2))<=MIN(DATOS!$C$28,INT(((DATOS!$C$13-2*S10-2*IF(DATOS!$C$25=0,0,INDEX(TABLAS!$C$52:$C$58,MATCH(DATOS!$C$25,TABLAS!$B$52:$B$58,0))))+MAX(DATOS!$C$32,INDEX(TABLAS!$C$52:$C$58,MIN(MATCH(DATOS!$C$27,TABLAS!$B$52:$B$58,0)+2,7))))/(INDEX(TABLAS!$C$52:$C$58,MIN(MATCH(DATOS!$C$27,TABLAS!$B$52:$B$58,0)+2,7))+MAX(DATOS!$C$32,INDEX(TABLAS!$C$52:$C$58,MIN(MATCH(DATOS!$C$27,TABLAS!$B$52:$B$58,0)+2,7))))))),INDEX(TABLAS!$B$52:$B$58,MIN(MATCH(DATOS!$C$27,TABLAS!$B$52:$B$58,0)+2,7)),IF(AND(CE10>=0,IF(MAX(DATOS!$C$29,CEILING(CE10/INDEX(TABLAS!$D$52:$D$58,MIN(MATCH(DATOS!$C$27,TABLAS!$B$52:$B$58,0)+3,7)),1))*INDEX(TABLAS!$D$52:$D$58,MIN(MATCH(DATOS!$C$27,TABLAS!$B$52:$B$58,0)+3,7))>=4/3*IF(BE10<=0,0,IF((1-2*BE10*1E5/(DATOS!$C$58*DATOS!$C$19*CD10^2*DATOS!$C$48))<0,-1,IF((1-SQRT((1-2*BE10*1E5/(DATOS!$C$58*DATOS!$C$19*CD10^2*DATOS!$C$48))))*DATOS!$C$48*DATOS!$C$19*CD10/DATOS!$C$40>DATOS!$C$82*DATOS!$C$19*CD10,-1,(1-SQRT((1-2*BE10*1E5/(DATOS!$C$58*DATOS!$C$19*CD10^2*DATOS!$C$48))))*DATOS!$C$48*DATOS!$C$19*CD10/DATOS!$C$40)))-0.0001,MAX(DATOS!$C$29,CEILING(CE10/INDEX(TABLAS!$D$52:$D$58,MIN(MATCH(DATOS!$C$27,TABLAS!$B$52:$B$58,0)+3,7)),1)),MAX(MAX(DATOS!$C$29,CEILING(CE10/INDEX(TABLAS!$D$52:$D$58,MIN(MATCH(DATOS!$C$27,TABLAS!$B$52:$B$58,0)+3,7)),1)),2))<=MIN(DATOS!$C$28,INT(((DATOS!$C$13-2*S10-2*IF(DATOS!$C$25=0,0,INDEX(TABLAS!$C$52:$C$58,MATCH(DATOS!$C$25,TABLAS!$B$52:$B$58,0))))+MAX(DATOS!$C$32,INDEX(TABLAS!$C$52:$C$58,MIN(MATCH(DATOS!$C$27,TABLAS!$B$52:$B$58,0)+3,7))))/(INDEX(TABLAS!$C$52:$C$58,MIN(MATCH(DATOS!$C$27,TABLAS!$B$52:$B$58,0)+3,7))+MAX(DATOS!$C$32,INDEX(TABLAS!$C$52:$C$58,MIN(MATCH(DATOS!$C$27,TABLAS!$B$52:$B$58,0)+3,7))))))),INDEX(TABLAS!$B$52:$B$58,MIN(MATCH(DATOS!$C$27,TABLAS!$B$52:$B$58,0)+3,7)),IF(AND(CE10>=0,IF(MAX(DATOS!$C$29,CEILING(CE10/INDEX(TABLAS!$D$52:$D$58,MIN(MATCH(DATOS!$C$27,TABLAS!$B$52:$B$58,0)+4,7)),1))*INDEX(TABLAS!$D$52:$D$58,MIN(MATCH(DATOS!$C$27,TABLAS!$B$52:$B$58,0)+4,7))>=4/3*IF(BE10<=0,0,IF((1-2*BE10*1E5/(DATOS!$C$58*DATOS!$C$19*CD10^2*DATOS!$C$48))<0,-1,IF((1-SQRT((1-2*BE10*1E5/(DATOS!$C$58*DATOS!$C$19*CD10^2*DATOS!$C$48))))*DATOS!$C$48*DATOS!$C$19*CD10/DATOS!$C$40>DATOS!$C$82*DATOS!$C$19*CD10,-1,(1-SQRT((1-2*BE10*1E5/(DATOS!$C$58*DATOS!$C$19*CD10^2*DATOS!$C$48))))*DATOS!$C$48*DATOS!$C$19*CD10/DATOS!$C$40)))-0.0001,MAX(DATOS!$C$29,CEILING(CE10/INDEX(TABLAS!$D$52:$D$58,MIN(MATCH(DATOS!$C$27,TABLAS!$B$52:$B$58,0)+4,7)),1)),MAX(MAX(DATOS!$C$29,CEILING(CE10/INDEX(TABLAS!$D$52:$D$58,MIN(MATCH(DATOS!$C$27,TABLAS!$B$52:$B$58,0)+4,7)),1)),2))<=MIN(DATOS!$C$28,INT(((DATOS!$C$13-2*S10-2*IF(DATOS!$C$25=0,0,INDEX(TABLAS!$C$52:$C$58,MATCH(DATOS!$C$25,TABLAS!$B$52:$B$58,0))))+MAX(DATOS!$C$32,INDEX(TABLAS!$C$52:$C$58,MIN(MATCH(DATOS!$C$27,TABLAS!$B$52:$B$58,0)+4,7))))/(INDEX(TABLAS!$C$52:$C$58,MIN(MATCH(DATOS!$C$27,TABLAS!$B$52:$B$58,0)+4,7))+MAX(DATOS!$C$32,INDEX(TABLAS!$C$52:$C$58,MIN(MATCH(DATOS!$C$27,TABLAS!$B$52:$B$58,0)+4,7))))))),INDEX(TABLAS!$B$52:$B$58,MIN(MATCH(DATOS!$C$27,TABLAS!$B$52:$B$58,0)+4,7)),INDEX(TABLAS!$B$52:$B$58,7)))))) -> 4 | CG10: =IF(D10="HUECO",0,IF(CE10<0,0,IF(MAX(DATOS!$C$29,CEILING(MAX(CE10,0)/INDEX(TABLAS!$D$52:$D$58,MATCH(CF10,TABLAS!$B$52:$B$58,0)),1))*INDEX(TABLAS!$D$52:$D$58,MATCH(CF10,TABLAS!$B$52:$B$58,0))>=4/3*IF(BE10<=0,0,IF((1-2*BE10*1E5/(DATOS!$C$58*DATOS!$C$19*CD10^2*DATOS!$C$48))<0,-1,IF((1-SQRT((1-2*BE10*1E5/(DATOS!$C$58*DATOS!$C$19*CD10^2*DATOS!$C$48))))*DATOS!$C$48*DATOS!$C$19*CD10/DATOS!$C$40>DATOS!$C$82*DATOS!$C$19*CD10,-1,(1-SQRT((1-2*BE10*1E5/(DATOS!$C$58*DATOS!$C$19*CD10^2*DATOS!$C$48))))*DATOS!$C$48*DATOS!$C$19*CD10/DATOS!$C$40)))-0.0001,MAX(DATOS!$C$29,CEILING(MAX(CE10,0)/INDEX(TABLAS!$D$52:$D$58,MATCH(CF10,TABLAS!$B$52:$B$58,0)),1)),MAX(MAX(DATOS!$C$29,CEILING(MAX(CE10,0)/INDEX(TABLAS!$D$52:$D$58,MATCH(CF10,TABLAS!$B$52:$B$58,0)),1)),2)))) -> 1 | CH10: =((DATOS!$C$15-S10-2*DATOS!$C$35-IF(DATOS!$C$25=0,0,INDEX(TABLAS!$C$52:$C$58,MATCH(DATOS!$C$25,TABLAS!$B$52:$B$58,0)))-INDEX(TABLAS!$C$52:$C$58,MATCH(BP10,TABLAS!$B$52:$B$58,0))-INDEX(TABLAS!$C$52:$C$58,MATCH(CF10,TABLAS!$B$52:$B$58,0))/2)-IF(AND((DATOS!$C$15-S10-2*DATOS!$C$35-IF(DATOS!$C$25=0,0,INDEX(TABLAS!$C$52:$C$58,MATCH(DATOS!$C$25,TABLAS!$B$52:$B$58,0)))-INDEX(TABLAS!$C$52:$C$58,MATCH(BP10,TABLAS!$B$52:$B$58,0))-INDEX(TABLAS!$C$52:$C$58,MATCH(CF10,TABLAS!$B$52:$B$58,0))/2)<=20,DATOS!$C$18<>"SÍ"),2,0)) -> 18.119 | CI10: =IF(CG10=0,0,DATOS!$C$58*CG10*INDEX(TABLAS!$D$52:$D$58,MATCH(CF10,TABLAS!$B$52:$B$58,0))*DATOS!$C$40*(CH10-CG10*INDEX(TABLAS!$D$52:$D$58,MATCH(CF10,TABLAS!$B$52:$B$58,0))*DATOS!$C$40/(DATOS!$C$48*DATOS!$C$19)/2)/1E5) -> 0.80957036 | CJ10: =IF(CE10<0,9.99,IF(CI10>0,BE10/CI10,0)) -> 0.34485167 | CK10: =IF(CG10=0,"—",0.003*(CH10-(CG10*INDEX(TABLAS!$D$52:$D$58,MATCH(CF10,TABLAS!$B$52:$B$58,0))*DATOS!$C$40/(DATOS!$C$48*DATOS!$C$19)/DATOS!$C$49))/(CG10*INDEX(TABLAS!$D$52:$D$58,MATCH(CF10,TABLAS!$B$52:$B$58,0))*DATOS!$C$40/(DATOS!$C$48*DATOS!$C$19)/DATOS!$C$49)) -> 0.015406886 | CL10: =IF(D10="HUECO","—",IF(AND(D10="PERIMETRAL",J10*100>=6*DATOS!$C$11,DATOS!$C$11<=80,DATOS!$C$13>=10,DATOS!$C$15<=3.5*DATOS!$C$13,DATOS!$C$14>=MAX(DATOS!$C$11/13,5)),"SÍ","NO")) -> NO | CM10: =IF(D10="PERIMETRAL",MAX(0,(N10/2-BR10)/100)*(0.95-0.5*L10)*Y10*IF(AND(Z10>0,Z10<4),DATOS!$C$63,1)*DATOS!$C$16/100/1000+AX10,IF(D10="VOLADO",(Y10*MAX(0,N10-BR10)/100+DATOS!$C$55*BA10)*DATOS!$C$16/100/1000,0)) -> 0.52584049 | CN10: =IF(D10="HUECO",0,DATOS!$C$59*2*MIN(1,SQRT(2/(1+0.04*BR10)))*(BQ10*INDEX(TABLAS!$D$52:$D$58,MATCH(BP10,TABLAS!$B$52:$B$58,0))/(DATOS!$C$19*BR10))^(1/3)*SQRT(DATOS!$C$39)*DATOS!$C$19*BR10*IF(CL10="SÍ",DATOS!$C$62,1)/1000) -> 0.8603981 | CO10: =IF(D10="HUECO","—",IF(CM10<=CN10,"CUMPLE",IF(MAX(0,CEILING((IF(D10="VOLADO",(N10-(CN10*1E5/DATOS!$C$16-DATOS!$C$55*BA10)*100/Y10),IF(CN10<=AX10,N10,N10/2-(CN10-AX10)/MAX(CM10-AX10,1E-9)*(N10/2-BR10)))-IF(INT((J10*100-DATOS!$C$17+DATOS!$C$13)/DATOS!$C$16)>0,(J10*100-DATOS!$C$17-(INT((J10*100-DATOS!$C$17+DATOS!$C$13)/DATOS!$C$16)*DATOS!$C$11+(INT((J10*100-DATOS!$C$17+DATOS!$C$13)/DATOS!$C$16)-1)*DATOS!$C$13))/2,J10*100/2))/DATOS!$C$16,1))<=0,"CUMPLE (basta el macizo de orilla)","MACIZAR "&MAX(0,CEILING((IF(D10="VOLADO",(N10-(CN10*1E5/DATOS!$C$16-DATOS!$C$55*BA10)*100/Y10),IF(CN10<=AX10,N10,N10/2-(CN10-AX10)/MAX(CM10-AX10,1E-9)*(N10/2-BR10)))-IF(INT((J10*100-DATOS!$C$17+DATOS!$C$13)/DATOS!$C$16)>0,(J10*100-DATOS!$C$17-(INT((J10*100-DATOS!$C$17+DATOS!$C$13)/DATOS!$C$16)*DATOS!$C$11+(INT((J10*100-DATOS!$C$17+DATOS!$C$13)/DATOS!$C$16)-1)*DATOS!$C$13))/2,J10*100/2))/DATOS!$C$16,1))&" hilera(s)"))) -> CUMPLE | CP10: =IF(D10="PERIMETRAL",((PRINCIPALES!$N$10*PRINCIPALES!$O$10^3/12/(3.025*100*IF(APOYOS!$G$33="CONTINUO",1,0.5)*DATOS!$C$77^3/12))+0+99+(PRINCIPALES!$N$29*PRINCIPALES!$O$29^3/12/(4.327*100*IF(APOYOS!$G$36="CONTINUO",1,0.5)*DATOS!$C$77^3/12)))/4,0) -> 25.671496 | CQ10: =IF(D10="PERIMETRAL",IF(CP10>2,MAX(9,O10*(0.8+DATOS!$C$40/14000)/(36+9*(O10/MAX(N10,1)))),IF(CP10>0.2,MAX(13,O10*(0.8+DATOS!$C$40/14000)/(36+5*(O10/MAX(N10,1))*(CP10-0.2))),MAX(13,O10/IF(Z10>0,30,33))))*IF(AND(CP10>0.2,OR(AND((APOYOS!$G$33="DISCONTINUO"),(PRINCIPALES!$N$10*PRINCIPALES!$O$10^3/12/(3.025*100*IF(APOYOS!$G$33="CONTINUO",1,0.5)*DATOS!$C$77^3/12))<0.8),AND((APOYOS!$G$34="DISCONTINUO"),0<0.8),AND((APOYOS!$G$35="DISCONTINUO"),99<0.8),AND((APOYOS!$G$36="DISCONTINUO"),(PRINCIPALES!$N$29*PRINCIPALES!$O$29^3/12/(4.327*100*IF(APOYOS!$G$36="CONTINUO",1,0.5)*DATOS!$C$77^3/12))<0.8))),1.1,1),IF(D10="VOLADO",MAX(25,J10*100/8),0)) -> 9.3624507 | CR10: =IF(D10="VOLADO",DATOS!$C$15,DATOS!$C$77) -> 16.723256 | CS10: =IF(D10="HUECO","—",IF(CR10>=CQ10,"CUMPLE",IF(D10="VOLADO","NO CUMPLE","CALCULAR FLECHA"))) -> CUMPLE | CT10: =IF(D10="HUECO","—",IF(DATOS!$C$14>=IF(IF(D10="VOLADO",J10,K10)>=6,6,5),"CUMPLE","CAPA ≥ 6 cm")) -> CUMPLE | CU10: =IF(D10="HUECO",0,IF(((4*((AL10*Y10*J10^2*1E-4*DATOS!$C$16/100/1000)+((MAX(AH10,AJ10)*Y10*J10^2*1E-4*DATOS!$C$16/100/1000)+(IF(AND(AH10>0,AJ10>0),MIN(AH10,AJ10),MAX(AH10,AJ10))*Y10*J10^2*1E-4*DATOS!$C$16/100/1000))/2)+BC10-(IF(AND(AH10>0,AJ10>0),MIN(AH10,AJ10),MAX(AH10,AJ10))*Y10*J10^2*1E-4*DATOS!$C$16/100/1000))^2-16*((AL10*Y10*J10^2*1E-4*DATOS!$C$16/100/1000)+((MAX(AH10,AJ10)*Y10*J10^2*1E-4*DATOS!$C$16/100/1000)+(IF(AND(AH10>0,AJ10>0),MIN(AH10,AJ10),MAX(AH10,AJ10))*Y10*J10^2*1E-4*DATOS!$C$16/100/1000))/2)*BC10)<0,CEILING(N10,5),CEILING(MAX(N10*((4*((AL10*Y10*J10^2*1E-4*DATOS!$C$16/100/1000)+((MAX(AH10,AJ10)*Y10*J10^2*1E-4*DATOS!$C$16/100/1000)+(IF(AND(AH10>0,AJ10>0),MIN(AH10,AJ10),MAX(AH10,AJ10))*Y10*J10^2*1E-4*DATOS!$C$16/100/1000))/2)+BC10-(IF(AND(AH10>0,AJ10>0),MIN(AH10,AJ10),MAX(AH10,AJ10))*Y10*J10^2*1E-4*DATOS!$C$16/100/1000))-SQRT(MAX(0,((4*((AL10*Y10*J10^2*1E-4*DATOS!$C$16/100/1000)+((MAX(AH10,AJ10)*Y10*J10^2*1E-4*DATOS!$C$16/100/1000)+(IF(AND(AH10>0,AJ10>0),MIN(AH10,AJ10),MAX(AH10,AJ10))*Y10*J10^2*1E-4*DATOS!$C$16/100/1000))/2)+BC10-(IF(AND(AH10>0,AJ10>0),MIN(AH10,AJ10),MAX(AH10,AJ10))*Y10*J10^2*1E-4*DATOS!$C$16/100/1000))^2-16*((AL10*Y10*J10^2*1E-4*DATOS!$C$16/100/1000)+((MAX(AH10,AJ10)*Y10*J10^2*1E-4*DATOS!$C$16/100/1000)+(IF(AND(AH10>0,AJ10>0),MIN(AH10,AJ10),MAX(AH10,AJ10))*Y10*J10^2*1E-4*DATOS!$C$16/100/1000))/2)*BC10))))/(8*MAX(((AL10*Y10*J10^2*1E-4*DATOS!$C$16/100/1000)+((MAX(AH10,AJ10)*Y10*J10^2*1E-4*DATOS!$C$16/100/1000)+(IF(AND(AH10>0,AJ10>0),MIN(AH10,AJ10),MAX(AH10,AJ10))*Y10*J10^2*1E-4*DATOS!$C$16/100/1000))/2),1E-9))+MAX(BR10,12*INDEX(TABLAS!$C$52:$C$58,MATCH(BP10,TABLAS!$B$52:$B$58,0)),N10/16),IF(OR(S10<INDEX(TABLAS!$C$52:$C$58,MATCH(BP10,TABLAS!$B$52:$B$58,0)),AND(BQ10>=2,(DATOS!$C$13-2*S10-2*IF(DATOS!$C$25=0,0,INDEX(TABLAS!$C$52:$C$58,MATCH(DATOS!$C$25,TABLAS!$B$52:$B$58,0)))-BQ10*INDEX(TABLAS!$C$52:$C$58,MATCH(BP10,TABLAS!$B$52:$B$58,0)))/MAX(BQ10-1,1)<2*INDEX(TABLAS!$C$52:$C$58,MATCH(BP10,TABLAS!$B$52:$B$58,0)))),INDEX(TABLAS!$I$52:$I$58,MATCH(BP10,TABLAS!$B$52:$B$58,0)),INDEX(TABLAS!$F$52:$F$58,MATCH(BP10,TABLAS!$B$52:$B$58,0)))),5))) -> 85 | CV10: =IF(D10="HUECO",0,IF(((4*((AM10*Y10*J10^2*1E-4*DATOS!$C$16/100/1000)+((MAX(AI10,AK10)*Y10*J10^2*1E-4*DATOS!$C$16/100/1000)+(IF(AND(AI10>0,AK10>0),MIN(AI10,AK10),MAX(AI10,AK10))*Y10*J10^2*1E-4*DATOS!$C$16/100/1000))/2)+BE10-(IF(AND(AI10>0,AK10>0),MIN(AI10,AK10),MAX(AI10,AK10))*Y10*J10^2*1E-4*DATOS!$C$16/100/1000))^2-16*((AM10*Y10*J10^2*1E-4*DATOS!$C$16/100/1000)+((MAX(AI10,AK10)*Y10*J10^2*1E-4*DATOS!$C$16/100/1000)+(IF(AND(AI10>0,AK10>0),MIN(AI10,AK10),MAX(AI10,AK10))*Y10*J10^2*1E-4*DATOS!$C$16/100/1000))/2)*BE10)<0,CEILING(O10,5),CEILING(MAX(O10*((4*((AM10*Y10*J10^2*1E-4*DATOS!$C$16/100/1000)+((MAX(AI10,AK10)*Y10*J10^2*1E-4*DATOS!$C$16/100/1000)+(IF(AND(AI10>0,AK10>0),MIN(AI10,AK10),MAX(AI10,AK10))*Y10*J10^2*1E-4*DATOS!$C$16/100/1000))/2)+BE10-(IF(AND(AI10>0,AK10>0),MIN(AI10,AK10),MAX(AI10,AK10))*Y10*J10^2*1E-4*DATOS!$C$16/100/1000))-SQRT(MAX(0,((4*((AM10*Y10*J10^2*1E-4*DATOS!$C$16/100/1000)+((MAX(AI10,AK10)*Y10*J10^2*1E-4*DATOS!$C$16/100/1000)+(IF(AND(AI10>0,AK10>0),MIN(AI10,AK10),MAX(AI10,AK10))*Y10*J10^2*1E-4*DATOS!$C$16/100/1000))/2)+BE10-(IF(AND(AI10>0,AK10>0),MIN(AI10,AK10),MAX(AI10,AK10))*Y10*J10^2*1E-4*DATOS!$C$16/100/1000))^2-16*((AM10*Y10*J10^2*1E-4*DATOS!$C$16/100/1000)+((MAX(AI10,AK10)*Y10*J10^2*1E-4*DATOS!$C$16/100/1000)+(IF(AND(AI10>0,AK10>0),MIN(AI10,AK10),MAX(AI10,AK10))*Y10*J10^2*1E-4*DATOS!$C$16/100/1000))/2)*BE10))))/(8*MAX(((AM10*Y10*J10^2*1E-4*DATOS!$C$16/100/1000)+((MAX(AI10,AK10)*Y10*J10^2*1E-4*DATOS!$C$16/100/1000)+(IF(AND(AI10>0,AK10>0),MIN(AI10,AK10),MAX(AI10,AK10))*Y10*J10^2*1E-4*DATOS!$C$16/100/1000))/2),1E-9))+MAX(CH10,12*INDEX(TABLAS!$C$52:$C$58,MATCH(CF10,TABLAS!$B$52:$B$58,0)),O10/16),IF(OR(S10<INDEX(TABLAS!$C$52:$C$58,MATCH(CF10,TABLAS!$B$52:$B$58,0)),AND(CG10>=2,(DATOS!$C$13-2*S10-2*IF(DATOS!$C$25=0,0,INDEX(TABLAS!$C$52:$C$58,MATCH(DATOS!$C$25,TABLAS!$B$52:$B$58,0)))-CG10*INDEX(TABLAS!$C$52:$C$58,MATCH(CF10,TABLAS!$B$52:$B$58,0)))/MAX(CG10-1,1)<2*INDEX(TABLAS!$C$52:$C$58,MATCH(CF10,TABLAS!$B$52:$B$58,0)))),INDEX(TABLAS!$I$52:$I$58,MATCH(CF10,TABLAS!$B$52:$B$58,0)),INDEX(TABLAS!$F$52:$F$58,MATCH(CF10,TABLAS!$B$52:$B$58,0)))),5))) -> 120 | CW10: =MAX(0,INT((F10*100-DATOS!$C$17+DATOS!$C$13)/DATOS!$C$16)) -> 6 | CX10: =MAX(0,INT((G10*100-DATOS!$C$17+DATOS!$C$13)/DATOS!$C$16)) -> 4 | CY10: =IF(COUNTIFS(TRIB!$C$6:$C$255,B10,TRIB!$K$6:$K$255,"NO CUMPLE*")+COUNTIFS(TRIB!$C$6:$C$255,B10,TRIB!$K$6:$K$255,"SIN APOYO*")>0,"VER PRINCIPALES",IF((APOYOS!$F$33="LIBRE")+(APOYOS!$F$34="LIBRE")+(APOYOS!$F$35="LIBRE")+(APOYOS!$F$36="LIBRE")>0,"REVISAR: borde libre","OK")) -> OK | CZ10: =IF(D10="HUECO","HUECO — marco de nervaduras principales",IF(AND(MAX(BL10,BT10,CB10,CJ10)<=1,NOT(OR(BI10>MIN(DATOS!$C$28,INT(((DATOS!$C$13-2*R10-2*IF(DATOS!$C$25=0,0,INDEX(TABLAS!$C$52:$C$58,MATCH(DATOS!$C$25,TABLAS!$B$52:$B$58,0))))+DATOS!$C$32)/(INDEX(TABLAS!$C$52:$C$58,MATCH(BH10,TABLAS!$B$52:$B$58,0))+DATOS!$C$32))),BQ10>MIN(DATOS!$C$28,INT(((DATOS!$C$13-2*S10-2*IF(DATOS!$C$25=0,0,INDEX(TABLAS!$C$52:$C$58,MATCH(DATOS!$C$25,TABLAS!$B$52:$B$58,0))))+DATOS!$C$32)/(INDEX(TABLAS!$C$52:$C$58,MATCH(BP10,TABLAS!$B$52:$B$58,0))+DATOS!$C$32))),BY10>MIN(DATOS!$C$28,INT(((DATOS!$C$13-2*R10-2*IF(DATOS!$C$25=0,0,INDEX(TABLAS!$C$52:$C$58,MATCH(DATOS!$C$25,TABLAS!$B$52:$B$58,0))))+DATOS!$C$32)/(INDEX(TABLAS!$C$52:$C$58,MATCH(BX10,TABLAS!$B$52:$B$58,0))+DATOS!$C$32))),CG10>MIN(DATOS!$C$28,INT(((DATOS!$C$13-2*S10-2*IF(DATOS!$C$25=0,0,INDEX(TABLAS!$C$52:$C$58,MATCH(DATOS!$C$25,TABLAS!$B$52:$B$58,0))))+DATOS!$C$32)/(INDEX(TABLAS!$C$52:$C$58,MATCH(CF10,TABLAS!$B$52:$B$58,0))+DATOS!$C$32))))),NOT(OR(AND(ISNUMBER(BM10),BM10<0.005),AND(ISNUMBER(BU10),BU10<0.005),AND(ISNUMBER(CC10),CC10<0.005),AND(ISNUMBER(CK10),CK10<0.005))),CS10="CUMPLE",CT10="CUMPLE"),IF(CY10="OK",IF(LEFT(CO10,6)="CUMPLE","CUMPLE","CUMPLE — "&CO10)&IF(LEFT(AZ10,5)="FUERA"," · fuera de 3.4.2.1 c)",""),IF(CY10="VER PRINCIPALES","VER PRINCIPALES","REVISAR APOYOS")),IF(AND(MAX(BL10,BT10,CB10,CJ10)<=1,NOT(OR(BI10>MIN(DATOS!$C$28,INT(((DATOS!$C$13-2*R10-2*IF(DATOS!$C$25=0,0,INDEX(TABLAS!$C$52:$C$58,MATCH(DATOS!$C$25,TABLAS!$B$52:$B$58,0))))+DATOS!$C$32)/(INDEX(TABLAS!$C$52:$C$58,MATCH(BH10,TABLAS!$B$52:$B$58,0))+DATOS!$C$32))),BQ10>MIN(DATOS!$C$28,INT(((DATOS!$C$13-2*S10-2*IF(DATOS!$C$25=0,0,INDEX(TABLAS!$C$52:$C$58,MATCH(DATOS!$C$25,TABLAS!$B$52:$B$58,0))))+DATOS!$C$32)/(INDEX(TABLAS!$C$52:$C$58,MATCH(BP10,TABLAS!$B$52:$B$58,0))+DATOS!$C$32))),BY10>MIN(DATOS!$C$28,INT(((DATOS!$C$13-2*R10-2*IF(DATOS!$C$25=0,0,INDEX(TABLAS!$C$52:$C$58,MATCH(DATOS!$C$25,TABLAS!$B$52:$B$58,0))))+DATOS!$C$32)/(INDEX(TABLAS!$C$52:$C$58,MATCH(BX10,TABLAS!$B$52:$B$58,0))+DATOS!$C$32))),CG10>MIN(DATOS!$C$28,INT(((DATOS!$C$13-2*S10-2*IF(DATOS!$C$25=0,0,INDEX(TABLAS!$C$52:$C$58,MATCH(DATOS!$C$25,TABLAS!$B$52:$B$58,0))))+DATOS!$C$32)/(INDEX(TABLAS!$C$52:$C$58,MATCH(CF10,TABLAS!$B$52:$B$58,0))+DATOS!$C$32))))),NOT(OR(AND(ISNUMBER(BM10),BM10<0.005),AND(ISNUMBER(BU10),BU10<0.005),AND(ISNUMBER(CC10),CC10<0.005),AND(ISNUMBER(CK10),CK10<0.005))),CS10="CALCULAR FLECHA"),"REVISAR: calcular flecha (h_eq < h mín.)","NO CUMPLE: "&IF(MAX(BL10,BT10,CB10,CJ10)>1,"flexión ","")&IF(OR(BI10>MIN(DATOS!$C$28,INT(((DATOS!$C$13-2*R10-2*IF(DATOS!$C$25=0,0,INDEX(TABLAS!$C$52:$C$58,MATCH(DATOS!$C$25,TABLAS!$B$52:$B$58,0))))+DATOS!$C$32)/(INDEX(TABLAS!$C$52:$C$58,MATCH(BH10,TABLAS!$B$52:$B$58,0))+DATOS!$C$32))),BQ10>MIN(DATOS!$C$28,INT(((DATOS!$C$13-2*S10-2*IF(DATOS!$C$25=0,0,INDEX(TABLAS!$C$52:$C$58,MATCH(DATOS!$C$25,TABLAS!$B$52:$B$58,0))))+DATOS!$C$32)/(INDEX(TABLAS!$C$52:$C$58,MATCH(BP10,TABLAS!$B$52:$B$58,0))+DATOS!$C$32))),BY10>MIN(DATOS!$C$28,INT(((DATOS!$C$13-2*R10-2*IF(DATOS!$C$25=0,0,INDEX(TABLAS!$C$52:$C$58,MATCH(DATOS!$C$25,TABLAS!$B$52:$B$58,0))))+DATOS!$C$32)/(INDEX(TABLAS!$C$52:$C$58,MATCH(BX10,TABLAS!$B$52:$B$58,0))+DATOS!$C$32))),CG10>MIN(DATOS!$C$28,INT(((DATOS!$C$13-2*S10-2*IF(DATOS!$C$25=0,0,INDEX(TABLAS!$C$52:$C$58,MATCH(DATOS!$C$25,TABLAS!$B$52:$B$58,0))))+DATOS!$C$32)/(INDEX(TABLAS!$C$52:$C$58,MATCH(CF10,TABLAS!$B$52:$B$58,0))+DATOS!$C$32)))),"no caben ","")&IF(OR(AND(ISNUMBER(BM10),BM10<0.005),AND(ISNUMBER(BU10),BU10<0.005),AND(ISNUMBER(CC10),CC10<0.005),AND(ISNUMBER(CK10),CK10<0.005)),"ε_t < 0.005 ","")&IF(CS10="NO CUMPLE","peralte ","")&IF(CT10<>"CUMPLE","capa < 6 cm","")))) -> CUMPLE · fuera de 3.4.2.1 c) | DA10: =IF(AND(D10="PERIMETRAL",MIN(CW10,CX10)=0),"Tablero macizo (no cabe un casetón en el claro corto): no aplica 6.7.8. La resistencia se revisa con una nervadura de 10 cm cada 70 cm y r_np (conservador); "&"como losa maciza lleva además As,mín = 0.0018·Ag en cada dirección cerca de la cara a tensión (6.7.6.1.1, p. 175). ",IF(AND(CL10="NO",D10="PERIMETRAL"),"No cumple 6.7.8.1.4 (a_c = "&DATOS!$C$11&" cm > claro corto/6 = "&TEXT(J10*100/6,"0")&" cm): se diseña como losa apoyada en vigas (6.7.8.1.9): nervaduras con recubrimiento de viga r_np = "&DATOS!$C$22&" cm (Tabla 4.14.16.a), V_cR sin ×1.1 y cortante sin estribos por 5.5.3.8.1 (criterio del Proyectista). Para que cuente como encasetonada: casetón de "&TEXT(FLOOR(MIN(80,J10*100/6),1),"0")&" cm o menor. ",""))&IF(LEFT(AZ10,5)="FUERA","M⁻ del borde común "&AZ10&": difieren más de 50% (3.4.2.1 c); se distribuyen 2/3 del desequilibrio (3.4.3.1) y conviene confirmar los momentos con el modelo. ","")&"Forma de L: se toma el rectángulo envolvente 4.327 × 3.025 (conservador; el claro corto real es 2.425 en la parte izquierda)." -> No cumple 6.7.8.1.4 (a_c = 60 cm > claro corto/6 = 50 cm): se diseña como losa apoyada en vigas (6.7.8.1.9): nervaduras con recubrimiento de viga r_np = 4 cm (Tabla 4.14.16.a), V_cR sin ×1.1 y cortante sin estribos por 5.5.3.8.1 (criterio del Proyectista). Para que cuente como encasetonada: casetón de 50 cm o menor. M⁻ del borde común FUERA con F80001 F80005 F80006: difieren más de 50% (3.4.2.1 c); se distribuyen 2/3 del desequilibrio (3.4.3.1) y conviene confirmar los momentos con el modelo. Forma de L: se toma el rectángulo envolvente 4.327 × 3.025 (conservador; el claro corto real es 2.425 en la parte izquierda).
